Workbook
Name StartingBalance: #REF!

Sheet Resumen
B1: =IFERROR(__xludf.DUMMYFUNCTION("GOOGLEFINANCE((""CURRENCY:CLF/CLP""))"),40825.75) -> 40825.75 | F1: Dolar | G1: =IFERROR(__xludf.DUMMYFUNCTION("GOOGLEFINANCE((""CURRENCY:USDCLP""))"),925.24) -> 925.24
B2: Gastos | H2: Pagos
B3: PPTO | C3: =D9 -> 1955021.9 | D3: =IFERROR(__xludf.DUMMYFUNCTION("SPARKLINE(C3,{""charttype"",""bar"";""max"",max(C3:C4);""color1"",""#AEB7C0""})"),"") | H3: Previsto | I3: =J9 -> 1955021.9 | J3: =IFERROR(__xludf.DUMMYFUNCTION("SPARKLINE(I3,{""charttype"",""bar"";""max"",max(I3:I4);""color1"",""#AEB7C0""})"),"")
B4: Gastado | C4: =E9 -> 1042755.6 | D4: =IFERROR(__xludf.DUMMYFUNCTION("SPARKLINE(C4,{""charttype"",""bar"";""max"",max(C3:C4);""color1"",""#334960""})"),"") | H4: Amex | I4: =IFERROR(__xludf.DUMMYFUNCTION("IMPORTRANGE(""https://docs.google.com/spreadsheets/d/1eg8N2weYKMcWwj9jcJqBX-y0loZRILY9c1SDJETZtoI/edit?pli=1&gid=124507033#gid=124507033&range=O40"",""O40"")"),176719.02083333395) -> 176719.02
B5: Pagado | C5: =K9 -> 0 | D5: =IFERROR(__xludf.DUMMYFUNCTION("SPARKLINE(C5,{""charttype"",""bar"";""max"",max(I3,C5);""color1"",""#334960""})"),"") | H5: Paga Jose | I5: =IFERROR(__xludf.DUMMYFUNCTION("IMPORTRANGE(""https://docs.google.com/spreadsheets/d/1eg8N2weYKMcWwj9jcJqBX-y0loZRILY9c1SDJETZtoI/edit?pli=1&gid=124507033#gid=124507033&range=M42"",""M42"")"),47714.13562500017) -> 47714.136
B7: Gastos | H7: Ingresos
D8: Previsto | E8: Pagado | F8: Difer. | J8: Previsto | K8: Real | L8: Difer. | O8: Por pagar pp
A9: Pagado | B9: Totales | D9: =sum(D10:D26) -> 1955021.9 | E9: =sum(E10:E26) -> 1042755.6 | F9: =sum(F10:F26) -> 912266.37 | H9: Totales | J9: =sum(J10:J26) -> 1955021.9 | K9: =sum(K10:K26) -> 0 | L9: =sum(L10:L26) -> -1955021.9 | N9: Jav | O9: =Transacciones!N3 -> 176000
B10: Spotify | D10: =Analisis!B2 -> 7400 | E10: =if(isblank($B10), "", sumif(Transacciones!$E:$E,$B10,Transacciones!$C:$C)) -> 7094 | F10: =if(isblank($B10), "", D10-E10) -> 306 | H10: Javier | J10: =C3*1 -> 1955021.9 | K10: =O10 | L10: =if(isblank($H10:$H11), "", K10:K11-J10:J11) -> -1955021.9 | N10: Por pagar
B11: Netflix | D11: 14253 | E11: =if(isblank($B11), "", sumif(Transacciones!$E:$E,$B11,Transacciones!$C:$C)) -> 14253 | F11: =if(isblank($B11), "", D11-E11) -> 0
B12: Supermercado | D12: 322000 | E12: =if(isblank($B12), "", sumif(Transacciones!$E:$E,$B12,Transacciones!$C:$C)) -> 176000 | F12: =if(isblank($B12), "", D12-E12) -> 146000
B13: Arriendo | D13: =E13 -> 704652.44 | E13: =if(isblank($B13), "", sumif(Transacciones!$E:$E,$B13,Transacciones!$C:$C)) -> 704652.44 | F13: =if(isblank($B13), "", D13-E13) -> 0
B14: Gastos comunes | D14: =Analisis!B6 -> 270000 | E14: =if(isblank($B14), "", sumif(Transacciones!$E:$E,$B14,Transacciones!$C:$C)) -> 0 | F14: =if(isblank($B14), "", D14-E14) -> 270000
B15: Nana | D15: =37000*3 -> 111000 | E15: =if(isblank($B15), "", sumif(Transacciones!$E:$E,$B15,Transacciones!$C:$C)) -> 74000 | F15: =if(isblank($B15), "", D15-E15) -> 37000
B16: Entel | D16: =Analisis!B8 -> 29850 | E16: =if(isblank($B16), "", sumif(Transacciones!$E:$E,$B16,Transacciones!$C:$C)) -> 18990 | F16: =if(isblank($B16), "", D16-E16) -> 10860 | K16: =if(isblank($H16), "", sumif(Transacciones!$K:$K,$H16,Transacciones!$I:$I)) | L16: =if(isblank($H16), "", K16-J16)
B17: Luz | D17: =Analisis!B9 -> 82107 | E17: =if(isblank($B17), "", sumif(Transacciones!$E:$E,$B17,Transacciones!$C:$C)) -> 0 | F17: =if(isblank($B17), "", D17-E17) -> 82107 | L17: =if(isblank($H17), "", K17-J17)
B18: Agua | D18: =Analisis!B10 -> 15860 | E18: =if(isblank($B18), "", sumif(Transacciones!$E:$E,$B18,Transacciones!$C:$C)) -> 0 | F18: =if(isblank($B18), "", D18-E18) -> 15860 | K18: =if(isblank($H18), "", sumif(Transacciones!$K:$K,$H18,Transacciones!$I:$I)) | L18: =if(isblank($H18), "", K18-J18)
B19: Gas | D19: =Analisis!B11 -> 8600 | E19: =if(isblank($B19), "", sumif(Transacciones!$E:$E,$B19,Transacciones!$C:$C)) -> 0 | F19: =if(isblank($B19), "", D19-E19) -> 8600 | L19: =if(isblank($H19), "", K19-J19)
B20: Reparaciones y hogar | D20: =Analisis!B12 -> 0 | E20: =if(isblank($B20), "", sumif(Transacciones!$E:$E,$B20,Transacciones!$C:$C)) -> 0 | F20: =if(isblank($B20), "", D20-E20) -> 0 | K20: =if(isblank($H20), "", sumif(Transacciones!$K:$K,$H20,Transacciones!$I:$I)) | L20: =if(isblank($H20), "", K20-J20)
B21: Seguro depto | D21: =48917/40509*B1 -> 49299.494 | E21: =if(isblank($B21), "", sumif(Transacciones!$E:$E,$B21,Transacciones!$C:$C)) -> 47766.128 | F21: =if(isblank($B21), "", D21-E21) -> 1533.3668 | K21: =if(isblank($H21), "", sumif(Transacciones!$K:$K,$H21,Transacciones!$I:$I)) | L21: =if(isblank($H21), "", K21-J21)
B22: tag | D22: 140000 | E22: =if(isblank($B22), "", sumif(Transacciones!$E:$E,$B22,Transacciones!$C:$C)) -> 0 | F22: =if(isblank($B22), "", D22-E22) -> 140000 | K22: =if(isblank($H22), "", sumif(Transacciones!$K:$K,$H22,Transacciones!$I:$I)) | L22: =if(isblank($H22), "", K22-J22)
B23: bencina/luz | D23: 200000 | E23: =if(isblank($B23), "", sumif(Transacciones!$E:$E,$B23,Transacciones!$C:$C)) -> 0 | F23: =if(isblank($B23), "", D23-E23) -> 200000 | K23: =if(isblank($H23), "", sumif(Transacciones!$K:$K,$H23,Transacciones!$I:$I)) | L23: =if(isblank($H23), "", K23-J23)
D25: =D6:F6
E26: =if(isblank($B26), "", sumif(Transacciones!$E:$E,$B26,Transacciones!$C:$C)) | F26: =if(isblank($B26), "", D26-E26) | K26: =if(isblank($H26), "", sumif(Transacciones!$K:$K,$H26,Transacciones!$I:$I)) | L26: =if(isblank($H26), "", K26-J26)

Sheet JOSE
A1: =-(B1-C1) -> 0 | B1: =SUM(B3:B1001)*0.73 -> 0 | C1: =SUM(C3:C1001)*0.27 -> 0 | E1: Dolar | F1: =Resumen!G1+2 -> 927.24
A2: ITEM | B2: Jose | C2: Javier | F2: 45467
E3: =1480000/(3900000+1480000) -> 0.27509294 | F3: café | H3: =25000+28300 -> 53300 | J3: Tag vuelta | K3: 2318
F4: cafetería | H4: 12390 | J4: Tag ida | K4: 4209
F5: pia | H5: -27000 | J5: Bencina | K5: =19*2/14*1350 -> 3664.2857
F6: entradas | G6: 80500
F7: Bencina | H7: 13250
F8: johny rockets | H8: =35600-13500 -> 22100
F9: lavado | H9: 6500
F10: Bencina | G10: 52061
F11: Tag | G11: 44275
F12: Seguro | G12: 55079
F13: Tag | G13: 6075
F14: Burger king | H14: 5800
F15: Padel | H15: 17000
F16: Bencina | H16: 10000
F17: Awto | H17: 5400
F18: Goodmeal | H18: 13000
F19: Completos | H19: =-7700*4 -> -30800
F20: Cintas | H20: 8000
F21: Almuerzo | H21: 19500
F22: Tag | G22: 64959
F23: 45497
F24: cabritas | H24: 8400
F25: padel | H25: 15000
F26: desayuno | H26: 20000
F27: padel seba | H27: 9000
F28: Seguro Argo | G28: 55258
F29: padel 8 | H29: 15000
F30: seguro
F31: tag | G31: 11837
F32: fork | H32: 12990
F33: wallys | H33: 18000
F34: padel 16 | H34: 10000
F35: Tag | G35: 41660
F36: andi | H36: 20000
F37: veggies | H37: 4500
F44: 45528
F45: Juguetes Lola | G45: 15400
F46: Seguro Argo | G46: 55000
F47: Juguetes Lola | H47: 10400
H48: 5100
F49: Almjerso llacolen | G49: 48620
F50: peajes 9/8 | H50: 10000
F51: peajes 18/8 | H51: 10000
F52: asado panchi | H52: 16600
F53: padel | H53: 32500
F54: padel 21 | H54: 16000
F55: TAG | G55: 156000
F56: padel 26 | H56: 16000
F57: lavado | H57: 8000
F58: Vacunas Lola 1 parte | G58: 35000
F61: puzzle pellet lola | G61: 8200
F62: Comedero Lola | G62: 18508
F63: Trazodona | H63: 14000
F64: Juegues Lola | G64: 9500
F65: peajes | H65: 10000
F66: Bencina shell conce | G66: 52500
F67: peajes 21 sept | H67: 10000
F68: Transf Javi | G68: 16000
F69: almuerzo nieve | H69: 58300
F70: tarjetas | H70: 12000
F71: Cosas pastelería | G71: 39000
F72: bencina | H72: 50955
F73: peajes 29 sept | H73: 10000
F76: peajes | H76: 5000
F77: calzones lola | G77: 7900
F78: burger | H78: 21000
F79: padel | H79: 15000
F80: padel | H80: 15000
F81: arrayan | H81: 24000
F84: Vacunas Lola | G84: 32000
F85: Helados con mirza | G85: 9600
F86: cafe | H86: =17*F1 -> 15763.08
F87: bici | G87: =8500*2 -> 17000
F88: nassau | H88: =127.8*F1 -> 118501.27
F89: museo helado | G89: =70.34*980 -> 68933.2
F90: Baby yoda | H90: =10*980 -> 9800
F91: kayak | H91: =38*980 -> 37240
F92: Lighting lane | G92: =63729/880*980 -> 70970.932
F93: parasol | H93: =30*980 -> 29400
F94: waterside. | H94: =229*980 -> 224420
F95: flmingo | H95: =17.32*980 -> 16973.6
F96: robbies marine | H96: =10*980 -> 9800
F97: parque 7 miles. | H97: =9*980 -> 8820
F98: dolares | H98: 200900
F99: Dolares bahamas | H99: =58.4*980 -> 57232
F100: Walmart | G100: 95275
F101: lavado alfombra | H101: 15000
F103: Desayuno cassis | G103: 28820
F104: mantención aire | H104: 69990
F105: La maestranza | G105: 21000
F106: regalo Elma | H106: 18000
F107: Airfrier | G107: 38900
F108: tiradores | H108: 15600
F109: super | H109: 68800
F110: guantes | H110: 28800
F111: kiosclub | H111: 23450
F112: super | H112: 99700
F114: padel y ceviche | H114: =(20000+86000)/2 -> 53000
...

Sheet Analisis
B1: Maximo | C1: Minimo | D1: Promedio | E1: 44061 | F1: 44092 | G1: 44122 | H1: 44153 | I1: 44183 | J1: 43849 | K1: 43515 | L1: 43909 | M1: 44305 | N1: 44700 | O1: 45096 | P1: 45492 | Q1: 45888 | R1: 46284 | S1: 46679 | T1: 47076 | U1: 47471 | V1: 43850 | W1: 43881 | X1: 43910 | Y1: 43941 | Z1: 43971 | AA1: 44002 | AB1: 44032 | AC1: 44063 | AD1: 44094 | AE1: 44124 | AF1: 44155 | AG1: 44185 | AH1: 44217 | AI1: 44248 | AJ1: Marzo 21 | AK1: Abril 21 | AL1: Mayo 21 | AM1: Junio 21 | AN1: Julio 21 | AO1: 44429 | AP1: 44460 | AQ1: 44490 | AR1: noviembre 21 | AS1: diciembre 21 | AT1: enero 22 | AU1: febrero 22 | AV1: marzo 22 | AW1: abril 22 | AX1: mayo 22 | AY1: junio 22 | AZ1: julio 22 | BA1: agosto 22 | BB1: septiembre 22 | BC1: octubre 22 | BD1: noviembre 22 | BE1: diciembre 22 | BF1: enero 23 | BG1: febrero 23 | BH1: marzo 23 | BI1: abril 23 | BJ1: mayo 23 | BK1: junio 23 | BL1: julio 23 | BM1: agosto 23 | BN1: septiembre 23 | BO1: octubre 23 | BP1: noviembre 23 | BQ1: diciembre 23 | BR1: enero 24 | BS1: febrero 24 | BT1: marzo 24 | BU1: abril 24 | BV1: mayo 24 | BW1: junio 24 | BX1: julio 24 | BY1: agosto 24 | BZ1: septiembre 24 | CA1: octubre 24 | CB1: noviembre 24 | CC1: diciembre 24 | CD1: enero 25 | CE1: febrero 25 | CF1: marzo 25 | CG1: abril 25 | CH1: mayo 25 | CI1: junio 25 | CJ1: julio 25 | CK1: agosto 25 | CL1: sep 25 | CM1: oct 25 | CN1: nov 25 | CO1: dic 25 | CP1: ene 26
A2: Spotify | B2: =MAX(BN2:ZZ2) -> 7400 | C2: =MIN(AK2:ZZ2) -> 6300 | D2: =AVERAGE(AK2:ZZ2) -> 6746.1786 | E2: =SUMIF(Agosto!$E$5:$E$25,$A2,Agosto!$C$5:$C$25) -> 5361 | F2: =SUMIF(Septiembre!$E$5:$E$25,$A2,Septiembre!$C$5:$C$25) -> 5361 | G2: =SUMIF(octubre!$E$5:E$25,$A2,octubre!$C$5:$C$25) -> 5361 | H2: =SUMIF(noviembre!$E$5:F$25,$A2,noviembre!$C$5:$C$25) -> 5361 | I2: =SUMIF(Diciembre!$E$5:CQ$25,$A2,Diciembre!$C$5:$C$25) -> 5361 | J2: =SUMIF(Enero!$E$5:E$25,$A2,Enero!$C$5:$C$25) -> 5361 | K2: =SUMIF(febrero!$E$5:$E$25,$A2,febrero!$C$5:CQ$25) -> 5361 | L2: =SUMIF(Marzo!$E$5:$E$25,$A2,Marzo!$C$5:CQ$25) -> 5361 | M2: =SUMIF(Abril!$E$5:$E$25,$A2,Abril!$C$5:CQ$25) -> 5361 | N2: =SUMIF(Mayo!$E$5:$E$25,$A2,Mayo!$C$5:CQ$25) -> 5361 | O2: =SUMIF(Junio!$E$5:$E$25,$A2,Junio!$C$5:CQ$25) -> 5361 | P2: =SUMIF(Julio!$E$5:$E$25,$A2,Julio!$C$5:CQ$25) -> 5361 | Q2: =SUMIF('Agosto 19'!$E$5:$E$23,$A2,'Agosto 19'!$C$5:CQ$25) -> 5361 | R2: =SUMIF('Septiembre 19'!$E$5:$E$23,$A2,'Septiembre 19'!$C$5:CQ$25) -> 5361 | S2: =SUMIF('Octubre 19'!$E$5:$E$23,$A2,'Octubre 19'!$C$5:CQ$25) -> 5361 | T2: =SUMIF('Noviembre 19'!$E$5:$E$23,$A2,'Noviembre 19'!$C$5:CQ$25) -> 5361 | U2: =SUMIF('Diciembre 19'!$E$5:$E$23,$A2,'Diciembre 19'!$C$5:CQ$25) -> 5361 | V2: =SUMIF('Enero 20'!$E$5:$E$23,$A2,'Enero 20'!$C$5:CQ$25) -> 5361 | W2: =SUMIF('Febrero 20'!$E$5:$E$23,$A2,'Febrero 20'!$C$5:CQ$25) -> 5990 | X2: =SUMIF('Marzo 20'!$E$5:$E$23,$A2,'Marzo 20'!$C$5:CQ$25) -> 5990 | Y2: =SUMIF('Abril 20'!$E$5:$E$23,$A2,'Abril 20'!$C$5:CQ$25) -> 5990 | Z2: =SUMIF('Mayo 20'!$E$5:$E$23,$A2,'Mayo 20'!$C$5:CQ$25) -> 5990 | AA2: =SUMIF('Junio 20'!$E$5:$E$23,$A2,'Junio 20'!$C$5:CQ$25) -> 5990 | AB2: =SUMIF('Julio 20'!$E$5:$E$23,$A2,'Julio 20'!$C$5:CQ$25) -> 5990 | AC2: =SUMIF('Agosto 20'!$E$5:$E$23,$A2,'Agosto 20'!$C$5:CQ$25) -> 5990 | AD2: =SUMIF('Septiembre 20'!$E$5:$E$23,$A2,'Septiembre 20'!$C$5:CQ$25) -> 5990 | AE2: =SUMIF('octubre 20'!$E$5:$E$23,$A2,'octubre 20'!$C$5:CQ$25) -> 5990 | AF2: =SUMIF('noviembre 20'!$E$5:$E$23,$A2,'noviembre 20'!$C$5:CQ$25) -> 5990 | AG2: =SUMIF('diciembre 20'!$E$5:$E$23,$A2,'diciembre 20'!$C$5:CQ$25) -> 5990 | AH2: =SUMIF('enero 21'!$E$5:$E$23,$A2,'enero 21'!$C$5:CQ$25) -> 6300 | AI2: =SUMIF('febrero 21'!$E$5:$E$23,$A2,'febrero 21'!$C$5:CQ$25) -> 6300 | AJ2: =SUMIF('marzo 21'!$E$5:$E$23,$A2,'marzo 21'!$C$5:CQ$25) -> 6300 | AK2: =SUMIF('abril 21'!$E$5:$E$23,$A2,'abril 21'!$C$5:CQ$25) -> 6300 | AL2: =SUMIF('mayo 21'!$E$5:$E$23,$A2,'mayo 21'!$C$5:CQ$25) -> 6300 | AM2: =SUMIF('Junio 21'!$E$5:$E$23,$A2,'Junio 21'!$C$5:CQ$25) -> 6300 | AN2: =SUMIF('Julio 21'!$E$5:$E$23,$A2,'Julio 21'!$C$5:CQ$25) -> 6300 | AO2: =SUMIF('Agosto 21'!$E$5:$E$23,$A2,'Agosto 21'!$C$5:CQ$25) -> 6300 | AP2: =SUMIF('Septiembre 21'!$E$5:$E$23,$A2,'Septiembre 21'!$C$5:CQ$25) -> 6300 | AQ2: =SUMIF('Octubre 21'!$E$5:$E$23,$A2,'Octubre 21'!$C$5:CQ$25) -> 6300 | AR2: =SUMIF('Noviembre 21'!$E$5:$E$23,$A2,'Noviembre 21'!$C$5:CQ$25) -> 6300 | AS2: =SUMIF('Diciembre 21'!$E$5:$E$23,$A2,'Noviembre 21'!$C$5:CQ$25) -> 6300 | AT2: =SUMIF('Enero 22'!$E$5:$E$23,$A2,'Enero 22'!$C$5:CQ$25) -> 6300 | AU2: =SUMIF('Febrero 22'!$E$5:$E$23,$A2,'Febrero 22'!$C$5:CQ$25) -> 6300 | AV2: =SUMIF('Marzo 22'!$E$5:$E$23,$A2,'Marzo 22'!$C$5:CQ$25) -> 6300 | AW2: =SUMIF('Abril 22'!$E$5:$E$23,$A2,'Abril 22'!$C$5:CQ$25) -> 6300 | AX2: =SUMIF('Mayo 22'!$E$5:$E$23,$A2,'Mayo 22'!$C$5:CQ$25) -> 6300 | AY2: =SUMIF('Junio 22'!$E$5:$E$23,$A2,'Junio 22'!$C$5:CQ$25) -> 6300 | AZ2: =SUMIF('Julio 22'!$E$5:$E$23,$A2,'Julio 22'!$C$5:CQ$25) -> 6300 | BA2: =SUMIF('Agosto 22'!$E$5:$E$23,$A2,'Agosto 22'!$C$5:CQ$25) -> 6300 | BB2: =SUMIF('septiembre 22'!$E$5:$E$23,$A2,'septiembre 22'!$C$5:CQ$25) -> 6300 | BC2: =SUMIF('octubre 22'!$E$5:$E$23,$A2,'octubre 22'!$C$5:CQ$25) -> 6300 | BD2: =SUMIF('noviembre 22'!$E$5:$E$23,$A2,'noviembre 22'!$C$5:CQ$25) -> 6300 | BE2: =SUMIF('diciembre 22'!$E$5:$E$23,$A2,'noviembre 22'!$C$5:CQ$25) -> 6300 | BF2: =SUMIF('Enero 23'!$E$5:$E$23,$A2,'Enero 23'!$C$5:CQ$25) -> 6300 | BG2: =SUMIF('Febrero 23'!$E$5:$E$23,$A2,'Febrero 23'!$C$5:CQ$25) -> 6300 | BH2: =SUMIF('Marzo 23'!$E$5:$E$23,$A2,'Marzo 23'!$C$5:CQ$25) -> 6300 | BI2: =SUMIF('Abril 23'!$E$5:$E$23,$A2,'Abril 23'!$C$5:CQ$25) -> 6300 | BJ2: =SUMIF('Mayo 23'!$E$5:$E$23,$A2,'Mayo 23'!$C$5:CQ$25) -> 6300 | BK2: =SUMIF('Junio 23'!$E$5:$E$23,$A2,'Junio 23'!$C$5:CQ$25) -> 6300 | BL2: =SUMIF('Julio 23'!$E$5:$E$23,$A2,'Julio 23'!$C$5:CQ$25) -> 6300 | BM2: =SUMIF('Agosto 23'!$E$5:$E$23,$A2,'Agosto 23'!$C$5:CQ$25) -> 7400 | BN2: =SUMIF('Septiembre 23'!$E$5:$E$23,$A2,'Septiembre 23'!$C$5:CQ$25) -> 7400 | BO2: =SUMIF('Octubre 23'!$E$5:$E$23,$A2,'Octubre 23'!$C$5:CQ$25) -> 7400 | BP2: =SUMIF('Noviembre 23'!$E$5:$E$23,$A2,'Noviembre 23'!$C$5:CQ$25) -> 7400 | BQ2: =SUMIF('Diciembre 23'!$E$5:$E$23,$A2,'Diciembre 23'!$C$5:CQ$25) -> 7400 | BR2: =SUMIF('Enero 24'!$E$5:$E$23,$A2,'Enero 24'!$C$5:CQ$25) -> 7400 | BS2: =SUMIF('Febrero 24'!$E$5:$E$23,$A2,'Febrero 24'!$C$5:CQ$25) -> 7400 | BT2: =SUMIF('Marzo 24'!$E$5:$E$23,$A2,'Marzo 24'!$C$5:CQ$25) -> 7400 | BU2: =SUMIF('abril 24'!$E$5:$E$23,$A2,'abril 24'!$C$5:CQ$25) -> 7400 | BV2: =SUMIF('Mayo 24'!$E$5:$E$23,$A2,'Mayo 24'!$C$5:CQ$25) -> 7094 | BW2: =SUMIF('Junio 24'!$E$5:$E$23,$A2,'Junio 24'!$C$5:CQ$25) -> 7094 | BX2: =SUMIF('Julio 24'!$E$5:$E$23,$A2,'Julio 24'!$C$5:CQ$25) -> 7094 | BY2: =SUMIF('Agosto 24'!$E$5:$E$23,$A2,'Agosto 24'!$C$5:CQ$25) -> 7094 | BZ2: =SUMIF('Septiembre 24'!$E$5:$E$23,$A2,'Septiembre 24'!$C$5:CQ$25) -> 7094 | CA2: =SUMIF('Octubre 24'!$E$5:$E$23,$A2,'Octubre 24'!$C$5:CQ$25) -> 7094 | CB2: =SUMIF('Noviembre 24'!$E$5:$E$23,$A2,'Noviembre 24'!$C$5:CQ$25) -> 7094 | CC2: =SUMIF('Diciembre 24'!$E$5:$E$23,$A2,'Diciembre 24'!$C$5:CQ$25) -> 7094 | CD2: =SUMIF('Enero 25'!$E$5:$E$23,$A2,'Enero 25'!$C$5:CQ$25) -> 7094 | CE2: =SUMIF('febrero 25'!$E$5:$E$23,$A2,'febrero 25'!$C$5:CQ$25) -> 7094 | CF2: =SUMIF('marzo 25'!$E$5:$E$23,$A2,'marzo 25'!$C$5:CQ$25) -> 7094 | CG2: =SUMIF('abril 25'!$E$5:$E$23,$A2,'abril 25'!$C$5:CQ$25) -> 7094 | CH2: =SUMIF('Mayo 25'!$E$5:$E$23,$A2,'Mayo 25'!$C$5:CQ$25) -> 7094 | CI2: =SUMIF('Junio 25'!$E$5:$E$23,$A2,'Junio 25'!$C$5:CQ$25) -> 7094 | CJ2: =SUMIF('Julio 25'!$E$5:$E$23,$A2,'Julio 25'!$C$5:CQ$25) -> 7094 | CK2: =SUMIF('Agosto 25'!$E$5:$E$23,$A2,'Agosto 25'!$C$5:CQ$25) -> 7094 | CL2: =SUMIF('Septiembre 25'!$E$5:$E$23,$A2,'Septiembre 25'!$C$5:CQ$25) -> 7094 | CM2: =SUMIF('Octubre 25'!$E$5:$E$23,$A2,'Octubre 25'!$C$5:CQ$25) -> 7094 | CN2: =SUMIF('noviembre 25'!$E$5:$E$23,$A2,'noviembre 25'!$C$5:CQ$25) -> 7094
A3: Netflix | B3: =MAX(BN3:ZZ3) -> 14253 | C3: =MIN(AK3:ZZ3) -> 10700 | D3: =AVERAGE(AK3:ZZ3) -> 11924.946 | E3: =SUMIF(Agosto!$E$5:$E$25,$A3,Agosto!$C$5:$C$25) -> 7390 | F3: =SUMIF(Septiembre!$E$5:$E$25,$A3,Septiembre!$C$5:$C$25) -> 7390 | G3: =SUMIF(octubre!$E$5:E$25,$A3,octubre!$C$5:$C$25) -> 7390 | H3: =SUMIF(noviembre!$E$5:F$25,$A3,noviembre!$C$5:$C$25) -> 7390 | I3: =SUMIF(Diciembre!$E$5:CQ$25,$A3,Diciembre!$C$5:$C$25) -> 7390 | J3: =SUMIF(Enero!$E$5:E$25,$A3,Enero!$C$5:$C$25) -> 7390 | K3: =SUMIF(febrero!$E$5:$E$25,$A3,febrero!$C$5:CQ$25) -> 7390 | L3: =SUMIF(Marzo!$E$5:$E$25,$A3,Marzo!$C$5:CQ$25) -> 7390 | M3: =SUMIF(Abril!$E$5:$E$25,$A3,Abril!$C$5:CQ$25) -> 7390 | N3: =SUMIF(Mayo!$E$5:$E$25,$A3,Mayo!$C$5:CQ$25) -> 7390 | O3: =SUMIF(Junio!$E$5:$E$25,$A3,Junio!$C$5:CQ$25) -> 7390 | P3: =SUMIF(Julio!$E$5:$E$25,$A3,Julio!$C$5:CQ$25) -> 7390 | Q3: =SUMIF('Agosto 19'!$E$5:$E$23,$A3,'Agosto 19'!$C$5:CQ$25) -> 7390 | R3: =SUMIF('Septiembre 19'!$E$5:$E$23,$A3,'Septiembre 19'!$C$5:CQ$25) -> 7390 | S3: =SUMIF('Octubre 19'!$E$5:$E$23,$A3,'Octubre 19'!$C$5:CQ$25) -> 7390 | T3: =SUMIF('Noviembre 19'!$E$5:$E$23,$A3,'Noviembre 19'!$C$5:CQ$25) -> 8983.6 | U3: =SUMIF('Diciembre 19'!$E$5:$E$23,$A3,'Diciembre 19'!$C$5:CQ$25) -> 8983.6 | V3: =SUMIF('Enero 20'!$E$5:$E$23,$A3,'Enero 20'!$C$5:CQ$25) -> 8983.6 | W3: =SUMIF('Febrero 20'!$E$5:$E$23,$A3,'Febrero 20'!$C$5:CQ$25) -> 8990 | X3: =SUMIF('Marzo 20'!$E$5:$E$23,$A3,'Marzo 20'!$C$5:CQ$25) -> 8990 | Y3: =SUMIF('Abril 20'!$E$5:$E$23,$A3,'Abril 20'!$C$5:CQ$25) -> 8990 | Z3: =SUMIF('Mayo 20'!$E$5:$E$23,$A3,'Mayo 20'!$C$5:CQ$25) -> 8990 | AA3: =SUMIF('Junio 20'!$E$5:$E$23,$A3,'Junio 20'!$C$5:CQ$25) -> 8990 | AB3: =SUMIF('Julio 20'!$E$5:$E$23,$A3,'Julio 20'!$C$5:CQ$25) -> 8990 | AC3: =SUMIF('Agosto 20'!$E$5:$E$23,$A3,'Agosto 20'!$C$5:CQ$25) -> 10700 | AD3: =SUMIF('Septiembre 20'!$E$5:$E$23,$A3,'Septiembre 20'!$C$5:CQ$25) -> 10700 | AE3: =SUMIF('octubre 20'!$E$5:$E$23,$A3,'octubre 20'!$C$5:CQ$25) -> 10700 | AF3: =SUMIF('noviembre 20'!$E$5:$E$23,$A3,'noviembre 20'!$C$5:CQ$25) -> 10700 | AG3: =SUMIF('diciembre 20'!$E$5:$E$23,$A3,'diciembre 20'!$C$5:CQ$25) -> 10700 | AH3: =SUMIF('enero 21'!$E$5:$E$23,$A3,'enero 21'!$C$5:CQ$25) -> 10700 | AI3: =SUMIF('febrero 21'!$E$5:$E$23,$A3,'febrero 21'!$C$5:CQ$25) -> 10700 | AJ3: =SUMIF('marzo 21'!$E$5:$E$23,$A3,'marzo 21'!$C$5:CQ$25) -> 10700 | AK3: =SUMIF('abril 21'!$E$5:$E$23,$A3,'abril 21'!$C$5:CQ$25) -> 10700 | AL3: =SUMIF('mayo 21'!$E$5:$E$23,$A3,'mayo 21'!$C$5:CQ$25) -> 10700 | AM3: =SUMIF('Junio 21'!$E$5:$E$23,$A3,'Junio 21'!$C$5:CQ$25) -> 10700 | AN3: =SUMIF('Julio 21'!$E$5:$E$23,$A3,'Julio 21'!$C$5:CQ$25) -> 10700 | AO3: =SUMIF('Agosto 21'!$E$5:$E$23,$A3,'Agosto 21'!$C$5:CQ$25) -> 10700 | AP3: =SUMIF('Septiembre 21'!$E$5:$E$23,$A3,'Septiembre 21'!$C$5:CQ$25) -> 10700 | AQ3: =SUMIF('Octubre 21'!$E$5:$E$23,$A3,'Octubre 21'!$C$5:CQ$25) -> 10700 | AR3: =SUMIF('Noviembre 21'!$E$5:$E$23,$A3,'Noviembre 21'!$C$5:CQ$25) -> 10700 | AS3: =SUMIF('Diciembre 21'!$E$5:$E$23,$A3,'Noviembre 21'!$C$5:CQ$25) -> 10700 | AT3: =SUMIF('Enero 22'!$E$5:$E$23,$A3,'Enero 22'!$C$5:CQ$25) -> 10700 | AU3: =SUMIF('Febrero 22'!$E$5:$E$23,$A3,'Febrero 22'!$C$5:CQ$25) -> 10700 | AV3: =SUMIF('Marzo 22'!$E$5:$E$23,$A3,'Marzo 22'!$C$5:CQ$25) -> 10700 | AW3: =SUMIF('Abril 22'!$E$5:$E$23,$A3,'Abril 22'!$C$5:CQ$25) -> 10700 | AX3: =SUMIF('Mayo 22'!$E$5:$E$23,$A3,'Mayo 22'!$C$5:CQ$25) -> 10700 | AY3: =SUMIF('Junio 22'!$E$5:$E$23,$A3,'Junio 22'!$C$5:CQ$25) -> 10700 | AZ3: =SUMIF('Julio 22'!$E$5:$E$23,$A3,'Julio 22'!$C$5:CQ$25) -> 10700 | BA3: =SUMIF('Agosto 22'!$E$5:$E$23,$A3,'Agosto 22'!$C$5:CQ$25) -> 10700 | BB3: =SUMIF('septiembre 22'!$E$5:$E$23,$A3,'septiembre 22'!$C$5:CQ$25) -> 10700 | BC3: =SUMIF('octubre 22'!$E$5:$E$23,$A3,'octubre 22'!$C$5:CQ$25) -> 10700 | BD3: =SUMIF('noviembre 22'!$E$5:$E$23,$A3,'noviembre 22'!$C$5:CQ$25) -> 10700 | BE3: =SUMIF('diciembre 22'!$E$5:$E$23,$A3,'noviembre 22'!$C$5:CQ$25) -> 10700 | BF3: =SUMIF('Enero 23'!$E$5:$E$23,$A3,'Enero 23'!$C$5:CQ$25) -> 10700 | BG3: =SUMIF('Febrero 23'!$E$5:$E$23,$A3,'Febrero 23'!$C$5:CQ$25) -> 10700 | BH3: =SUMIF('Marzo 23'!$E$5:$E$23,$A3,'Marzo 23'!$C$5:CQ$25) -> 10700 | BI3: =SUMIF('Abril 23'!$E$5:$E$23,$A3,'Abril 23'!$C$5:CQ$25) -> 10700 | BJ3: =SUMIF('Mayo 23'!$E$5:$E$23,$A3,'Mayo 23'!$C$5:CQ$25) -> 10700 | BK3: =SUMIF('Junio 23'!$E$5:$E$23,$A3,'Junio 23'!$C$5:CQ$25) -> 10700 | BL3: =SUMIF('Julio 23'!$E$5:$E$23,$A3,'Julio 23'!$C$5:CQ$25) -> 10700 | BM3: =SUMIF('Agosto 23'!$E$5:$E$23,$A3,'Agosto 23'!$C$5:CQ$25) -> 10700 | BN3: =SUMIF('Septiembre 23'!$E$5:$E$23,$A3,'Septiembre 23'!$C$5:CQ$25) -> 10700 | BO3: =SUMIF('Octubre 23'!$E$5:$E$23,$A3,'Octubre 23'!$C$5:CQ$25) -> 10700 | BP3: =SUMIF('Noviembre 23'!$E$5:$E$23,$A3,'Noviembre 23'!$C$5:CQ$25) -> 10700 | BQ3: =SUMIF('Diciembre 23'!$E$5:$E$23,$A3,'Diciembre 23'!$C$5:CQ$25) -> 10700 | BR3: =SUMIF('Enero 24'!$E$5:$E$23,$A3,'Enero 24'!$C$5:CQ$25) -> 10700 | BS3: =SUMIF('Febrero 24'!$E$5:$E$23,$A3,'Febrero 24'!$C$5:CQ$25) -> 10700 | BT3: 11790 | BU3: =SUMIF('abril 24'!$E$5:$E$23,$A3,'abril 24'!$C$5:CQ$25) -> 10700 | BV3: =SUMIF('Mayo 24'!$E$5:$E$23,$A3,'Mayo 24'!$C$5:CQ$25) -> 14253 | BW3: =SUMIF('Junio 24'!$E$5:$E$23,$A3,'Junio 24'!$C$5:CQ$25) -> 14253 | BX3: =SUMIF('Julio 24'!$E$5:$E$23,$A3,'Julio 24'!$C$5:CQ$25) -> 14253 | BY3: =SUMIF('Agosto 24'!$E$5:$E$23,$A3,'Agosto 24'!$C$5:CQ$25) -> 14253 | BZ3: =SUMIF('Septiembre 24'!$E$5:$E$23,$A3,'Septiembre 24'!$C$5:CQ$25) -> 14253 | CA3: =SUMIF('Octubre 24'!$E$5:$E$23,$A3,'Octubre 24'!$C$5:CQ$25) -> 14253 | CB3: =SUMIF('Noviembre 24'!$E$5:$E$23,$A3,'Noviembre 24'!$C$5:CQ$25) -> 14253 | CC3: =SUMIF('Diciembre 24'!$E$5:$E$23,$A3,'Diciembre 24'!$C$5:CQ$25) -> 14253 | CD3: =SUMIF('Enero 25'!$E$5:$E$23,$A3,'Enero 25'!$C$5:CQ$25) -> 14253 | CE3: =SUMIF('febrero 25'!$E$5:$E$23,$A3,'febrero 25'!$C$5:CQ$25) -> 14253 | CF3: =SUMIF('marzo 25'!$E$5:$E$23,$A3,'marzo 25'!$C$5:CQ$25) -> 14253 | CG3: =SUMIF('abril 25'!$E$5:$E$23,$A3,'abril 25'!$C$5:CQ$25) -> 14253 | CH3: =SUMIF('Mayo 25'!$E$5:$E$23,$A3,'Mayo 25'!$C$5:CQ$25) -> 14253 | CI3: =SUMIF('Junio 25'!$E$5:$E$23,$A3,'Junio 25'!$C$5:CQ$25) -> 14253 | CJ3: =SUMIF('Julio 25'!$E$5:$E$23,$A3,'Julio 25'!$C$5:CQ$25) -> 14253 | CK3: =SUMIF('Agosto 25'!$E$5:$E$23,$A3,'Agosto 25'!$C$5:CQ$25) -> 14253 | CL3: =SUMIF('Septiembre 25'!$E$5:$E$23,$A3,'Septiembre 25'!$C$5:CQ$25) -> 14253 | CM3: =SUMIF('Octubre 25'!$E$5:$E$23,$A3,'Octubre 25'!$C$5:CQ$25) -> 14253 | CN3: =SUMIF('noviembre 25'!$E$5:$E$23,$A3,'noviembre 25'!$C$5:CQ$25) -> 14253
A4: Supermercado | B4: =MAX(BN4:ZZ4) -> 597487.52 | C4: =MIN(AK4:ZZ4) -> 0 | D4: =AVERAGE(AK4:ZZ4) -> 205213.37 | E4: =SUMIF(Agosto!$E$5:$E$25,$A4,Agosto!$C$5:$C$25) -> 323457 | F4: =SUMIF(Septiembre!$E$5:$E$25,$A4,Septiembre!$C$5:$C$25) -> 179594 | G4: =SUMIF(octubre!$E$5:E$25,$A4,octubre!$C$5:$C$25) -> 198576 | H4: =SUMIF(noviembre!$E$5:F$25,$A4,noviembre!$C$5:$C$25) -> 171902 | I4: =SUMIF(Diciembre!$E$5:CQ$25,$A4,Diciembre!$C$5:$C$25) -> 239690 | J4: =SUMIF(Enero!$E$5:E$25,$A4,Enero!$C$5:$C$25) -> 179779 | K4: =SUMIF(febrero!$E$5:$E$25,$A4,febrero!$C$5:CQ$25) -> 186244 | L4: =SUMIF(Marzo!$E$5:$E$25,$A4,Marzo!$C$5:CQ$25) -> 189515 | M4: =SUMIF(Abril!$E$5:$E$25,$A4,Abril!$C$5:CQ$25) -> 36309 | N4: =SUMIF(Mayo!$E$5:$E$25,$A4,Mayo!$C$5:CQ$25) -> 85000 | O4: =SUMIF(Junio!$E$5:$E$25,$A4,Junio!$C$5:CQ$25) -> 149585 | P4: =SUMIF(Julio!$E$5:$E$25,$A4,Julio!$C$5:CQ$25) -> 95516 | Q4: =SUMIF('Agosto 19'!$E$5:$E$23,$A4,'Agosto 19'!$C$5:CQ$25) -> 45000 | R4: =SUMIF('Septiembre 19'!$E$5:$E$23,$A4,'Septiembre 19'!$C$5:CQ$25) -> 80000 | S4: =SUMIF('Octubre 19'!$E$5:$E$23,$A4,'Octubre 19'!$C$5:CQ$25) -> 60000 | T4: =SUMIF('Noviembre 19'!$E$5:$E$23,$A4,'Noviembre 19'!$C$5:CQ$25) -> 37330 | U4: =SUMIF('Diciembre 19'!$E$5:$E$23,$A4,'Diciembre 19'!$C$5:CQ$25) -> 105268 | V4: =SUMIF('Enero 20'!$E$5:$E$23,$A4,'Enero 20'!$C$5:CQ$25) -> 105268 | W4: =SUMIF('Febrero 20'!$E$5:$E$23,$A4,'Febrero 20'!$C$5:CQ$25) -> 19765 | X4: =SUMIF('Marzo 20'!$E$5:$E$23,$A4,'Marzo 20'!$C$5:CQ$25) -> 79995 | Y4: =SUMIF('Abril 20'!$E$5:$E$23,$A4,'Abril 20'!$C$5:CQ$25) -> 253396 | Z4: =SUMIF('Mayo 20'!$E$5:$E$23,$A4,'Mayo 20'!$C$5:CQ$25) -> 200000 | AA4: =SUMIF('Junio 20'!$E$5:$E$23,$A4,'Junio 20'!$C$5:CQ$25) -> 233113 | AB4: =SUMIF('Julio 20'!$E$5:$E$23,$A4,'Julio 20'!$C$5:CQ$25) -> 187500 | AC4: =SUMIF('Agosto 20'!$E$5:$E$23,$A4,'Agosto 20'!$C$5:CQ$25) -> 120518 | AD4: =SUMIF('Septiembre 20'!$E$5:$E$23,$A4,'Septiembre 20'!$C$5:CQ$25) -> 230260 | AE4: =SUMIF('octubre 20'!$E$5:$E$23,$A4,'octubre 20'!$C$5:CQ$25) -> 143000 | AF4: =SUMIF('noviembre 20'!$E$5:$E$23,$A4,'noviembre 20'!$C$5:CQ$25) -> 115000 | AG4: =SUMIF('diciembre 20'!$E$5:$E$23,$A4,'diciembre 20'!$C$5:CQ$25) -> 76900 | AH4: =SUMIF('enero 21'!$E$5:$E$23,$A4,'enero 21'!$C$5:CQ$25) -> 115970 | AI4: =SUMIF('febrero 21'!$E$5:$E$23,$A4,'febrero 21'!$C$5:CQ$25) -> 119814 | AJ4: =SUMIF('marzo 21'!$E$5:$E$23,$A4,'marzo 21'!$C$5:CQ$25) -> 133000 | AK4: =SUMIF('abril 21'!$E$5:$E$23,$A4,'abril 21'!$C$5:CQ$25) -> 280400 | AL4: =SUMIF('mayo 21'!$E$5:$E$23,$A4,'mayo 21'!$C$5:CQ$25) -> 231334 | AM4: =SUMIF('Junio 21'!$E$5:$E$23,$A4,'Junio 21'!$C$5:CQ$25) -> 271789 | AN4: =SUMIF('Julio 21'!$E$5:$E$23,$A4,'Julio 21'!$C$5:CQ$25) -> 221452 | AO4: =SUMIF('Agosto 21'!$E$5:$E$23,$A4,'Agosto 21'!$C$5:CQ$25) -> 69710 | AP4: =SUMIF('Septiembre 21'!$E$5:$E$23,$A4,'Septiembre 21'!$C$5:CQ$25) -> 364000 | AQ4: =SUMIF('Octubre 21'!$E$5:$E$23,$A4,'Octubre 21'!$C$5:CQ$25) -> 154762 | AR4: =SUMIF('Noviembre 21'!$E$5:$E$23,$A4,'Noviembre 21'!$C$5:CQ$25) -> 183421 | AS4: =SUMIF('Diciembre 21'!$E$5:$E$23,$A4,'Noviembre 21'!$C$5:CQ$25) -> 183421 | AT4: =SUMIF('Enero 22'!$E$5:$E$23,$A4,'Enero 22'!$C$5:CQ$25) -> 140000 | AU4: =SUMIF('Febrero 22'!$E$5:$E$23,$A4,'Febrero 22'!$C$5:CQ$25) -> 40000 | AV4: =SUMIF('Marzo 22'!$E$5:$E$23,$A4,'Marzo 22'!$C$5:CQ$25) -> 308000 | AW4: =SUMIF('Abril 22'!$E$5:$E$23,$A4,'Abril 22'!$C$5:CQ$25) -> 108000 | AX4: =SUMIF('Mayo 22'!$E$5:$E$23,$A4,'Mayo 22'!$C$5:CQ$25) -> 180000 | AY4: =SUMIF('Junio 22'!$E$5:$E$23,$A4,'Junio 22'!$C$5:CQ$25) -> 100000 | AZ4: =SUMIF('Julio 22'!$E$5:$E$23,$A4,'Julio 22'!$C$5:CQ$25) -> 140000 | BA4: =SUMIF('Agosto 22'!$E$5:$E$23,$A4,'Agosto 22'!$C$5:CQ$25) -> 85000 | BB4: =SUMIF('septiembre 22'!$E$5:$E$23,$A4,'septiembre 22'!$C$5:CQ$25) -> 106000 | BC4: =SUMIF('octubre 22'!$E$5:$E$23,$A4,'octubre 22'!$C$5:CQ$25) -> 158000 | BD4: =SUMIF('noviembre 22'!$E$5:$E$23,$A4,'noviembre 22'!$C$5:CQ$25) -> 125000 | BE4: =SUMIF('diciembre 22'!$E$5:$E$23,$A4,'noviembre 22'!$C$5:CQ$25) -> 125000 | BF4: =SUMIF('Enero 23'!$E$5:$E$23,$A4,'Enero 23'!$C$5:CQ$25) -> 117000 | BG4: =SUMIF('Febrero 23'!$E$5:$E$23,$A4,'Febrero 23'!$C$5:CQ$25) -> 42000 | BH4: =SUMIF('Marzo 23'!$E$5:$E$23,$A4,'Marzo 23'!$C$5:CQ$25) -> 137835 | BI4: =SUMIF('Abril 23'!$E$5:$E$23,$A4,'Abril 23'!$C$5:CQ$25) -> 32600 | BJ4: =SUMIF('Mayo 23'!$E$5:$E$23,$A4,'Mayo 23'!$C$5:CQ$25) -> 140000 | BK4: =SUMIF('Junio 23'!$E$5:$E$23,$A4,'Junio 23'!$C$5:CQ$25) -> 140000 | BL4: =SUMIF('Julio 23'!$E$5:$E$23,$A4,'Julio 23'!$C$5:CQ$25) -> 200000 | BM4: =SUMIF('Agosto 23'!$E$5:$E$23,$A4,'Agosto 23'!$C$5:CQ$25) -> 130000 | BN4: =SUMIF('Septiembre 23'!$E$5:$E$23,$A4,'Septiembre 23'!$C$5:CQ$25) -> 160000 | BO4: =SUMIF('Octubre 23'!$E$5:$E$23,$A4,'Octubre 23'!$C$5:CQ$25) -> 160000 | BP4: =SUMIF('Noviembre 23'!$E$5:$E$23,$A4,'Noviembre 23'!$C$5:CQ$25) -> 160000 | BQ4: =SUMIF('Diciembre 23'!$E$5:$E$23,$A4,'Diciembre 23'!$C$5:CQ$25) -> 160000 | BR4: =SUMIF('Enero 24'!$E$5:$E$23,$A4,'Enero 24'!$C$5:CQ$25) -> 0 | BS4: =SUMIF('Febrero 24'!$E$5:$E$23,$A4,'Febrero 24'!$C$5:CQ$25) -> 70000 | BT4: =SUMIF('Marzo 24'!$E$5:$E$23,$A4,'Marzo 24'!$C$5:CQ$25) -> 70000 | BU4: =SUMIF('abril 24'!$E$5:$E$23,$A4,'abril 24'!$C$5:CQ$25) -> 380000 | BV4: =SUMIF('Mayo 24'!$E$5:$E$23,$A4,'Mayo 24'!$C$5:CQ$25) -> 304902.44 | BW4: =SUMIF('Junio 24'!$E$5:$E$23,$A4,'Junio 24'!$C$5:CQ$25) -> 322000 | BX4: =SUMIF('Julio 24'!$E$5:$E$23,$A4,'Julio 24'!$C$5:CQ$25) -> 112000 | BY4: =SUMIF('Agosto 24'!$E$5:$E$23,$A4,'Agosto 24'!$C$5:CQ$25) -> 321510 | BZ4: =SUMIF('Septiembre 24'!$E$5:$E$23,$A4,'Septiembre 24'!$C$5:CQ$25) -> 396000 | CA4: =SUMIF('Octubre 24'!$E$5:$E$23,$A4,'Octubre 24'!$C$5:CQ$25) -> 597487.52 | CB4: =SUMIF('Noviembre 24'!$E$5:$E$23,$A4,'Noviembre 24'!$C$5:CQ$25) -> 322000 | CC4: =SUMIF('Diciembre 24'!$E$5:$E$23,$A4,'Diciembre 24'!$C$5:CQ$25) -> 202000 | CD4: =SUMIF('Enero 25'!$E$5:$E$23,$A4,'Enero 25'!$C$5:CQ$25) -> 210000 | CE4: =SUMIF('febrero 25'!$E$5:$E$23,$A4,'febrero 25'!$C$5:CQ$25) -> 178000 | CF4: =SUMIF('marzo 25'!$E$5:$E$23,$A4,'marzo 25'!$C$5:CQ$25) -> 327000 | CG4: =SUMIF('abril 25'!$E$5:$E$23,$A4,'abril 25'!$C$5:CQ$25) -> 311000 | CH4: =SUMIF('Mayo 25'!$E$5:$E$23,$A4,'Mayo 25'!$C$5:CQ$25) -> 317500 | CI4: =SUMIF('Junio 25'!$E$5:$E$23,$A4,'Junio 25'!$C$5:CQ$25) -> 354825 | CJ4: =SUMIF('Julio 25'!$E$5:$E$23,$A4,'Julio 25'!$C$5:CQ$25) -> 298000 | CK4: =SUMIF('Agosto 25'!$E$5:$E$23,$A4,'Agosto 25'!$C$5:CQ$25) -> 326000 | CL4: =SUMIF('Septiembre 25'!$E$5:$E$23,$A4,'Septiembre 25'!$C$5:CQ$25) -> 324000 | CM4: =SUMIF('Octubre 25'!$E$5:$E$23,$A4,'Octubre 25'!$C$5:CQ$25) -> 324000 | CN4: =SUMIF('noviembre 25'!$E$5:$E$23,$A4,'noviembre 25'!$C$5:CQ$25) -> 269000
A5: Arriendo | B5: =MAX(BN5:ZZ5) -> 640662.16 | C5: =MIN(AK5:ZZ5) -> 466000 | D5: =AVERAGE(AK5:ZZ5) -> 615770.03 | E5: =SUMIF(Agosto!$E$5:$E$25,$A5,Agosto!$C$5:$C$25) -> 580000 | F5: =SUMIF(Septiembre!$E$5:$E$25,$A5,Septiembre!$C$5:$C$25) -> 580000 | G5: =SUMIF(octubre!$E$5:E$25,$A5,octubre!$C$5:$C$25) -> 580000 | H5: =SUMIF(noviembre!$E$5:F$25,$A5,noviembre!$C$5:$C$25) -> 580000 | I5: =SUMIF(Diciembre!$E$5:CQ$25,$A5,Diciembre!$C$5:$C$25) -> 580000 | J5: =SUMIF(Enero!$E$5:E$25,$A5,Enero!$C$5:$C$25) -> 580000 | K5: =SUMIF(febrero!$E$5:$E$25,$A5,febrero!$C$5:CQ$25) -> 586380 | L5: =SUMIF(Marzo!$E$5:$E$25,$A5,Marzo!$C$5:CQ$25) -> 586380 | M5: =SUMIF(Abril!$E$5:$E$25,$A5,Abril!$C$5:CQ$25) -> 586380 | N5: =SUMIF(Mayo!$E$5:$E$25,$A5,Mayo!$C$5:CQ$25) -> 586380 | O5: =SUMIF(Junio!$E$5:$E$25,$A5,Junio!$C$5:CQ$25) -> 586380 | P5: =SUMIF(Julio!$E$5:$E$25,$A5,Julio!$C$5:CQ$25) -> 586380 | Q5: =SUMIF('Agosto 19'!$E$5:$E$23,$A5,'Agosto 19'!$C$5:CQ$25) -> 586380 | R5: =SUMIF('Septiembre 19'!$E$5:$E$23,$A5,'Septiembre 19'!$C$5:CQ$25) -> 586380 | S5: =SUMIF('Octubre 19'!$E$5:$E$23,$A5,'Octubre 19'!$C$5:CQ$25) -> 586380 | T5: =SUMIF('Noviembre 19'!$E$5:$E$23,$A5,'Noviembre 19'!$C$5:CQ$25) -> 586380 | U5: =SUMIF('Diciembre 19'!$E$5:$E$23,$A5,'Diciembre 19'!$C$5:CQ$25) -> 586380 | V5: =SUMIF('Enero 20'!$E$5:$E$23,$A5,'Enero 20'!$C$5:CQ$25) -> 586380 | W5: =SUMIF('Febrero 20'!$E$5:$E$23,$A5,'Febrero 20'!$C$5:CQ$25) -> 586380 | X5: =SUMIF('Marzo 20'!$E$5:$E$23,$A5,'Marzo 20'!$C$5:CQ$25) -> 586380 | Y5: =SUMIF('Abril 20'!$E$5:$E$23,$A5,'Abril 20'!$C$5:CQ$25) -> 586380 | Z5: =SUMIF('Mayo 20'!$E$5:$E$23,$A5,'Mayo 20'!$C$5:CQ$25) -> 586380 | AA5: =SUMIF('Junio 20'!$E$5:$E$23,$A5,'Junio 20'!$C$5:CQ$25) -> 586380 | AB5: =SUMIF('Julio 20'!$E$5:$E$23,$A5,'Julio 20'!$C$5:CQ$25) -> 586380 | AC5: =SUMIF('Agosto 20'!$E$5:$E$23,$A5,'Agosto 20'!$C$5:CQ$25) -> 586380 | AD5: =SUMIF('Septiembre 20'!$E$5:$E$23,$A5,'Septiembre 20'!$C$5:CQ$25) -> 586380 | AE5: =SUMIF('octubre 20'!$E$5:$E$23,$A5,'octubre 20'!$C$5:CQ$25) -> 586380 | AF5: =SUMIF('noviembre 20'!$E$5:$E$23,$A5,'noviembre 20'!$C$5:CQ$25) -> 586380 | AG5: =SUMIF('diciembre 20'!$E$5:$E$23,$A5,'diciembre 20'!$C$5:CQ$25) -> 586380 | AH5: =SUMIF('enero 21'!$E$5:$E$23,$A5,'enero 21'!$C$5:CQ$25) -> 586380 | AI5: =SUMIF('febrero 21'!$E$5:$E$23,$A5,'febrero 21'!$C$5:CQ$25) -> 550000 | AJ5: =SUMIF('marzo 21'!$E$5:$E$23,$A5,'marzo 21'!$C$5:CQ$25) -> 550000 | AK5: =SUMIF('abril 21'!$E$5:$E$23,$A5,'abril 21'!$C$5:CQ$25) -> 550000 | AL5: =SUMIF('mayo 21'!$E$5:$E$23,$A5,'mayo 21'!$C$5:CQ$25) -> 550000 | AM5: =SUMIF('Junio 21'!$E$5:$E$23,$A5,'Junio 21'!$C$5:CQ$25) -> 466000 | AN5: =SUMIF('Julio 21'!$E$5:$E$23,$A5,'Julio 21'!$C$5:CQ$25) -> 466000 | AO5: =SUMIF('Agosto 21'!$E$5:$E$23,$A5,'Agosto 21'!$C$5:CQ$25) -> 466000 | AP5: =SUMIF('Septiembre 21'!$E$5:$E$23,$A5,'Septiembre 21'!$C$5:CQ$25) -> 466000 | AQ5: =SUMIF('Octubre 21'!$E$5:$E$23,$A5,'Octubre 21'!$C$5:CQ$25) -> 466000 | AR5: =SUMIF('Noviembre 21'!$E$5:$E$23,$A5,'Noviembre 21'!$C$5:CQ$25) -> 471000 | AS5: =SUMIF('Diciembre 21'!$E$5:$E$23,$A5,'Noviembre 21'!$C$5:CQ$25) -> 471000 | AT5: =SUMIF('Enero 22'!$E$5:$E$23,$A5,'Enero 22'!$C$5:CQ$25) -> 640662.16 | AU5: =SUMIF('Febrero 22'!$E$5:$E$23,$A5,'Febrero 22'!$C$5:CQ$25) -> 640662.16 | AV5: =SUMIF('Marzo 22'!$E$5:$E$23,$A5,'Marzo 22'!$C$5:CQ$25) -> 640662.16 | AW5: =SUMIF('Abril 22'!$E$5:$E$23,$A5,'Abril 22'!$C$5:CQ$25) -> 640662.16 | AX5: =SUMIF('Mayo 22'!$E$5:$E$23,$A5,'Mayo 22'!$C$5:CQ$25) -> 640662.16 | AY5: =SUMIF('Junio 22'!$E$5:$E$23,$A5,'Junio 22'!$C$5:CQ$25) -> 640662.16 | AZ5: =SUMIF('Julio 22'!$E$5:$E$23,$A5,'Julio 22'!$C$5:CQ$25) -> 640662.16 | BA5: =SUMIF('Agosto 22'!$E$5:$E$23,$A5,'Agosto 22'!$C$5:CQ$25) -> 640662.16 | BB5: =SUMIF('septiembre 22'!$E$5:$E$23,$A5,'septiembre 22'!$C$5:CQ$25) -> 640662.16 | BC5: =SUMIF('octubre 22'!$E$5:$E$23,$A5,'octubre 22'!$C$5:CQ$25) -> 640662.16 | BD5: =SUMIF('noviembre 22'!$E$5:$E$23,$A5,'noviembre 22'!$C$5:CQ$25) -> 640662.16 | BE5: =SUMIF('diciembre 22'!$E$5:$E$23,$A5,'noviembre 22'!$C$5:CQ$25) -> 640662.16 | BF5: =SUMIF('Enero 23'!$E$5:$E$23,$A5,'Enero 23'!$C$5:CQ$25) -> 640662.16 | BG5: =SUMIF('Febrero 23'!$E$5:$E$23,$A5,'Febrero 23'!$C$5:CQ$25) -> 640662.16 | BH5: =SUMIF('Marzo 23'!$E$5:$E$23,$A5,'Marzo 23'!$C$5:CQ$25) -> 640662.16 | BI5: =SUMIF('Abril 23'!$E$5:$E$23,$A5,'Abril 23'!$C$5:CQ$25) -> 640662.16 | BJ5: =SUMIF('Mayo 23'!$E$5:$E$23,$A5,'Mayo 23'!$C$5:CQ$25) -> 640662.16 | BK5: =SUMIF('Junio 23'!$E$5:$E$23,$A5,'Junio 23'!$C$5:CQ$25) -> 640662.16 | BL5: =SUMIF('Julio 23'!$E$5:$E$23,$A5,'Julio 23'!$C$5:CQ$25) -> 640662.16 | BM5: =SUMIF('Agosto 23'!$E$5:$E$23,$A5,'Agosto 23'!$C$5:CQ$25) -> 640662.16 | BN5: =SUMIF('Septiembre 23'!$E$5:$E$23,$A5,'Septiembre 23'!$C$5:CQ$25) -> 640662.16 | BO5: =SUMIF('Octubre 23'!$E$5:$E$23,$A5,'Octubre 23'!$C$5:CQ$25) -> 640662.16 | BP5: =SUMIF('Noviembre 23'!$E$5:$E$23,$A5,'Noviembre 23'!$C$5:CQ$25) -> 640662.16 | BQ5: =SUMIF('Diciembre 23'!$E$5:$E$23,$A5,'Diciembre 23'!$C$5:CQ$25) -> 640662.16 | BR5: =SUMIF('Enero 24'!$E$5:$E$23,$A5,'Enero 24'!$C$5:CQ$25) -> 640662.16 | BS5: =SUMIF('Febrero 24'!$E$5:$E$23,$A5,'Febrero 24'!$C$5:CQ$25) -> 640662.16 | BT5: =SUMIF('Marzo 24'!$E$5:$E$23,$A5,'Marzo 24'!$C$5:CQ$25) -> 640662.16 | BU5: =SUMIF('abril 24'!$E$5:$E$23,$A5,'abril 24'!$C$5:CQ$25) -> 640662.16 | BV5: =SUMIF('Mayo 24'!$E$5:$E$23,$A5,'Mayo 24'!$C$5:CQ$25) -> 640662.16 | BW5: =SUMIF('Junio 24'!$E$5:$E$23,$A5,'Junio 24'!$C$5:CQ$25) -> 640662.16 | BX5: =SUMIF('Julio 24'!$E$5:$E$23,$A5,'Julio 24'!$C$5:CQ$25) -> 640662.16 | BY5: =SUMIF('Agosto 24'!$E$5:$E$23,$A5,'Agosto 24'!$C$5:CQ$25) -> 640662.16 | BZ5: =SUMIF('Septiembre 24'!$E$5:$E$23,$A5,'Septiembre 24'!$C$5:CQ$25) -> 640662.16 | CA5: =SUMIF('Octubre 24'!$E$5:$E$23,$A5,'Octubre 24'!$C$5:CQ$25) -> 640662.16 | CB5: =SUMIF('Noviembre 24'!$E$5:$E$23,$A5,'Noviembre 24'!$C$5:CQ$25) -> 640662.16 | CC5: =SUMIF('Diciembre 24'!$E$5:$E$23,$A5,'Diciembre 24'!$C$5:CQ$25) -> 640662.16 | CD5: =SUMIF('Enero 25'!$E$5:$E$23,$A5,'Enero 25'!$C$5:CQ$25) -> 640662.16 | CE5: =SUMIF('febrero 25'!$E$5:$E$23,$A5,'febrero 25'!$C$5:CQ$25) -> 640662.16 | CF5: =SUMIF('marzo 25'!$E$5:$E$23,$A5,'marzo 25'!$C$5:CQ$25) -> 640662.16 | CG5: =SUMIF('abril 25'!$E$5:$E$23,$A5,'abril 25'!$C$5:CQ$25) -> 640662.16 | CH5: =SUMIF('Mayo 25'!$E$5:$E$23,$A5,'Mayo 25'!$C$5:CQ$25) -> 640662.16 | CI5: =SUMIF('Junio 25'!$E$5:$E$23,$A5,'Junio 25'!$C$5:CQ$25) -> 640662.16 | CJ5: =SUMIF('Julio 25'!$E$5:$E$23,$A5,'Julio 25'!$C$5:CQ$25) -> 640662.16 | CK5: =SUMIF('Agosto 25'!$E$5:$E$23,$A5,'Agosto 25'!$C$5:CQ$25) -> 640662.16 | CL5: =SUMIF('Septiembre 25'!$E$5:$E$23,$A5,'Septiembre 25'!$C$5:CQ$25) -> 640662.16 | CM5: =SUMIF('Octubre 25'!$E$5:$E$23,$A5,'Octubre 25'!$C$5:CQ$25) -> 640662.16 | CN5: =SUMIF('noviembre 25'!$E$5:$E$23,$A5,'noviembre 25'!$C$5:CQ$25) -> 640662.16
A6: Gastos comunes | B6: =MAX(BN6:ZZ6) -> 270000 | C6: =MIN(AK6:ZZ6) -> 144056 | D6: =AVERAGE(AK6:ZZ6) -> 202150.46 | E6: =SUMIF(Agosto!$E$5:$E$25,$A6,Agosto!$C$5:$C$25) -> 150000 | F6: =SUMIF(Septiembre!$E$5:$E$25,$A6,Septiembre!$C$5:$C$25) -> 163601 | G6: =SUMIF(octubre!$E$5:E$25,$A6,octubre!$C$5:$C$25) -> 129087 | H6: =SUMIF(noviembre!$E$5:F$25,$A6,noviembre!$C$5:$C$25) -> 147120 | I6: =SUMIF(Diciembre!$E$5:CQ$25,$A6,Diciembre!$C$5:$C$25) -> 134136 | J6: =SUMIF(Enero!$E$5:E$25,$A6,Enero!$C$5:$C$25) -> 114748 | K6: =SUMIF(febrero!$E$5:$E$25,$A6,febrero!$C$5:CQ$25) -> 115626 | L6: =SUMIF(Marzo!$E$5:$E$25,$A6,Marzo!$C$5:CQ$25) -> 125210 | M6: =SUMIF(Abril!$E$5:$E$25,$A6,Abril!$C$5:CQ$25) -> 145000 | N6: =SUMIF(Mayo!$E$5:$E$25,$A6,Mayo!$C$5:CQ$25) -> 141000 | O6: =SUMIF(Junio!$E$5:$E$25,$A6,Junio!$C$5:CQ$25) -> 126159 | P6: =SUMIF(Julio!$E$5:$E$25,$A6,Julio!$C$5:CQ$25) -> 157201 | Q6: =SUMIF('Agosto 19'!$E$5:$E$23,$A6,'Agosto 19'!$C$5:CQ$25) -> 174538 | R6: =SUMIF('Septiembre 19'!$E$5:$E$23,$A6,'Septiembre 19'!$C$5:CQ$25) -> 137822 | S6: =SUMIF('Octubre 19'!$E$5:$E$23,$A6,'Octubre 19'!$C$5:CQ$25) -> 192128 | T6: =SUMIF('Noviembre 19'!$E$5:$E$23,$A6,'Noviembre 19'!$C$5:CQ$25) -> 129148 | U6: =SUMIF('Diciembre 19'!$E$5:$E$23,$A6,'Diciembre 19'!$C$5:CQ$25) -> 111989 | V6: =SUMIF('Enero 20'!$E$5:$E$23,$A6,'Enero 20'!$C$5:CQ$25) -> 124389 | W6: =SUMIF('Febrero 20'!$E$5:$E$23,$A6,'Febrero 20'!$C$5:CQ$25) -> 96394 | X6: =SUMIF('Marzo 20'!$E$5:$E$23,$A6,'Marzo 20'!$C$5:CQ$25) -> 110457 | Y6: =SUMIF('Abril 20'!$E$5:$E$23,$A6,'Abril 20'!$C$5:CQ$25) -> 110355 | Z6: =SUMIF('Mayo 20'!$E$5:$E$23,$A6,'Mayo 20'!$C$5:CQ$25) -> 116014 | AA6: =SUMIF('Junio 20'!$E$5:$E$23,$A6,'Junio 20'!$C$5:CQ$25) -> 120891 | AB6: =SUMIF('Julio 20'!$E$5:$E$23,$A6,'Julio 20'!$C$5:CQ$25) -> 146308 | AC6: =SUMIF('Agosto 20'!$E$5:$E$23,$A6,'Agosto 20'!$C$5:CQ$25) -> 166549 | AD6: =SUMIF('Septiembre 20'!$E$5:$E$23,$A6,'Septiembre 20'!$C$5:CQ$25) -> 140181 | AE6: =SUMIF('octubre 20'!$E$5:$E$23,$A6,'octubre 20'!$C$5:CQ$25) -> 121609 | AF6: =SUMIF('noviembre 20'!$E$5:$E$23,$A6,'noviembre 20'!$C$5:CQ$25) -> 117535 | AG6: =SUMIF('diciembre 20'!$E$5:$E$23,$A6,'diciembre 20'!$C$5:CQ$25) -> 126117 | AH6: =SUMIF('enero 21'!$E$5:$E$23,$A6,'enero 21'!$C$5:CQ$25) -> 138100 | AI6: =SUMIF('febrero 21'!$E$5:$E$23,$A6,'febrero 21'!$C$5:CQ$25) -> 116051 | AJ6: =SUMIF('marzo 21'!$E$5:$E$23,$A6,'marzo 21'!$C$5:CQ$25) -> 135000 | AK6: =SUMIF('abril 21'!$E$5:$E$23,$A6,'abril 21'!$C$5:CQ$25) -> 144056 | AL6: =SUMIF('mayo 21'!$E$5:$E$23,$A6,'mayo 21'!$C$5:CQ$25) -> 161513 | AM6: =SUMIF('Junio 21'!$E$5:$E$23,$A6,'Junio 21'!$C$5:CQ$25) -> 171383 | AN6: =SUMIF('Julio 21'!$E$5:$E$23,$A6,'Julio 21'!$C$5:CQ$25) -> 162615 | AO6: =SUMIF('Agosto 21'!$E$5:$E$23,$A6,'Agosto 21'!$C$5:CQ$25) -> 174074 | AP6: =SUMIF('Septiembre 21'!$E$5:$E$23,$A6,'Septiembre 21'!$C$5:CQ$25) -> 177519 | AQ6: =SUMIF('Octubre 21'!$E$5:$E$23,$A6,'Octubre 21'!$C$5:CQ$25) -> 168795 | AR6: =SUMIF('Noviembre 21'!$E$5:$E$23,$A6,'Noviembre 21'!$C$5:CQ$25) -> 180954 | AS6: =SUMIF('Diciembre 21'!$E$5:$E$23,$A6,'Noviembre 21'!$C$5:CQ$25) -> 180954 | AT6: =SUMIF('Enero 22'!$E$5:$E$23,$A6,'Enero 22'!$C$5:CQ$25) -> 156000 | AU6: =SUMIF('Febrero 22'!$E$5:$E$23,$A6,'Febrero 22'!$C$5:CQ$25) -> 167592 | AV6: =SUMIF('Marzo 22'!$E$5:$E$23,$A6,'Marzo 22'!$C$5:CQ$25) -> 177531 | AW6: =SUMIF('Abril 22'!$E$5:$E$23,$A6,'Abril 22'!$C$5:CQ$25) -> 168060 | AX6: =SUMIF('Mayo 22'!$E$5:$E$23,$A6,'Mayo 22'!$C$5:CQ$25) -> 172675 | AY6: =SUMIF('Junio 22'!$E$5:$E$23,$A6,'Junio 22'!$C$5:CQ$25) -> 173865 | AZ6: =SUMIF('Julio 22'!$E$5:$E$23,$A6,'Julio 22'!$C$5:CQ$25) -> 178915 | BA6: =SUMIF('Agosto 22'!$E$5:$E$23,$A6,'Agosto 22'!$C$5:CQ$25) -> 181886 | BB6: =SUMIF('septiembre 22'!$E$5:$E$23,$A6,'septiembre 22'!$C$5:CQ$25) -> 181886 | BC6: =SUMIF('octubre 22'!$E$5:$E$23,$A6,'octubre 22'!$C$5:CQ$25) -> 199000 | BD6: =SUMIF('noviembre 22'!$E$5:$E$23,$A6,'noviembre 22'!$C$5:CQ$25) -> 178421 | BE6: =SUMIF('diciembre 22'!$E$5:$E$23,$A6,'noviembre 22'!$C$5:CQ$25) -> 178421 | BF6: =SUMIF('Enero 23'!$E$5:$E$23,$A6,'Enero 23'!$C$5:CQ$25) -> 189369 | BG6: =SUMIF('Febrero 23'!$E$5:$E$23,$A6,'Febrero 23'!$C$5:CQ$25) -> 172569 | BH6: =SUMIF('Marzo 23'!$E$5:$E$23,$A6,'Marzo 23'!$C$5:CQ$25) -> 197555 | BI6: =SUMIF('Abril 23'!$E$5:$E$23,$A6,'Abril 23'!$C$5:CQ$25) -> 184711 | BJ6: =SUMIF('Mayo 23'!$E$5:$E$23,$A6,'Mayo 23'!$C$5:CQ$25) -> 194071 | BK6: =SUMIF('Junio 23'!$E$5:$E$23,$A6,'Junio 23'!$C$5:CQ$25) -> 184071 | BL6: =SUMIF('Julio 23'!$E$5:$E$23,$A6,'Julio 23'!$C$5:CQ$25) -> 177929 | BM6: =SUMIF('Agosto 23'!$E$5:$E$23,$A6,'Agosto 23'!$C$5:CQ$25) -> 209199 | BN6: =SUMIF('Septiembre 23'!$E$5:$E$23,$A6,'Septiembre 23'!$C$5:CQ$25) -> 208199 | BO6: =SUMIF('Octubre 23'!$E$5:$E$23,$A6,'Octubre 23'!$C$5:CQ$25) -> 214783 | BP6: =SUMIF('Noviembre 23'!$E$5:$E$23,$A6,'Noviembre 23'!$C$5:CQ$25) -> 218783 | BQ6: =SUMIF('Diciembre 23'!$E$5:$E$23,$A6,'Diciembre 23'!$C$5:CQ$25) -> 235877 | BR6: =SUMIF('Enero 24'!$E$5:$E$23,$A6,'Enero 24'!$C$5:CQ$25) -> 225877 | BS6: =SUMIF('Febrero 24'!$E$5:$E$23,$A6,'Febrero 24'!$C$5:CQ$25) -> 225877 | BT6: =SUMIF('Marzo 24'!$E$5:$E$23,$A6,'Marzo 24'!$C$5:CQ$25) -> 230877 | BU6: =SUMIF('abril 24'!$E$5:$E$23,$A6,'abril 24'!$C$5:CQ$25) -> 216000 | BV6: =SUMIF('Mayo 24'!$E$5:$E$23,$A6,'Mayo 24'!$C$5:CQ$25) -> 226964 | BW6: =SUMIF('Junio 24'!$E$5:$E$23,$A6,'Junio 24'!$C$5:CQ$25) -> 234964 | BX6: =SUMIF('Julio 24'!$E$5:$E$23,$A6,'Julio 24'!$C$5:CQ$25) -> 252000 | BY6: =SUMIF('Agosto 24'!$E$5:$E$23,$A6,'Agosto 24'!$C$5:CQ$25) -> 251000 | BZ6: =SUMIF('Septiembre 24'!$E$5:$E$23,$A6,'Septiembre 24'!$C$5:CQ$25) -> 252000 | CA6: =SUMIF('Octubre 24'!$E$5:$E$23,$A6,'Octubre 24'!$C$5:CQ$25) -> 227000 | CB6: =SUMIF('Noviembre 24'!$E$5:$E$23,$A6,'Noviembre 24'!$C$5:CQ$25) -> 250000 | CC6: =SUMIF('Diciembre 24'!$E$5:$E$23,$A6,'Diciembre 24'!$C$5:CQ$25) -> 250000 | CD6: =SUMIF('Enero 25'!$E$5:$E$23,$A6,'Enero 25'!$C$5:CQ$25) -> 217636 | CE6: =SUMIF('febrero 25'!$E$5:$E$23,$A6,'febrero 25'!$C$5:CQ$25) -> 195000 | CF6: =SUMIF('marzo 25'!$E$5:$E$23,$A6,'marzo 25'!$C$5:CQ$25) -> 181000 | CG6: =SUMIF('abril 25'!$E$5:$E$23,$A6,'abril 25'!$C$5:CQ$25) -> 210000 | CH6: =SUMIF('Mayo 25'!$E$5:$E$23,$A6,'Mayo 25'!$C$5:CQ$25) -> 240000 | CI6: =SUMIF('Junio 25'!$E$5:$E$23,$A6,'Junio 25'!$C$5:CQ$25) -> 196000 | CJ6: =SUMIF('Julio 25'!$E$5:$E$23,$A6,'Julio 25'!$C$5:CQ$25) -> 225000 | CK6: =SUMIF('Agosto 25'!$E$5:$E$23,$A6,'Agosto 25'!$C$5:CQ$25) -> 270000 | CL6: =SUMIF('Septiembre 25'!$E$5:$E$23,$A6,'Septiembre 25'!$C$5:CQ$25) -> 240000 | CM6: =SUMIF('Octubre 25'!$E$5:$E$23,$A6,'Octubre 25'!$C$5:CQ$25) -> 240000 | CN6: =SUMIF('noviembre 25'!$E$5:$E$23,$A6,'noviembre 25'!$C$5:CQ$25) -> 240000
A7: Nana | B7: =MAX(BN7:ZZ7) -> 111000 | C7: =MIN(AK7:ZZ7) -> 0 | D7: =AVERAGE(AK7:ZZ7) -> 62428.571 | E7: =SUMIF(Agosto!$E$5:$E$25,$A7,Agosto!$C$5:$C$25) -> 0 | F7: =SUMIF(Septiembre!$E$5:$E$25,$A7,Septiembre!$C$5:$C$25) -> 0 | G7: =SUMIF(octubre!$E$5:E$25,$A7,octubre!$C$5:$C$25) -> 65000 | H7: =SUMIF(noviembre!$E$5:F$25,$A7,noviembre!$C$5:$C$25) -> 35000 | I7: =SUMIF(Diciembre!$E$5:CQ$25,$A7,Diciembre!$C$5:$C$25) -> 65000 | J7: =SUMIF(Enero!$E$5:E$25,$A7,Enero!$C$5:$C$25) -> 104175 | K7: =SUMIF(febrero!$E$5:$E$25,$A7,febrero!$C$5:CQ$25) -> 80000 | L7: =SUMIF(Marzo!$E$5:$E$25,$A7,Marzo!$C$5:CQ$25) -> 80000 | M7: =SUMIF(Abril!$E$5:$E$25,$A7,Abril!$C$5:CQ$25) -> 80000 | N7: =SUMIF(Mayo!$E$5:$E$25,$A7,Mayo!$C$5:CQ$25) -> 60000 | O7: =SUMIF(Junio!$E$5:$E$25,$A7,Junio!$C$5:CQ$25) -> 40000 | P7: =SUMIF(Julio!$E$5:$E$25,$A7,Julio!$C$5:CQ$25) -> 40000 | Q7: =SUMIF('Agosto 19'!$E$5:$E$23,$A7,'Agosto 19'!$C$5:CQ$25) -> 60000 | R7: =SUMIF('Septiembre 19'!$E$5:$E$23,$A7,'Septiembre 19'!$C$5:CQ$25) -> 60000 | S7: =SUMIF('Octubre 19'!$E$5:$E$23,$A7,'Octubre 19'!$C$5:CQ$25) -> 20000 | T7: =SUMIF('Noviembre 19'!$E$5:$E$23,$A7,'Noviembre 19'!$C$5:CQ$25) -> 40000 | U7: =SUMIF('Diciembre 19'!$E$5:$E$23,$A7,'Diciembre 19'!$C$5:CQ$25) -> 40000 | V7: =SUMIF('Enero 20'!$E$5:$E$23,$A7,'Enero 20'!$C$5:CQ$25) -> 50000 | W7: =SUMIF('Febrero 20'!$E$5:$E$23,$A7,'Febrero 20'!$C$5:CQ$25) -> 40000 | X7: =SUMIF('Marzo 20'!$E$5:$E$23,$A7,'Marzo 20'!$C$5:CQ$25) -> 40000 | Y7: =SUMIF('Abril 20'!$E$5:$E$23,$A7,'Abril 20'!$C$5:CQ$25) -> 0 | Z7: =SUMIF('Mayo 20'!$E$5:$E$23,$A7,'Mayo 20'!$C$5:CQ$25) -> 0 | AA7: 0 | AB7: =SUMIF('Julio 20'!$E$5:$E$23,$A7,'Julio 20'!$C$5:CQ$25) -> 60000 | AC7: =SUMIF('Agosto 20'!$E$5:$E$23,$A7,'Agosto 20'!$C$5:CQ$25) -> 60000 | AD7: =SUMIF('Septiembre 20'!$E$5:$E$23,$A7,'Septiembre 20'!$C$5:CQ$25) -> 60000 | AE7: =SUMIF('octubre 20'!$E$5:$E$23,$A7,'octubre 20'!$C$5:CQ$25) -> 0 | AF7: =SUMIF('noviembre 20'!$E$5:$E$23,$A7,'noviembre 20'!$C$5:CQ$25) -> 0 | AG7: =SUMIF('diciembre 20'!$E$5:$E$23,$A7,'diciembre 20'!$C$5:CQ$25) -> 0 | AH7: =SUMIF('enero 21'!$E$5:$E$23,$A7,'enero 21'!$C$5:CQ$25) -> 0 | AI7: =SUMIF('febrero 21'!$E$5:$E$23,$A7,'febrero 21'!$C$5:CQ$25) -> 0 | AJ7: =SUMIF('marzo 21'!$E$5:$E$23,$A7,'marzo 21'!$C$5:CQ$25) -> 0 | AK7: =SUMIF('abril 21'!$E$5:$E$23,$A7,'abril 21'!$C$5:CQ$25) -> 0 | AL7: =SUMIF('mayo 21'!$E$5:$E$23,$A7,'mayo 21'!$C$5:CQ$25) -> 0 | AM7: =SUMIF('Junio 21'!$E$5:$E$23,$A7,'Junio 21'!$C$5:CQ$25) -> 0 | AN7: =SUMIF('Julio 21'!$E$5:$E$23,$A7,'Julio 21'!$C$5:CQ$25) -> 0 | AO7: =SUMIF('Agosto 21'!$E$5:$E$23,$A7,'Agosto 21'!$C$5:CQ$25) -> 0 | AP7: =SUMIF('Septiembre 21'!$E$5:$E$23,$A7,'Septiembre 21'!$C$5:CQ$25) -> 0 | AQ7: =SUMIF('Octubre 21'!$E$5:$E$23,$A7,'Octubre 21'!$C$5:CQ$25) -> 0 | AR7: =SUMIF('Noviembre 21'!$E$5:$E$23,$A7,'Noviembre 21'!$C$5:CQ$25) -> 0 | AS7: =SUMIF('Diciembre 21'!$E$5:$E$23,$A7,'Noviembre 21'!$C$5:CQ$25) -> 0 | AT7: =SUMIF('Enero 22'!$E$5:$E$23,$A7,'Enero 22'!$C$5:CQ$25) -> 100000 | AU7: =SUMIF('Febrero 22'!$E$5:$E$23,$A7,'Febrero 22'!$C$5:CQ$25) -> 105000 | AV7: =SUMIF('Marzo 22'!$E$5:$E$23,$A7,'Marzo 22'!$C$5:CQ$25) -> 100000 | AW7: =SUMIF('Abril 22'!$E$5:$E$23,$A7,'Abril 22'!$C$5:CQ$25) -> 100000 | AX7: =SUMIF('Mayo 22'!$E$5:$E$23,$A7,'Mayo 22'!$C$5:CQ$25) -> 100000 | AY7: =SUMIF('Junio 22'!$E$5:$E$23,$A7,'Junio 22'!$C$5:CQ$25) -> 125000 | AZ7: =SUMIF('Julio 22'!$E$5:$E$23,$A7,'Julio 22'!$C$5:CQ$25) -> 125000 | BA7: =SUMIF('Agosto 22'!$E$5:$E$23,$A7,'Agosto 22'!$C$5:CQ$25) -> 100000 | BB7: =SUMIF('septiembre 22'!$E$5:$E$23,$A7,'septiembre 22'!$C$5:CQ$25) -> 150000 | BC7: =SUMIF('octubre 22'!$E$5:$E$23,$A7,'octubre 22'!$C$5:CQ$25) -> 150000 | BD7: =SUMIF('noviembre 22'!$E$5:$E$23,$A7,'noviembre 22'!$C$5:CQ$25) -> 150000 | BE7: =SUMIF('diciembre 22'!$E$5:$E$23,$A7,'noviembre 22'!$C$5:CQ$25) -> 150000 | BF7: =SUMIF('Enero 23'!$E$5:$E$23,$A7,'Enero 23'!$C$5:CQ$25) -> 150000 | BG7: =SUMIF('Febrero 23'!$E$5:$E$23,$A7,'Febrero 23'!$C$5:CQ$25) -> 150000 | BH7: =SUMIF('Marzo 23'!$E$5:$E$23,$A7,'Marzo 23'!$C$5:CQ$25) -> 150000 | BI7: =SUMIF('Abril 23'!$E$5:$E$23,$A7,'Abril 23'!$C$5:CQ$25) -> 0 | BJ7: =SUMIF('Mayo 23'!$E$5:$E$23,$A7,'Mayo 23'!$C$5:CQ$25) -> 0 | BK7: =SUMIF('Junio 23'!$E$5:$E$23,$A7,'Junio 23'!$C$5:CQ$25) -> 0 | BL7: =SUMIF('Julio 23'!$E$5:$E$23,$A7,'Julio 23'!$C$5:CQ$25) -> 0 | BM7: =SUMIF('Agosto 23'!$E$5:$E$23,$A7,'Agosto 23'!$C$5:CQ$25) -> 0 | BN7: =SUMIF('Septiembre 23'!$E$5:$E$23,$A7,'Septiembre 23'!$C$5:CQ$25) -> 0 | BO7: =SUMIF('Octubre 23'!$E$5:$E$23,$A7,'Octubre 23'!$C$5:CQ$25) -> 0 | BP7: =SUMIF('Noviembre 23'!$E$5:$E$23,$A7,'Noviembre 23'!$C$5:CQ$25) -> 0 | BQ7: =SUMIF('Diciembre 23'!$E$5:$E$23,$A7,'Diciembre 23'!$C$5:CQ$25) -> 0 | BR7: =SUMIF('Enero 24'!$E$5:$E$23,$A7,'Enero 24'!$C$5:CQ$25) -> 0 | BS7: =SUMIF('Febrero 24'!$E$5:$E$23,$A7,'Febrero 24'!$C$5:CQ$25) -> 0 | BT7: =SUMIF('Marzo 24'!$E$5:$E$23,$A7,'Marzo 24'!$C$5:CQ$25) -> 0 | BU7: =SUMIF('abril 24'!$E$5:$E$23,$A7,'abril 24'!$C$5:CQ$25) -> 37000 | BV7: =SUMIF('Mayo 24'!$E$5:$E$23,$A7,'Mayo 24'!$C$5:CQ$25) -> 74000 | BW7: =SUMIF('Junio 24'!$E$5:$E$23,$A7,'Junio 24'!$C$5:CQ$25) -> 74000 | BX7: =SUMIF('Julio 24'!$E$5:$E$23,$A7,'Julio 24'!$C$5:CQ$25) -> 74000 | BY7: =SUMIF('Agosto 24'!$E$5:$E$23,$A7,'Agosto 24'!$C$5:CQ$25) -> 74000 | BZ7: =SUMIF('Septiembre 24'!$E$5:$E$23,$A7,'Septiembre 24'!$C$5:CQ$25) -> 74000 | CA7: =SUMIF('Octubre 24'!$E$5:$E$23,$A7,'Octubre 24'!$C$5:CQ$25) -> 74000 | CB7: =SUMIF('Noviembre 24'!$E$5:$E$23,$A7,'Noviembre 24'!$C$5:CQ$25) -> 74000 | CC7: =SUMIF('Diciembre 24'!$E$5:$E$23,$A7,'Diciembre 24'!$C$5:CQ$25) -> 74000 | CD7: =SUMIF('Enero 25'!$E$5:$E$23,$A7,'Enero 25'!$C$5:CQ$25) -> 74000 | CE7: =SUMIF('febrero 25'!$E$5:$E$23,$A7,'febrero 25'!$C$5:CQ$25) -> 74000 | CF7: =SUMIF('marzo 25'!$E$5:$E$23,$A7,'marzo 25'!$C$5:CQ$25) -> 74000 | CG7: =SUMIF('abril 25'!$E$5:$E$23,$A7,'abril 25'!$C$5:CQ$25) -> 74000 | CH7: =SUMIF('Mayo 25'!$E$5:$E$23,$A7,'Mayo 25'!$C$5:CQ$25) -> 74000 | CI7: =SUMIF('Junio 25'!$E$5:$E$23,$A7,'Junio 25'!$C$5:CQ$25) -> 74000 | CJ7: =SUMIF('Julio 25'!$E$5:$E$23,$A7,'Julio 25'!$C$5:CQ$25) -> 74000 | CK7: =SUMIF('Agosto 25'!$E$5:$E$23,$A7,'Agosto 25'!$C$5:CQ$25) -> 111000 | CL7: =SUMIF('Septiembre 25'!$E$5:$E$23,$A7,'Septiembre 25'!$C$5:CQ$25) -> 111000 | CM7: =SUMIF('Octubre 25'!$E$5:$E$23,$A7,'Octubre 25'!$C$5:CQ$25) -> 111000 | CN7: =SUMIF('noviembre 25'!$E$5:$E$23,$A7,'noviembre 25'!$C$5:CQ$25) -> 111000
A8: Entel | B8: =MAX(BN8:ZZ8) -> 29850 | C8: =MIN(AK8:ZZ8) -> 17000 | D8: =AVERAGE(AK8:ZZ8) -> 22400.161 | E8: 37247 | F8: 39990 | G8: 39990 | H8: 39900 | I8: 39990 | J8: 39990 | K8: 45578 | L8: 45574 | M8: 45574 | N8: 11640 | O8: 25990 | P8: 25990 | Q8: 25990 | R8: 25990 | S8: 25990 | T8: =SUMIF('Noviembre 19'!$E$5:$E$23,$A8,'Noviembre 19'!$C$5:CQ$25) -> 21990 | U8: 21990 | V8: =SUMIF('Enero 20'!$E$5:$E$23,$A8,'Enero 20'!$C$5:CQ$25) -> 21990 | W8: =SUMIF('Febrero 20'!$E$5:$E$23,$A8,'Febrero 20'!$C$5:CQ$25) -> 21990 | X8: =SUMIF('Marzo 20'!$E$5:$E$23,$A8,'Marzo 20'!$C$5:CQ$25) -> 21990 | Y8: =SUMIF('Abril 20'!$E$5:$E$23,$A8,'Abril 20'!$C$5:CQ$25) -> 21990 | Z8: =SUMIF('Mayo 20'!$E$5:$E$23,$A8,'Mayo 20'!$C$5:CQ$25) -> 22124 | AA8: =SUMIF('Junio 20'!$E$5:$E$23,$A8,'Junio 20'!$C$5:CQ$25) -> 22124 | AB8: =SUMIF('Julio 20'!$E$5:$E$23,$A8,'Julio 20'!$C$5:CQ$25) -> 25990 | AC8: =SUMIF('Agosto 20'!$E$5:$E$23,$A8,'Agosto 20'!$C$5:CQ$25) -> 25990 | AD8: =SUMIF('Septiembre 20'!$E$5:$E$23,$A8,'Septiembre 20'!$C$5:CQ$25) -> 25990 | AE8: =SUMIF('octubre 20'!$E$5:$E$23,$A8,'octubre 20'!$C$5:CQ$25) -> 25990 | AF8: =SUMIF('noviembre 20'!$E$5:$E$23,$A8,'noviembre 20'!$C$5:CQ$25) -> 25990 | AG8: =SUMIF('diciembre 20'!$E$5:$E$23,$A8,'diciembre 20'!$C$5:CQ$25) -> 25990 | AH8: =SUMIF('enero 21'!$E$5:$E$23,$A8,'enero 21'!$C$5:CQ$25) -> 25990 | AI8: =SUMIF('febrero 21'!$E$5:$E$23,$A8,'febrero 21'!$C$5:CQ$25) -> 25990 | AJ8: =SUMIF('marzo 21'!$E$5:$E$23,$A8,'marzo 21'!$C$5:CQ$25) -> 25990 | AK8: =SUMIF('abril 21'!$E$5:$E$23,$A8,'abril 21'!$C$5:CQ$25) -> 21990 | AL8: =SUMIF('mayo 21'!$E$5:$E$23,$A8,'mayo 21'!$C$5:CQ$25) -> 21990 | AM8: =SUMIF('Junio 21'!$E$5:$E$23,$A8,'Junio 21'!$C$5:CQ$25) -> 21990 | AN8: =SUMIF('Julio 21'!$E$5:$E$23,$A8,'Julio 21'!$C$5:CQ$25) -> 21990 | AO8: =SUMIF('Agosto 21'!$E$5:$E$23,$A8,'Agosto 21'!$C$5:CQ$25) -> 21990 | AP8: =SUMIF('Septiembre 21'!$E$5:$E$23,$A8,'Septiembre 21'!$C$5:CQ$25) -> 21990 | AQ8: =SUMIF('Octubre 21'!$E$5:$E$23,$A8,'Octubre 21'!$C$5:CQ$25) -> 27990 | AR8: =SUMIF('Noviembre 21'!$E$5:$E$23,$A8,'Noviembre 21'!$C$5:CQ$25) -> 27990 | AS8: =SUMIF('Diciembre 21'!$E$5:$E$23,$A8,'Noviembre 21'!$C$5:CQ$25) -> 27990 | AT8: =SUMIF('Enero 22'!$E$5:$E$23,$A8,'Enero 22'!$C$5:CQ$25) -> 29190 | AU8: =SUMIF('Febrero 22'!$E$5:$E$23,$A8,'Febrero 22'!$C$5:CQ$25) -> 28420 | AV8: =SUMIF('Marzo 22'!$E$5:$E$23,$A8,'Marzo 22'!$C$5:CQ$25) -> 27990 | AW8: =SUMIF('Abril 22'!$E$5:$E$23,$A8,'Abril 22'!$C$5:CQ$25) -> 27990 | AX8: =SUMIF('Mayo 22'!$E$5:$E$23,$A8,'Mayo 22'!$C$5:CQ$25) -> 27990 | AY8: =SUMIF('Junio 22'!$E$5:$E$23,$A8,'Junio 22'!$C$5:CQ$25) -> 27990 | AZ8: =SUMIF('Julio 22'!$E$5:$E$23,$A8,'Julio 22'!$C$5:CQ$25) -> 27990 | BA8: =SUMIF('Agosto 22'!$E$5:$E$23,$A8,'Agosto 22'!$C$5:CQ$25) -> 27990 | BB8: =SUMIF('septiembre 22'!$E$5:$E$23,$A8,'septiembre 22'!$C$5:CQ$25) -> 27990 | BC8: =SUMIF('octubre 22'!$E$5:$E$23,$A8,'octubre 22'!$C$5:CQ$25) -> 27990 | BD8: =SUMIF('noviembre 22'!$E$5:$E$23,$A8,'noviembre 22'!$C$5:CQ$25) -> 27990 | BE8: =SUMIF('diciembre 22'!$E$5:$E$23,$A8,'noviembre 22'!$C$5:CQ$25) -> 27990 | BF8: =SUMIF('Enero 23'!$E$5:$E$23,$A8,'Enero 23'!$C$5:CQ$25) -> 27990 | BG8: =SUMIF('Febrero 23'!$E$5:$E$23,$A8,'Febrero 23'!$C$5:CQ$25) -> 27990 | BH8: =SUMIF('Marzo 23'!$E$5:$E$23,$A8,'Marzo 23'!$C$5:CQ$25) -> 27990 | BI8: =SUMIF('Abril 23'!$E$5:$E$23,$A8,'Abril 23'!$C$5:CQ$25) -> 19990 | BJ8: =SUMIF('Mayo 23'!$E$5:$E$23,$A8,'Mayo 23'!$C$5:CQ$25) -> 19990 | BK8: =SUMIF('Junio 23'!$E$5:$E$23,$A8,'Junio 23'!$C$5:CQ$25) -> 19990 | BL8: =SUMIF('Julio 23'!$E$5:$E$23,$A8,'Julio 23'!$C$5:CQ$25) -> 19990 | BM8: =SUMIF('Agosto 23'!$E$5:$E$23,$A8,'Agosto 23'!$C$5:CQ$25) -> 19990 | BN8: =SUMIF('Septiembre 23'!$E$5:$E$23,$A8,'Septiembre 23'!$C$5:CQ$25) -> 20718 | BO8: =SUMIF('Octubre 23'!$E$5:$E$23,$A8,'Octubre 23'!$C$5:CQ$25) -> 20718 | BP8: =SUMIF('Noviembre 23'!$E$5:$E$23,$A8,'Noviembre 23'!$C$5:CQ$25) -> 20718 | BQ8: =SUMIF('Diciembre 23'!$E$5:$E$23,$A8,'Diciembre 23'!$C$5:CQ$25) -> 20718 | BR8: =SUMIF('Enero 24'!$E$5:$E$23,$A8,'Enero 24'!$C$5:CQ$25) -> 21380 | BS8: =SUMIF('Febrero 24'!$E$5:$E$23,$A8,'Febrero 24'!$C$5:CQ$25) -> 21380 | BT8: =SUMIF('Marzo 24'!$E$5:$E$23,$A8,'Marzo 24'!$C$5:CQ$25) -> 21380 | BU8: =SUMIF('abril 24'!$E$5:$E$23,$A8,'abril 24'!$C$5:CQ$25) -> 29850 | BV8: =SUMIF('Mayo 24'!$E$5:$E$23,$A8,'Mayo 24'!$C$5:CQ$25) -> 19777 | BW8: =SUMIF('Junio 24'!$E$5:$E$23,$A8,'Junio 24'!$C$5:CQ$25) -> 17990 | BX8: =SUMIF('Julio 24'!$E$5:$E$23,$A8,'Julio 24'!$C$5:CQ$25) -> 17990 | BY8: =SUMIF('Agosto 24'!$E$5:$E$23,$A8,'Agosto 24'!$C$5:CQ$25) -> 17990 | BZ8: =SUMIF('Septiembre 24'!$E$5:$E$23,$A8,'Septiembre 24'!$C$5:CQ$25) -> 17990 | CA8: =SUMIF('Octubre 24'!$E$5:$E$23,$A8,'Octubre 24'!$C$5:CQ$25) -> 17990 | CB8: =SUMIF('Noviembre 24'!$E$5:$E$23,$A8,'Noviembre 24'!$C$5:CQ$25) -> 17990 | CC8: =SUMIF('Diciembre 24'!$E$5:$E$23,$A8,'Diciembre 24'!$C$5:CQ$25) -> 23990 | CD8: =SUMIF('Enero 25'!$E$5:$E$23,$A8,'Enero 25'!$C$5:CQ$25) -> 17000 | CE8: =SUMIF('febrero 25'!$E$5:$E$23,$A8,'febrero 25'!$C$5:CQ$25) -> 17000 | CF8: =SUMIF('marzo 25'!$E$5:$E$23,$A8,'marzo 25'!$C$5:CQ$25) -> 17000 | CG8: =SUMIF('abril 25'!$E$5:$E$23,$A8,'abril 25'!$C$5:CQ$25) -> 17000 | CH8: =SUMIF('Mayo 25'!$E$5:$E$23,$A8,'Mayo 25'!$C$5:CQ$25) -> 17000 | CI8: =SUMIF('Junio 25'!$E$5:$E$23,$A8,'Junio 25'!$C$5:CQ$25) -> 17000 | CJ8: =SUMIF('Julio 25'!$E$5:$E$23,$A8,'Julio 25'!$C$5:CQ$25) -> 17000 | CK8: =SUMIF('Agosto 25'!$E$5:$E$23,$A8,'Agosto 25'!$C$5:CQ$25) -> 17000 | CL8: =SUMIF('Septiembre 25'!$E$5:$E$23,$A8,'Septiembre 25'!$C$5:CQ$25) -> 17500 | CM8: =SUMIF('Octubre 25'!$E$5:$E$23,$A8,'Octubre 25'!$C$5:CQ$25) -> 17500 | CN8: =SUMIF('noviembre 25'!$E$5:$E$23,$A8,'noviembre 25'!$C$5:CQ$25) -> 17500
A9: Luz | B9: =MAX(BN9:ZZ9) -> 82107 | C9: =MIN(AK9:ZZ9) -> 0 | D9: =AVERAGE(AK9:ZZ9) -> 22993.179 | E9: =SUMIF(Agosto!$E$5:$E$25,$A9,Agosto!$C$5:$C$25) -> 1656 | F9: =SUMIF(Septiembre!$E$5:$E$25,$A9,Septiembre!$C$5:$C$25) -> 1547 | G9: =SUMIF(octubre!$E$5:E$25,$A9,octubre!$C$5:$C$25) -> 3627 | H9: =SUMIF(noviembre!$E$5:F$25,$A9,noviembre!$C$5:$C$25) -> 2979 | I9: =SUMIF(Diciembre!$E$5:CQ$25,$A9,Diciembre!$C$5:$C$25) -> 2927 | J9: =SUMIF(Enero!$E$5:E$25,$A9,Enero!$C$5:$C$25) -> 3949 | K9: =SUMIF(febrero!$E$5:$E$25,$A9,febrero!$C$5:CQ$25) -> 9704 | L9: =SUMIF(Marzo!$E$5:$E$25,$A9,Marzo!$C$5:CQ$25) -> 9186 | M9: =SUMIF(Abril!$E$5:$E$25,$A9,Abril!$C$5:CQ$25) -> 8331 | N9: =SUMIF(Mayo!$E$5:$E$25,$A9,Mayo!$C$5:CQ$25) -> 11678 | O9: =SUMIF(Junio!$E$5:$E$25,$A9,Junio!$C$5:CQ$25) -> 9116 | P9: =SUMIF(Julio!$E$5:$E$25,$A9,Julio!$C$5:CQ$25) -> 7713 | Q9: =SUMIF('Agosto 19'!$E$5:$E$23,$A9,'Agosto 19'!$C$5:CQ$25) -> 9869 | R9: =SUMIF('Septiembre 19'!$E$5:$E$23,$A9,'Septiembre 19'!$C$5:CQ$25) -> 10800 | S9: =SUMIF('Octubre 19'!$E$5:$E$23,$A9,'Octubre 19'!$C$5:CQ$25) -> 8434 | T9: =SUMIF('Noviembre 19'!$E$5:$E$23,$A9,'Noviembre 19'!$C$5:CQ$25) -> 8668 | U9: =SUMIF('Diciembre 19'!$E$5:$E$23,$A9,'Diciembre 19'!$C$5:CQ$25) -> 7089 | V9: =SUMIF('Enero 20'!$E$5:$E$23,$A9,'Enero 20'!$C$5:CQ$25) -> 11963 | W9: =SUMIF('Febrero 20'!$E$5:$E$23,$A9,'Febrero 20'!$C$5:CQ$25) -> 18702 | X9: =SUMIF('Marzo 20'!$E$5:$E$23,$A9,'Marzo 20'!$C$5:CQ$25) -> 18004 | Y9: =SUMIF('Abril 20'!$E$5:$E$23,$A9,'Abril 20'!$C$5:CQ$25) -> 12150 | Z9: =SUMIF('Mayo 20'!$E$5:$E$23,$A9,'Mayo 20'!$C$5:CQ$25) -> 14606 | AA9: =SUMIF('Junio 20'!$E$5:$E$23,$A9,'Junio 20'!$C$5:CQ$25) -> 14385 | AB9: =SUMIF('Julio 20'!$E$5:$E$23,$A9,'Julio 20'!$C$5:CQ$25) -> 15128 | AC9: =SUMIF('Agosto 20'!$E$5:$E$23,$A9,'Agosto 20'!$C$5:CQ$25) -> 16119 | AD9: =SUMIF('Septiembre 20'!$E$5:$E$23,$A9,'Septiembre 20'!$C$5:CQ$25) -> 12028 | AE9: =SUMIF('octubre 20'!$E$5:$E$23,$A9,'octubre 20'!$C$5:CQ$25) -> 0 | AF9: =SUMIF('noviembre 20'!$E$5:$E$23,$A9,'noviembre 20'!$C$5:CQ$25) -> 11500 | AG9: =SUMIF('diciembre 20'!$E$5:$E$23,$A9,'diciembre 20'!$C$5:CQ$25) -> 11466 | AH9: =SUMIF('enero 21'!$E$5:$E$23,$A9,'enero 21'!$C$5:CQ$25) -> 16191 | AI9: =SUMIF('febrero 21'!$E$5:$E$23,$A9,'febrero 21'!$C$5:CQ$25) -> 9873 | AJ9: =SUMIF('marzo 21'!$E$5:$E$23,$A9,'marzo 21'!$C$5:CQ$25) -> 9216 | AK9: =SUMIF('abril 21'!$E$5:$E$23,$A9,'abril 21'!$C$5:CQ$25) -> 16185 | AL9: =SUMIF('mayo 21'!$E$5:$E$23,$A9,'mayo 21'!$C$5:CQ$25) -> 26468 | AM9: =SUMIF('Junio 21'!$E$5:$E$23,$A9,'Junio 21'!$C$5:CQ$25) -> 14181 | AN9: =SUMIF('Julio 21'!$E$5:$E$23,$A9,'Julio 21'!$C$5:CQ$25) -> 7818 | AO9: =SUMIF('Agosto 21'!$E$5:$E$23,$A9,'Agosto 21'!$C$5:CQ$25) -> 12000 | AP9: =SUMIF('Septiembre 21'!$E$5:$E$23,$A9,'Septiembre 21'!$C$5:CQ$25) -> 0 | AQ9: =SUMIF('Octubre 21'!$E$5:$E$23,$A9,'Octubre 21'!$C$5:CQ$25) -> 13200 | AR9: =SUMIF('Noviembre 21'!$E$5:$E$23,$A9,'Noviembre 21'!$C$5:CQ$25) -> 13852 | AS9: =SUMIF('Diciembre 21'!$E$5:$E$23,$A9,'Noviembre 21'!$C$5:CQ$25) -> 13852 | AT9: =SUMIF('Enero 22'!$E$5:$E$23,$A9,'Enero 22'!$C$5:CQ$25) -> 12600 | AU9: =SUMIF('Febrero 22'!$E$5:$E$23,$A9,'Febrero 22'!$C$5:CQ$25) -> 10841 | AV9: =SUMIF('Marzo 22'!$E$5:$E$23,$A9,'Marzo 22'!$C$5:CQ$25) -> 8900 | AW9: =SUMIF('Abril 22'!$E$5:$E$23,$A9,'Abril 22'!$C$5:CQ$25) -> 9255 | AX9: =SUMIF('Mayo 22'!$E$5:$E$23,$A9,'Mayo 22'!$C$5:CQ$25) -> 10563 | AY9: =SUMIF('Junio 22'!$E$5:$E$23,$A9,'Junio 22'!$C$5:CQ$25) -> 12000 | AZ9: =SUMIF('Julio 22'!$E$5:$E$23,$A9,'Julio 22'!$C$5:CQ$25) -> 19300 | BA9: =SUMIF('Agosto 22'!$E$5:$E$23,$A9,'Agosto 22'!$C$5:CQ$25) -> 19971 | BB9: =SUMIF('septiembre 22'!$E$5:$E$23,$A9,'septiembre 22'!$C$5:CQ$25) -> 11058 | BC9: =SUMIF('octubre 22'!$E$5:$E$23,$A9,'octubre 22'!$C$5:CQ$25) -> 0 | BD9: =SUMIF('noviembre 22'!$E$5:$E$23,$A9,'noviembre 22'!$C$5:CQ$25) -> 9672 | BE9: =SUMIF('diciembre 22'!$E$5:$E$23,$A9,'noviembre 22'!$C$5:CQ$25) -> 9672 | BF9: =SUMIF('Enero 23'!$E$5:$E$23,$A9,'Enero 23'!$C$5:CQ$25) -> 11091 | BG9: =SUMIF('Febrero 23'!$E$5:$E$23,$A9,'Febrero 23'!$C$5:CQ$25) -> 9867 | BH9: =SUMIF('Marzo 23'!$E$5:$E$23,$A9,'Marzo 23'!$C$5:CQ$25) -> 9602 | BI9: =SUMIF('Abril 23'!$E$5:$E$23,$A9,'Abril 23'!$C$5:CQ$25) -> 8000 | BJ9: =SUMIF('Mayo 23'!$E$5:$E$23,$A9,'Mayo 23'!$C$5:CQ$25) -> 8324 | BK9: =SUMIF('Junio 23'!$E$5:$E$23,$A9,'Junio 23'!$C$5:CQ$25) -> 7308 | BL9: =SUMIF('Julio 23'!$E$5:$E$23,$A9,'Julio 23'!$C$5:CQ$25) -> 15117 | BM9: =SUMIF('Agosto 23'!$E$5:$E$23,$A9,'Agosto 23'!$C$5:CQ$25) -> 13890 | BN9: =SUMIF('Septiembre 23'!$E$5:$E$23,$A9,'Septiembre 23'!$C$5:CQ$25) -> 21446 | BO9: =SUMIF('Octubre 23'!$E$5:$E$23,$A9,'Octubre 23'!$C$5:CQ$25) -> 15300 | BP9: =SUMIF('Noviembre 23'!$E$5:$E$23,$A9,'Noviembre 23'!$C$5:CQ$25) -> 15695 | BQ9: =SUMIF('Diciembre 23'!$E$5:$E$23,$A9,'Diciembre 23'!$C$5:CQ$25) -> 16507 | BR9: =SUMIF('Enero 24'!$E$5:$E$23,$A9,'Enero 24'!$C$5:CQ$25) -> 30073 | BS9: =SUMIF('Febrero 24'!$E$5:$E$23,$A9,'Febrero 24'!$C$5:CQ$25) -> 36500 | BT9: =SUMIF('Marzo 24'!$E$5:$E$23,$A9,'Marzo 24'!$C$5:CQ$25) -> 41316 | BU9: =SUMIF('abril 24'!$E$5:$E$23,$A9,'abril 24'!$C$5:CQ$25) -> 26500 | BV9: =SUMIF('Mayo 24'!$E$5:$E$23,$A9,'Mayo 24'!$C$5:CQ$25) -> 30617 | BW9: =SUMIF('Junio 24'!$E$5:$E$23,$A9,'Junio 24'!$C$5:CQ$25) -> 35993 | BX9: =SUMIF('Julio 24'!$E$5:$E$23,$A9,'Julio 24'!$C$5:CQ$25) -> 38894 | BY9: =SUMIF('Agosto 24'!$E$5:$E$23,$A9,'Agosto 24'!$C$5:CQ$25) -> 38432 | BZ9: =SUMIF('Septiembre 24'!$E$5:$E$23,$A9,'Septiembre 24'!$C$5:CQ$25) -> 27697 | CA9: =SUMIF('Octubre 24'!$E$5:$E$23,$A9,'Octubre 24'!$C$5:CQ$25) -> 24676 | CB9: =SUMIF('Noviembre 24'!$E$5:$E$23,$A9,'Noviembre 24'!$C$5:CQ$25) -> 43800 | CC9: =SUMIF('Diciembre 24'!$E$5:$E$23,$A9,'Diciembre 24'!$C$5:CQ$25) -> 24064 | CD9: =SUMIF('Enero 25'!$E$5:$E$23,$A9,'Enero 25'!$C$5:CQ$25) -> 82107 | CE9: =SUMIF('febrero 25'!$E$5:$E$23,$A9,'febrero 25'!$C$5:CQ$25) -> 66739 | CF9: =SUMIF('marzo 25'!$E$5:$E$23,$A9,'marzo 25'!$C$5:CQ$25) -> 40200 | CG9: =SUMIF('abril 25'!$E$5:$E$23,$A9,'abril 25'!$C$5:CQ$25) -> 32500 | CH9: =SUMIF('Mayo 25'!$E$5:$E$23,$A9,'Mayo 25'!$C$5:CQ$25) -> 31500 | CI9: =SUMIF('Junio 25'!$E$5:$E$23,$A9,'Junio 25'!$C$5:CQ$25) -> 36000 | CJ9: =SUMIF('Julio 25'!$E$5:$E$23,$A9,'Julio 25'!$C$5:CQ$25) -> 49275 | CK9: =SUMIF('Agosto 25'!$E$5:$E$23,$A9,'Agosto 25'!$C$5:CQ$25) -> 57000 | CL9: =SUMIF('Septiembre 25'!$E$5:$E$23,$A9,'Septiembre 25'!$C$5:CQ$25) -> 41200 | CM9: =SUMIF('Octubre 25'!$E$5:$E$23,$A9,'Octubre 25'!$C$5:CQ$25) -> 29000 | CN9: =SUMIF('noviembre 25'!$E$5:$E$23,$A9,'noviembre 25'!$C$5:CQ$25) -> 20000
A10: Agua | B10: =MAX(BN10:ZZ10) -> 15860 | C10: =MIN(AK10:ZZ10) -> 0 | D10: =AVERAGE(AK10:ZZ10) -> 7271.8036 | E10: =SUMIF(Agosto!$E$5:$E$25,$A10,Agosto!$C$5:$C$25) -> 1850 | F10: =SUMIF(Septiembre!$E$5:$E$25,$A10,Septiembre!$C$5:$C$25) -> 3754 | G10: =SUMIF(octubre!$E$5:E$25,$A10,octubre!$C$5:$C$25) -> 3872 | H10: =SUMIF(noviembre!$E$5:F$25,$A10,noviembre!$C$5:$C$25) -> 3942 | I10: =SUMIF(Diciembre!$E$5:CQ$25,$A10,Diciembre!$C$5:$C$25) -> 3916 | J10: =SUMIF(Enero!$E$5:E$25,$A10,Enero!$C$5:$C$25) -> 8230 | K10: =SUMIF(febrero!$E$5:$E$25,$A10,febrero!$C$5:CQ$25) -> 4270 | L10: =SUMIF(Marzo!$E$5:$E$25,$A10,Marzo!$C$5:CQ$25) -> 8590 | M10: =SUMIF(Abril!$E$5:$E$25,$A10,Abril!$C$5:CQ$25) -> 7760 | N10: =SUMIF(Mayo!$E$5:$E$25,$A10,Mayo!$C$5:CQ$25) -> 4790 | O10: =SUMIF(Junio!$E$5:$E$25,$A10,Junio!$C$5:CQ$25) -> 5320 | P10: =SUMIF(Julio!$E$5:$E$25,$A10,Julio!$C$5:CQ$25) -> 5450 | Q10: =SUMIF('Agosto 19'!$E$5:$E$23,$A10,'Agosto 19'!$C$5:CQ$25) -> 4720 | R10: =SUMIF('Septiembre 19'!$E$5:$E$23,$A10,'Septiembre 19'!$C$5:CQ$25) -> 6640 | S10: =SUMIF('Octubre 19'!$E$5:$E$23,$A10,'Octubre 19'!$C$5:CQ$25) -> 5610 | T10: =SUMIF('Noviembre 19'!$E$5:$E$23,$A10,'Noviembre 19'!$C$5:CQ$25) -> 4530 | U10: =SUMIF('Diciembre 19'!$E$5:$E$23,$A10,'Diciembre 19'!$C$5:CQ$25) -> 6020 | V10: =SUMIF('Enero 20'!$E$5:$E$23,$A10,'Enero 20'!$C$5:CQ$25) -> 4860 | W10: =SUMIF('Febrero 20'!$E$5:$E$23,$A10,'Febrero 20'!$C$5:CQ$25) -> 5440 | X10: =SUMIF('Marzo 20'!$E$5:$E$23,$A10,'Marzo 20'!$C$5:CQ$25) -> 6204 | Y10: =SUMIF('Abril 20'!$E$5:$E$23,$A10,'Abril 20'!$C$5:CQ$25) -> 4650 | Z10: =SUMIF('Mayo 20'!$E$5:$E$23,$A10,'Mayo 20'!$C$5:CQ$25) -> 8790 | AA10: =SUMIF('Junio 20'!$E$5:$E$23,$A10,'Junio 20'!$C$5:CQ$25) -> 6400 | AB10: =SUMIF('Julio 20'!$E$5:$E$23,$A10,'Julio 20'!$C$5:CQ$25) -> 3070 | AC10: =SUMIF('Agosto 20'!$E$5:$E$23,$A10,'Agosto 20'!$C$5:CQ$25) -> 7470 | AD10: =SUMIF('Septiembre 20'!$E$5:$E$23,$A10,'Septiembre 20'!$C$5:CQ$25) -> 5600 | AE10: =SUMIF('octubre 20'!$E$5:$E$23,$A10,'octubre 20'!$C$5:CQ$25) -> 6540 | AF10: =SUMIF('noviembre 20'!$E$5:$E$23,$A10,'noviembre 20'!$C$5:CQ$25) -> 5600 | AG10: =SUMIF('diciembre 20'!$E$5:$E$23,$A10,'diciembre 20'!$C$5:CQ$25) -> 5600 | AH10: =SUMIF('enero 21'!$E$5:$E$23,$A10,'enero 21'!$C$5:CQ$25) -> 10140 | AI10: =SUMIF('febrero 21'!$E$5:$E$23,$A10,'febrero 21'!$C$5:CQ$25) -> 5780 | AJ10: =SUMIF('marzo 21'!$E$5:$E$23,$A10,'marzo 21'!$C$5:CQ$25) -> 4600 | AK10: =SUMIF('abril 21'!$E$5:$E$23,$A10,'abril 21'!$C$5:CQ$25) -> 12200 | AL10: =SUMIF('mayo 21'!$E$5:$E$23,$A10,'mayo 21'!$C$5:CQ$25) -> 2690 | AM10: =SUMIF('Junio 21'!$E$5:$E$23,$A10,'Junio 21'!$C$5:CQ$25) -> 1900 | AN10: =SUMIF('Julio 21'!$E$5:$E$23,$A10,'Julio 21'!$C$5:CQ$25) -> 15130 | AO10: =SUMIF('Agosto 21'!$E$5:$E$23,$A10,'Agosto 21'!$C$5:CQ$25) -> 0 | AP10: =SUMIF('Septiembre 21'!$E$5:$E$23,$A10,'Septiembre 21'!$C$5:CQ$25) -> 8200 | AQ10: =SUMIF('Octubre 21'!$E$5:$E$23,$A10,'Octubre 21'!$C$5:CQ$25) -> 5190 | AR10: =SUMIF('Noviembre 21'!$E$5:$E$23,$A10,'Noviembre 21'!$C$5:CQ$25) -> 6350 | AS10: =SUMIF('Diciembre 21'!$E$5:$E$23,$A10,'Noviembre 21'!$C$5:CQ$25) -> 6350 | AT10: =SUMIF('Enero 22'!$E$5:$E$23,$A10,'Enero 22'!$C$5:CQ$25) -> 15700 | AU10: =SUMIF('Febrero 22'!$E$5:$E$23,$A10,'Febrero 22'!$C$5:CQ$25) -> 7580 | AV10: =SUMIF('Marzo 22'!$E$5:$E$23,$A10,'Marzo 22'!$C$5:CQ$25) -> 4160 | AW10: =SUMIF('Abril 22'!$E$5:$E$23,$A10,'Abril 22'!$C$5:CQ$25) -> 4370 | AX10: =SUMIF('Mayo 22'!$E$5:$E$23,$A10,'Mayo 22'!$C$5:CQ$25) -> 10070 | AY10: =SUMIF('Junio 22'!$E$5:$E$23,$A10,'Junio 22'!$C$5:CQ$25) -> 4320 | AZ10: =SUMIF('Julio 22'!$E$5:$E$23,$A10,'Julio 22'!$C$5:CQ$25) -> 4520 | BA10: =SUMIF('Agosto 22'!$E$5:$E$23,$A10,'Agosto 22'!$C$5:CQ$25) -> 2210 | BB10: =SUMIF('septiembre 22'!$E$5:$E$23,$A10,'septiembre 22'!$C$5:CQ$25) -> 3370 | BC10: =SUMIF('octubre 22'!$E$5:$E$23,$A10,'octubre 22'!$C$5:CQ$25) -> 0 | BD10: =SUMIF('noviembre 22'!$E$5:$E$23,$A10,'noviembre 22'!$C$5:CQ$25) -> 5840 | BE10: =SUMIF('diciembre 22'!$E$5:$E$23,$A10,'noviembre 22'!$C$5:CQ$25) -> 5840 | BF10: =SUMIF('Enero 23'!$E$5:$E$23,$A10,'Enero 23'!$C$5:CQ$25) -> 2709 | BG10: =SUMIF('Febrero 23'!$E$5:$E$23,$A10,'Febrero 23'!$C$5:CQ$25) -> 3910 | BH10: =SUMIF('Marzo 23'!$E$5:$E$23,$A10,'Marzo 23'!$C$5:CQ$25) -> 6320 | BI10: =SUMIF('Abril 23'!$E$5:$E$23,$A10,'Abril 23'!$C$5:CQ$25) -> 5020 | BJ10: =SUMIF('Mayo 23'!$E$5:$E$23,$A10,'Mayo 23'!$C$5:CQ$25) -> 4670 | BK10: =SUMIF('Junio 23'!$E$5:$E$23,$A10,'Junio 23'!$C$5:CQ$25) -> 2380 | BL10: =SUMIF('Julio 23'!$E$5:$E$23,$A10,'Julio 23'!$C$5:CQ$25) -> 2380 | BM10: =SUMIF('Agosto 23'!$E$5:$E$23,$A10,'Agosto 23'!$C$5:CQ$25) -> 4890 | BN10: =SUMIF('Septiembre 23'!$E$5:$E$23,$A10,'Septiembre 23'!$C$5:CQ$25) -> 5980 | BO10: =SUMIF('Octubre 23'!$E$5:$E$23,$A10,'Octubre 23'!$C$5:CQ$25) -> 6500 | BP10: =SUMIF('Noviembre 23'!$E$5:$E$23,$A10,'Noviembre 23'!$C$5:CQ$25) -> 10770 | BQ10: =SUMIF('Diciembre 23'!$E$5:$E$23,$A10,'Diciembre 23'!$C$5:CQ$25) -> 7640 | BR10: =SUMIF('Enero 24'!$E$5:$E$23,$A10,'Enero 24'!$C$5:CQ$25) -> 11280 | BS10: =SUMIF('Febrero 24'!$E$5:$E$23,$A10,'Febrero 24'!$C$5:CQ$25) -> 10880 | BT10: =SUMIF('Marzo 24'!$E$5:$E$23,$A10,'Marzo 24'!$C$5:CQ$25) -> 8340 | BU10: =SUMIF('abril 24'!$E$5:$E$23,$A10,'abril 24'!$C$5:CQ$25) -> 10320 | BV10: =SUMIF('Mayo 24'!$E$5:$E$23,$A10,'Mayo 24'!$C$5:CQ$25) -> 7490 | BW10: =SUMIF('Junio 24'!$E$5:$E$23,$A10,'Junio 24'!$C$5:CQ$25) -> 10320 | BX10: =SUMIF('Julio 24'!$E$5:$E$23,$A10,'Julio 24'!$C$5:CQ$25) -> 7490 | BY10: =SUMIF('Agosto 24'!$E$5:$E$23,$A10,'Agosto 24'!$C$5:CQ$25) -> 9100 | BZ10: =SUMIF('Septiembre 24'!$E$5:$E$23,$A10,'Septiembre 24'!$C$5:CQ$25) -> 7810 | CA10: =SUMIF('Octubre 24'!$E$5:$E$23,$A10,'Octubre 24'!$C$5:CQ$25) -> 7950 | CB10: =SUMIF('Noviembre 24'!$E$5:$E$23,$A10,'Noviembre 24'!$C$5:CQ$25) -> 10180 | CC10: =SUMIF('Diciembre 24'!$E$5:$E$23,$A10,'Diciembre 24'!$C$5:CQ$25) -> 4960 | CD10: =SUMIF('Enero 25'!$E$5:$E$23,$A10,'Enero 25'!$C$5:CQ$25) -> 8362 | CE10: =SUMIF('febrero 25'!$E$5:$E$23,$A10,'febrero 25'!$C$5:CQ$25) -> 7500 | CF10: =SUMIF('marzo 25'!$E$5:$E$23,$A10,'marzo 25'!$C$5:CQ$25) -> 15860 | CG10: =SUMIF('abril 25'!$E$5:$E$23,$A10,'abril 25'!$C$5:CQ$25) -> 12100 | CH10: =SUMIF('Mayo 25'!$E$5:$E$23,$A10,'Mayo 25'!$C$5:CQ$25) -> 12900 | CI10: =SUMIF('Junio 25'!$E$5:$E$23,$A10,'Junio 25'!$C$5:CQ$25) -> 10900 | CJ10: =SUMIF('Julio 25'!$E$5:$E$23,$A10,'Julio 25'!$C$5:CQ$25) -> 10900 | CK10: =SUMIF('Agosto 25'!$E$5:$E$23,$A10,'Agosto 25'!$C$5:CQ$25) -> 9470 | CL10: =SUMIF('Septiembre 25'!$E$5:$E$23,$A10,'Septiembre 25'!$C$5:CQ$25) -> 8050 | CM10: =SUMIF('Octubre 25'!$E$5:$E$23,$A10,'Octubre 25'!$C$5:CQ$25) -> 9900 | CN10: =SUMIF('noviembre 25'!$E$5:$E$23,$A10,'noviembre 25'!$C$5:CQ$25) -> 6000
A11: Gas | B11: =MAX(BN11:ZZ11) -> 8600 | C11: =MIN(AK11:ZZ11) -> 0 | D11: =AVERAGE(AK11:ZZ11) -> 2150.5714 | E11: =SUMIF(Agosto!$E$5:$E$25,$A11,Agosto!$C$5:$C$25) -> 5000 | F11: =SUMIF(Septiembre!$E$5:$E$25,$A11,Septiembre!$C$5:$C$25) -> 0 | G11: =SUMIF(octubre!$E$5:E$25,$A11,octubre!$C$5:$C$25) -> 2708 | H11: =SUMIF(noviembre!$E$5:F$25,$A11,noviembre!$C$5:$C$25) -> 0 | I11: =SUMIF(Diciembre!$E$5:CQ$25,$A11,Diciembre!$C$5:$C$25) -> 1399 | J11: =SUMIF(Enero!$E$5:E$25,$A11,Enero!$C$5:$C$25) -> 0 | K11: =SUMIF(febrero!$E$5:$E$25,$A11,febrero!$C$5:CQ$25) -> 1329 | L11: =SUMIF(Marzo!$E$5:$E$25,$A11,Marzo!$C$5:CQ$25) -> 0 | M11: =SUMIF(Abril!$E$5:$E$25,$A11,Abril!$C$5:CQ$25) -> 2686 | N11: =SUMIF(Mayo!$E$5:$E$25,$A11,Mayo!$C$5:CQ$25) -> 0 | O11: =SUMIF(Junio!$E$5:$E$25,$A11,Junio!$C$5:CQ$25) -> 0 | P11: =SUMIF(Julio!$E$5:$E$25,$A11,Julio!$C$5:CQ$25) -> 0 | Q11: =SUMIF('Agosto 19'!$E$5:$E$23,$A11,'Agosto 19'!$C$5:CQ$25) -> 1376 | R11: =SUMIF('Septiembre 19'!$E$5:$E$23,$A11,'Septiembre 19'!$C$5:CQ$25) -> 0 | S11: =SUMIF('Octubre 19'!$E$5:$E$23,$A11,'Octubre 19'!$C$5:CQ$25) -> 1390 | T11: =SUMIF('Noviembre 19'!$E$5:$E$23,$A11,'Noviembre 19'!$C$5:CQ$25) -> 0 | U11: =SUMIF('Diciembre 19'!$E$5:$E$23,$A11,'Diciembre 19'!$C$5:CQ$25) -> 1348 | V11: =SUMIF('Enero 20'!$E$5:$E$23,$A11,'Enero 20'!$C$5:CQ$25) -> 1348 | W11: =SUMIF('Febrero 20'!$E$5:$E$23,$A11,'Febrero 20'!$C$5:CQ$25) -> 1348 | X11: =SUMIF('Marzo 20'!$E$5:$E$23,$A11,'Marzo 20'!$C$5:CQ$25) -> 2860 | Y11: =SUMIF('Abril 20'!$E$5:$E$23,$A11,'Abril 20'!$C$5:CQ$25) -> 0 | Z11: =SUMIF('Mayo 20'!$E$5:$E$23,$A11,'Mayo 20'!$C$5:CQ$25) -> 2794 | AA11: =SUMIF('Junio 20'!$E$5:$E$23,$A11,'Junio 20'!$C$5:CQ$25) -> 0 | AB11: =SUMIF('Julio 20'!$E$5:$E$23,$A11,'Julio 20'!$C$5:CQ$25) -> 0 | AC11: =SUMIF('Agosto 20'!$E$5:$E$23,$A11,'Agosto 20'!$C$5:CQ$25) -> 7092 | AD11: =SUMIF('Septiembre 20'!$E$5:$E$23,$A11,'Septiembre 20'!$C$5:CQ$25) -> 0 | AE11: =SUMIF('octubre 20'!$E$5:$E$23,$A11,'octubre 20'!$C$5:CQ$25) -> 4176 | AF11: =SUMIF('noviembre 20'!$E$5:$E$23,$A11,'noviembre 20'!$C$5:CQ$25) -> 0 | AG11: =SUMIF('diciembre 20'!$E$5:$E$23,$A11,'diciembre 20'!$C$5:CQ$25) -> 2745 | AH11: =SUMIF('enero 21'!$E$5:$E$23,$A11,'enero 21'!$C$5:CQ$25) -> 0 | AI11: =SUMIF('febrero 21'!$E$5:$E$23,$A11,'febrero 21'!$C$5:CQ$25) -> 1470 | AJ11: =SUMIF('marzo 21'!$E$5:$E$23,$A11,'marzo 21'!$C$5:CQ$25) -> 0 | AK11: =SUMIF('abril 21'!$E$5:$E$23,$A11,'abril 21'!$C$5:CQ$25) -> 0 | AL11: =SUMIF('mayo 21'!$E$5:$E$23,$A11,'mayo 21'!$C$5:CQ$25) -> 4484 | AM11: =SUMIF('Junio 21'!$E$5:$E$23,$A11,'Junio 21'!$C$5:CQ$25) -> 0 | AN11: =SUMIF('Julio 21'!$E$5:$E$23,$A11,'Julio 21'!$C$5:CQ$25) -> 4562 | AO11: =SUMIF('Agosto 21'!$E$5:$E$23,$A11,'Agosto 21'!$C$5:CQ$25) -> 0 | AP11: =SUMIF('Septiembre 21'!$E$5:$E$23,$A11,'Septiembre 21'!$C$5:CQ$25) -> 3233 | AQ11: =SUMIF('Octubre 21'!$E$5:$E$23,$A11,'Octubre 21'!$C$5:CQ$25) -> 0 | AR11: =SUMIF('Noviembre 21'!$E$5:$E$23,$A11,'Noviembre 21'!$C$5:CQ$25) -> 3382 | AS11: =SUMIF('Diciembre 21'!$E$5:$E$23,$A11,'Noviembre 21'!$C$5:CQ$25) -> 3382 | AT11: =SUMIF('Enero 22'!$E$5:$E$23,$A11,'Enero 22'!$C$5:CQ$25) -> 1600 | AU11: =SUMIF('Febrero 22'!$E$5:$E$23,$A11,'Febrero 22'!$C$5:CQ$25) -> 0 | AV11: =SUMIF('Marzo 22'!$E$5:$E$23,$A11,'Marzo 22'!$C$5:CQ$25) -> 1689 | AW11: =SUMIF('Abril 22'!$E$5:$E$23,$A11,'Abril 22'!$C$5:CQ$25) -> 0 | AX11: =SUMIF('Mayo 22'!$E$5:$E$23,$A11,'Mayo 22'!$C$5:CQ$25) -> 1800 | AY11: =SUMIF('Junio 22'!$E$5:$E$23,$A11,'Junio 22'!$C$5:CQ$25) -> 0 | AZ11: =SUMIF('Julio 22'!$E$5:$E$23,$A11,'Julio 22'!$C$5:CQ$25) -> 0 | BA11: =SUMIF('Agosto 22'!$E$5:$E$23,$A11,'Agosto 22'!$C$5:CQ$25) -> 0 | BB11: =SUMIF('septiembre 22'!$E$5:$E$23,$A11,'septiembre 22'!$C$5:CQ$25) -> 1824 | BC11: =SUMIF('octubre 22'!$E$5:$E$23,$A11,'octubre 22'!$C$5:CQ$25) -> 0 | BD11: =SUMIF('noviembre 22'!$E$5:$E$23,$A11,'noviembre 22'!$C$5:CQ$25) -> 0 | BE11: =SUMIF('diciembre 22'!$E$5:$E$23,$A11,'noviembre 22'!$C$5:CQ$25) -> 0 | BF11: =SUMIF('Enero 23'!$E$5:$E$23,$A11,'Enero 23'!$C$5:CQ$25) -> 0 | BG11: =SUMIF('Febrero 23'!$E$5:$E$23,$A11,'Febrero 23'!$C$5:CQ$25) -> 0 | BH11: =SUMIF('Marzo 23'!$E$5:$E$23,$A11,'Marzo 23'!$C$5:CQ$25) -> 0 | BI11: =SUMIF('Abril 23'!$E$5:$E$23,$A11,'Abril 23'!$C$5:CQ$25) -> 1887 | BJ11: =SUMIF('Mayo 23'!$E$5:$E$23,$A11,'Mayo 23'!$C$5:CQ$25) -> 0 | BK11: =SUMIF('Junio 23'!$E$5:$E$23,$A11,'Junio 23'!$C$5:CQ$25) -> 0 | BL11: =SUMIF('Julio 23'!$E$5:$E$23,$A11,'Julio 23'!$C$5:CQ$25) -> 0 | BM11: =SUMIF('Agosto 23'!$E$5:$E$23,$A11,'Agosto 23'!$C$5:CQ$25) -> 0 | BN11: =SUMIF('Septiembre 23'!$E$5:$E$23,$A11,'Septiembre 23'!$C$5:CQ$25) -> 0 | BO11: =SUMIF('Octubre 23'!$E$5:$E$23,$A11,'Octubre 23'!$C$5:CQ$25) -> 0 | BP11: =SUMIF('Noviembre 23'!$E$5:$E$23,$A11,'Noviembre 23'!$C$5:CQ$25) -> 0 | BQ11: =SUMIF('Diciembre 23'!$E$5:$E$23,$A11,'Diciembre 23'!$C$5:CQ$25) -> 0 | BR11: =SUMIF('Enero 24'!$E$5:$E$23,$A11,'Enero 24'!$C$5:CQ$25) -> 0 | BS11: =SUMIF('Febrero 24'!$E$5:$E$23,$A11,'Febrero 24'!$C$5:CQ$25) -> 0 | BT11: =SUMIF('Marzo 24'!$E$5:$E$23,$A11,'Marzo 24'!$C$5:CQ$25) -> 3958 | BU11: =SUMIF('abril 24'!$E$5:$E$23,$A11,'abril 24'!$C$5:CQ$25) -> 0 | BV11: =SUMIF('Mayo 24'!$E$5:$E$23,$A11,'Mayo 24'!$C$5:CQ$25) -> 6321 | BW11: =SUMIF('Junio 24'!$E$5:$E$23,$A11,'Junio 24'!$C$5:CQ$25) -> 0 | BX11: =SUMIF('Julio 24'!$E$5:$E$23,$A11,'Julio 24'!$C$5:CQ$25) -> 6300 | BY11: =SUMIF('Agosto 24'!$E$5:$E$23,$A11,'Agosto 24'!$C$5:CQ$25) -> 0 | BZ11: =SUMIF('Septiembre 24'!$E$5:$E$23,$A11,'Septiembre 24'!$C$5:CQ$25) -> 5873 | CA11: =SUMIF('Octubre 24'!$E$5:$E$23,$A11,'Octubre 24'!$C$5:CQ$25) -> 5873 | CB11: =SUMIF('Noviembre 24'!$E$5:$E$23,$A11,'Noviembre 24'!$C$5:CQ$25) -> 5873 | CC11: =SUMIF('Diciembre 24'!$E$5:$E$23,$A11,'Diciembre 24'!$C$5:CQ$25) -> 5873 | CD11: =SUMIF('Enero 25'!$E$5:$E$23,$A11,'Enero 25'!$C$5:CQ$25) -> 2000 | CE11: =SUMIF('febrero 25'!$E$5:$E$23,$A11,'febrero 25'!$C$5:CQ$25) -> 2000 | CF11: =SUMIF('marzo 25'!$E$5:$E$23,$A11,'marzo 25'!$C$5:CQ$25) -> 4150 | CG11: =SUMIF('abril 25'!$E$5:$E$23,$A11,'abril 25'!$C$5:CQ$25) -> 4150 | CH11: =SUMIF('Mayo 25'!$E$5:$E$23,$A11,'Mayo 25'!$C$5:CQ$25) -> 6318 | CI11: =SUMIF('Junio 25'!$E$5:$E$23,$A11,'Junio 25'!$C$5:CQ$25) -> 0 | CJ11: =SUMIF('Julio 25'!$E$5:$E$23,$A11,'Julio 25'!$C$5:CQ$25) -> 8600 | CK11: =SUMIF('Agosto 25'!$E$5:$E$23,$A11,'Agosto 25'!$C$5:CQ$25) -> 8600 | CL11: =SUMIF('Septiembre 25'!$E$5:$E$23,$A11,'Septiembre 25'!$C$5:CQ$25) -> 6300 | CM11: =SUMIF('Octubre 25'!$E$5:$E$23,$A11,'Octubre 25'!$C$5:CQ$25) -> 6300 | CN11: =SUMIF('noviembre 25'!$E$5:$E$23,$A11,'noviembre 25'!$C$5:CQ$25) -> 4100
A12: Reparaciones y hogar | B12: =MAX(BN12:ZZ12) -> 0 | C12: =MIN(AK12:ZZ12) -> 0 | D12: =AVERAGE(AK12:ZZ12) -> 0 | E12: =SUMIF(Agosto!$E$5:$E$25,$A12,Agosto!$C$5:$C$25) -> 211060 | F12: =SUMIF(Septiembre!$E$5:$E$25,$A12,Septiembre!$C$5:$C$25) -> 60000 | G12: =SUMIF(octubre!$E$5:E$25,$A12,octubre!$C$5:$C$25) -> 72885 | H12: =SUMIF(noviembre!$E$5:F$25,$A12,noviembre!$C$5:$C$25) -> 10750 | I12: =SUMIF(Diciembre!$E$5:CQ$25,$A12,Diciembre!$C$5:$C$25) -> 41000 | J12: =SUMIF(Enero!$E$5:E$25,$A12,Enero!$C$5:$C$25) -> 19209 | K12: =SUMIF(febrero!$E$5:$E$25,$A12,febrero!$C$5:CQ$25) -> 0 | L12: =SUMIF(Marzo!$E$5:$E$25,$A12,Marzo!$C$5:CQ$25) -> 0 | M12: =SUMIF(Abril!$E$5:$E$25,$A12,Abril!$C$5:CQ$25) -> 0 | N12: =SUMIF(Mayo!$E$5:$E$25,$A12,Mayo!$C$5:CQ$25) -> 0 | O12: =SUMIF(Junio!$E$5:$E$25,$A12,Junio!$C$5:CQ$25) -> 0 | P12: =SUMIF(Julio!$E$5:$E$25,$A12,Julio!$C$5:CQ$25) -> 0 | Q12: =SUMIF('Agosto 19'!$E$5:$E$23,$A12,'Agosto 19'!$C$5:CQ$25) -> 0 | R12: =SUMIF('Septiembre 19'!$E$5:$E$23,$A12,'Septiembre 19'!$C$5:CQ$25) -> 0 | S12: =SUMIF('Octubre 19'!$E$5:$E$23,$A12,'Octubre 19'!$C$5:CQ$25) -> 0 | T12: =SUMIF('Noviembre 19'!$E$5:$E$23,$A12,'Noviembre 19'!$C$5:CQ$25) -> 0 | U12: =SUMIF('Diciembre 19'!$E$5:$E$23,$A12,'Diciembre 19'!$C$5:CQ$25) -> 0 | V12: =SUMIF('Enero 20'!$E$5:$E$23,$A12,'Enero 20'!$C$5:CQ$25) -> 0 | W12: =SUMIF('Febrero 20'!$E$5:$E$23,$A12,'Febrero 20'!$C$5:CQ$25) -> 0 | X12: =SUMIF('Marzo 20'!$E$5:$E$23,$A12,'Marzo 20'!$C$5:CQ$25) -> 0 | Y12: =SUMIF('Abril 20'!$E$5:$E$23,$A12,'Abril 20'!$C$5:CQ$25) -> 0 | Z12: =SUMIF('Mayo 20'!$E$5:$E$23,$A12,'Mayo 20'!$C$5:CQ$25) -> 0 | AA12: =SUMIF('Junio 20'!$E$5:$E$23,$A12,'Junio 20'!$C$5:CQ$25) -> 0 | AB12: =SUMIF('Julio 20'!$E$5:$E$23,$A12,'Julio 20'!$C$5:CQ$25) -> 0 | AC12: =SUMIF('Agosto 20'!$E$5:$E$23,$A12,'Agosto 20'!$C$5:CQ$25) -> 0 | AD12: =SUMIF('Septiembre 20'!$E$5:$E$23,$A12,'Septiembre 20'!$C$5:CQ$25) -> 0 | AE12: =SUMIF('octubre 20'!$E$5:$E$23,$A12,'octubre 20'!$C$5:CQ$25) -> 0 | AF12: =SUMIF('noviembre 20'!$E$5:$E$23,$A12,'noviembre 20'!$C$5:CQ$25) -> 0 | AG12: =SUMIF('diciembre 20'!$E$5:$E$23,$A12,'diciembre 20'!$C$5:CQ$25) -> 0 | AH12: =SUMIF('enero 21'!$E$5:$E$23,$A12,'enero 21'!$C$5:CQ$25) -> 0 | AI12: =SUMIF('febrero 21'!$E$5:$E$23,$A12,'febrero 21'!$C$5:CQ$25) -> 0 | AJ12: =SUMIF('marzo 21'!$E$5:$E$23,$A12,'marzo 21'!$C$5:CQ$25) -> 0 | AK12: =SUMIF('abril 21'!$E$5:$E$23,$A12,'abril 21'!$C$5:CQ$25) -> 0 | AL12: =SUMIF('mayo 21'!$E$5:$E$23,$A12,'mayo 21'!$C$5:CQ$25) -> 0 | AM12: =SUMIF('Junio 21'!$E$5:$E$23,$A12,'Junio 21'!$C$5:CQ$25) -> 0 | AN12: =SUMIF('Julio 21'!$E$5:$E$23,$A12,'Julio 21'!$C$5:CQ$25) -> 0 | AO12: =SUMIF('Agosto 21'!$E$5:$E$23,$A12,'Agosto 21'!$C$5:CQ$25) -> 0 | AP12: =SUMIF('Septiembre 21'!$E$5:$E$23,$A12,'Septiembre 21'!$C$5:CQ$25) -> 0 | AQ12: =SUMIF('Octubre 21'!$E$5:$E$23,$A12,'Octubre 21'!$C$5:CQ$25) -> 0 | AR12: =SUMIF('Noviembre 21'!$E$5:$E$23,$A12,'Noviembre 21'!$C$5:CQ$25) -> 0 | AS12: =SUMIF('Diciembre 21'!$E$5:$E$23,$A12,'Noviembre 21'!$C$5:CQ$25) -> 0 | AT12: =SUMIF('Enero 22'!$E$5:$E$23,$A12,'Enero 22'!$C$5:CQ$25) -> 0 | AU12: =SUMIF('Febrero 22'!$E$5:$E$23,$A12,'Febrero 22'!$C$5:CQ$25) -> 0 | AV12: =SUMIF('Marzo 22'!$E$5:$E$23,$A12,'Marzo 22'!$C$5:CQ$25) -> 0 | AW12: =SUMIF('Abril 22'!$E$5:$E$23,$A12,'Abril 22'!$C$5:CQ$25) -> 0 | AX12: =SUMIF('Mayo 22'!$E$5:$E$23,$A12,'Mayo 22'!$C$5:CQ$25) -> 0 | AY12: =SUMIF('Junio 22'!$E$5:$E$23,$A12,'Junio 22'!$C$5:CQ$25) -> 0 | AZ12: =SUMIF('Julio 22'!$E$5:$E$23,$A12,'Julio 22'!$C$5:CQ$25) -> 0 | BA12: =SUMIF('Agosto 22'!$E$5:$E$23,$A12,'Agosto 22'!$C$5:CQ$25) -> 0 | BB12: =SUMIF('septiembre 22'!$E$5:$E$23,$A12,'septiembre 22'!$C$5:CQ$25) -> 0 | BC12: =SUMIF('octubre 22'!$E$5:$E$23,$A12,'octubre 22'!$C$5:CQ$25) -> 0 | BD12: =SUMIF('noviembre 22'!$E$5:$E$23,$A12,'noviembre 22'!$C$5:CQ$25) -> 0 | BE12: =SUMIF('diciembre 22'!$E$5:$E$23,$A12,'noviembre 22'!$C$5:CQ$25) -> 0 | BF12: =SUMIF('Enero 23'!$E$5:$E$23,$A12,'Enero 23'!$C$5:CQ$25) -> 0 | BG12: =SUMIF('Febrero 23'!$E$5:$E$23,$A12,'Febrero 23'!$C$5:CQ$25) -> 0 | BH12: =SUMIF('Marzo 23'!$E$5:$E$23,$A12,'Marzo 23'!$C$5:CQ$25) -> 0 | BI12: =SUMIF('Abril 23'!$E$5:$E$23,$A12,'Abril 23'!$C$5:CQ$25) -> 0 | BJ12: =SUMIF('Mayo 23'!$E$5:$E$23,$A12,'Mayo 23'!$C$5:CQ$25) -> 0 | BK12: =SUMIF('Junio 23'!$E$5:$E$23,$A12,'Junio 23'!$C$5:CQ$25) -> 0 | BL12: =SUMIF('Julio 23'!$E$5:$E$23,$A12,'Julio 23'!$C$5:CQ$25) -> 0 | BM12: =SUMIF('Agosto 23'!$E$5:$E$23,$A12,'Agosto 23'!$C$5:CQ$25) -> 0 | BN12: =SUMIF('Septiembre 23'!$E$5:$E$23,$A12,'Septiembre 23'!$C$5:CQ$25) -> 0 | BO12: =SUMIF('Octubre 23'!$E$5:$E$23,$A12,'Octubre 23'!$C$5:CQ$25) -> 0 | BP12: =SUMIF('Noviembre 23'!$E$5:$E$23,$A12,'Noviembre 23'!$C$5:CQ$25) -> 0 | BQ12: =SUMIF('Diciembre 23'!$E$5:$E$23,$A12,'Diciembre 23'!$C$5:CQ$25) -> 0 | BR12: =SUMIF('Enero 24'!$E$5:$E$23,$A12,'Enero 24'!$C$5:CQ$25) -> 0 | BS12: =SUMIF('Febrero 24'!$E$5:$E$23,$A12,'Febrero 24'!$C$5:CQ$25) -> 0 | BT12: =SUMIF('Marzo 24'!$E$5:$E$23,$A12,'Marzo 24'!$C$5:CQ$25) -> 0 | BU12: =SUMIF('abril 24'!$E$5:$E$23,$A12,'abril 24'!$C$5:CQ$25) -> 0 | BV12: =SUMIF('Mayo 24'!$E$5:$E$23,$A12,'Mayo 24'!$C$5:CQ$25) -> 0 | BW12: =SUMIF('Junio 24'!$E$5:$E$23,$A12,'Junio 24'!$C$5:CQ$25) -> 0 | BX12: =SUMIF('Julio 24'!$E$5:$E$23,$A12,'Julio 24'!$C$5:CQ$25) -> 0 | BY12: =SUMIF('Agosto 24'!$E$5:$E$23,$A12,'Agosto 24'!$C$5:CQ$25) -> 0 | BZ12: =SUMIF('Septiembre 24'!$E$5:$E$23,$A12,'Septiembre 24'!$C$5:CQ$25) -> 0 | CA12: =SUMIF('Octubre 24'!$E$5:$E$23,$A12,'Octubre 24'!$C$5:CQ$25) -> 0 | CB12: =SUMIF('Noviembre 24'!$E$5:$E$23,$A12,'Noviembre 24'!$C$5:CQ$25) -> 0 | CC12: =SUMIF('Diciembre 24'!$E$5:$E$23,$A12,'Diciembre 24'!$C$5:CQ$25) -> 0 | CD12: =SUMIF('Enero 25'!$E$5:$E$23,$A12,'Enero 25'!$C$5:CQ$25) -> 0 | CE12: =SUMIF('febrero 25'!$E$5:$E$23,$A12,'febrero 25'!$C$5:CQ$25) -> 0 | CF12: =SUMIF('marzo 25'!$E$5:$E$23,$A12,'marzo 25'!$C$5:CQ$25) -> 0 | CG12: =SUMIF('abril 25'!$E$5:$E$23,$A12,'abril 25'!$C$5:CQ$25) -> 0 | CH12: =SUMIF('Mayo 25'!$E$5:$E$23,$A12,'Mayo 25'!$C$5:CQ$25) -> 0 | CI12: =SUMIF('Junio 25'!$E$5:$E$23,$A12,'Junio 25'!$C$5:CQ$25) -> 0 | CJ12: =SUMIF('Julio 25'!$E$5:$E$23,$A12,'Julio 25'!$C$5:CQ$25) -> 0 | CK12: =SUMIF('Agosto 25'!$E$5:$E$23,$A12,'Agosto 25'!$C$5:CQ$25) -> 0 | CL12: =SUMIF('Septiembre 25'!$E$5:$E$23,$A12,'Septiembre 25'!$C$5:CQ$25) -> 0 | CM12: =SUMIF('Octubre 25'!$E$5:$E$23,$A12,'Octubre 25'!$C$5:CQ$25) -> 0 | CN12: =SUMIF('noviembre 25'!$E$5:$E$23,$A12,'noviembre 25'!$C$5:CQ$25) -> 0
A13: Lavandería | B13: =MAX(BN13:ZZ13) -> 0 | C13: =MIN(AK13:ZZ13) -> 0 | D13: =AVERAGE(AK13:ZZ13) -> 0 | E13: =SUMIF(Agosto!$E$5:$E$25,$A13,Agosto!$C$5:$C$25) -> 22000 | F13: =SUMIF(Septiembre!$E$5:$E$25,$A13,Septiembre!$C$5:$C$25) -> 20000 | G13: =SUMIF(octubre!$E$5:E$25,$A13,octubre!$C$5:$C$25) -> 53600 | H13: =SUMIF(noviembre!$E$5:F$25,$A13,noviembre!$C$5:$C$25) -> 20000 | I13: =SUMIF(Diciembre!$E$5:CQ$25,$A13,Diciembre!$C$5:$C$25) -> 0 | J13: =SUMIF(Enero!$E$5:E$25,$A13,Enero!$C$5:$C$25) -> 20000 | K13: =SUMIF(febrero!$E$5:$E$25,$A13,febrero!$C$5:CQ$25) -> 20000 | L13: =SUMIF(Marzo!$E$5:$E$25,$A13,Marzo!$C$5:CQ$25) -> 20000 | M13: =SUMIF(Abril!$E$5:$E$25,$A13,Abril!$C$5:CQ$25) -> 10000 | N13: =SUMIF(Mayo!$E$5:$E$25,$A13,Mayo!$C$5:CQ$25) -> 10000 | O13: =SUMIF(Junio!$E$5:$E$25,$A13,Junio!$C$5:CQ$25) -> 10000 | P13: =SUMIF(Julio!$E$5:$E$25,$A13,Julio!$C$5:CQ$25) -> 20000 | Q13: =SUMIF('Agosto 19'!$E$5:$E$23,$A13,'Agosto 19'!$C$5:CQ$25) -> 30000 | R13: =SUMIF('Septiembre 19'!$E$5:$E$23,$A13,'Septiembre 19'!$C$5:CQ$25) -> 20000 | S13: =SUMIF('Octubre 19'!$E$5:$E$23,$A13,'Octubre 19'!$C$5:CQ$25) -> 20000 | T13: =SUMIF('Noviembre 19'!$E$5:$E$23,$A13,'Noviembre 19'!$C$5:CQ$25) -> 20000 | U13: =SUMIF('Diciembre 19'!$E$5:$E$23,$A13,'Diciembre 19'!$C$5:CQ$25) -> 20000 | V13: =SUMIF('Enero 20'!$E$5:$E$23,$A13,'Enero 20'!$C$5:CQ$25) -> 20000 | W13: =SUMIF('Febrero 20'!$E$5:$E$23,$A13,'Febrero 20'!$C$5:CQ$25) -> 20000 | X13: =SUMIF('Marzo 20'!$E$5:$E$23,$A13,'Marzo 20'!$C$5:CQ$25) -> 20000 | Y13: =SUMIF('Abril 20'!$E$5:$E$23,$A13,'Abril 20'!$C$5:CQ$25) -> 20000 | Z13: =SUMIF('Mayo 20'!$E$5:$E$23,$A13,'Mayo 20'!$C$5:CQ$25) -> 20000 | AA13: =SUMIF('Junio 20'!$E$5:$E$23,$A13,'Junio 20'!$C$5:CQ$25) -> 20000 | AB13: =SUMIF('Julio 20'!$E$5:$E$23,$A13,'Julio 20'!$C$5:CQ$25) -> 20000 | AC13: =SUMIF('Agosto 20'!$E$5:$E$23,$A13,'Agosto 20'!$C$5:CQ$25) -> 29000 | AD13: =SUMIF('Septiembre 20'!$E$5:$E$23,$A13,'Septiembre 20'!$C$5:CQ$25) -> 20000 | AE13: =SUMIF('octubre 20'!$E$5:$E$23,$A13,'octubre 20'!$C$5:CQ$25) -> 0 | AF13: =SUMIF('noviembre 20'!$E$5:$E$23,$A13,'noviembre 20'!$C$5:CQ$25) -> 20000 | AG13: =SUMIF('diciembre 20'!$E$5:$E$23,$A13,'diciembre 20'!$C$5:CQ$25) -> 20000 | AH13: =SUMIF('enero 21'!$E$5:$E$23,$A13,'enero 21'!$C$5:CQ$25) -> 10000 | AI13: =SUMIF('febrero 21'!$E$5:$E$23,$A13,'febrero 21'!$C$5:CQ$25) -> 0 | AJ13: =SUMIF('marzo 21'!$E$5:$E$23,$A13,'marzo 21'!$C$5:CQ$25) -> 0 | AK13: =SUMIF('abril 21'!$E$5:$E$23,$A13,'abril 21'!$C$5:CQ$25) -> 0 | AL13: =SUMIF('mayo 21'!$E$5:$E$23,$A13,'mayo 21'!$C$5:CQ$25) -> 0 | AM13: =SUMIF('Junio 21'!$E$5:$E$23,$A13,'Junio 21'!$C$5:CQ$25) -> 0 | AN13: =SUMIF('Julio 21'!$E$5:$E$23,$A13,'Julio 21'!$C$5:CQ$25) -> 0 | AO13: =SUMIF('Agosto 21'!$E$5:$E$23,$A13,'Agosto 21'!$C$5:CQ$25) -> 0 | AP13: =SUMIF('Septiembre 21'!$E$5:$E$23,$A13,'Septiembre 21'!$C$5:CQ$25) -> 0 | AQ13: =SUMIF('Octubre 21'!$E$5:$E$23,$A13,'Octubre 21'!$C$5:CQ$25) -> 0 | AR13: =SUMIF('Noviembre 21'!$E$5:$E$23,$A13,'Noviembre 21'!$C$5:CQ$25) -> 0 | AS13: =SUMIF('Diciembre 21'!$E$5:$E$23,$A13,'Noviembre 21'!$C$5:CQ$25) -> 0 | AT13: =SUMIF('Enero 22'!$E$5:$E$23,$A13,'Enero 22'!$C$5:CQ$25) -> 0 | AU13: =SUMIF('Febrero 22'!$E$5:$E$23,$A13,'Febrero 22'!$C$5:CQ$25) -> 0 | AV13: =SUMIF('Marzo 22'!$E$5:$E$23,$A13,'Marzo 22'!$C$5:CQ$25) -> 0 | AW13: =SUMIF('Abril 22'!$E$5:$E$23,$A13,'Abril 22'!$C$5:CQ$25) -> 0 | AX13: =SUMIF('Mayo 22'!$E$5:$E$23,$A13,'Mayo 22'!$C$5:CQ$25) -> 0 | AY13: =SUMIF('Junio 22'!$E$5:$E$23,$A13,'Junio 22'!$C$5:CQ$25) -> 0 | AZ13: =SUMIF('Julio 22'!$E$5:$E$23,$A13,'Julio 22'!$C$5:CQ$25) -> 0 | BA13: =SUMIF('Agosto 22'!$E$5:$E$23,$A13,'Agosto 22'!$C$5:CQ$25) -> 0 | BB13: =SUMIF('septiembre 22'!$E$5:$E$23,$A13,'septiembre 22'!$C$5:CQ$25) -> 0 | BC13: =SUMIF('octubre 22'!$E$5:$E$23,$A13,'octubre 22'!$C$5:CQ$25) -> 0 | BD13: =SUMIF('noviembre 22'!$E$5:$E$23,$A13,'noviembre 22'!$C$5:CQ$25) -> 0 | BE13: =SUMIF('diciembre 22'!$E$5:$E$23,$A13,'noviembre 22'!$C$5:CQ$25) -> 0 | BF13: =SUMIF('Enero 23'!$E$5:$E$23,$A13,'Enero 23'!$C$5:CQ$25) -> 0 | BG13: =SUMIF('Febrero 23'!$E$5:$E$23,$A13,'Febrero 23'!$C$5:CQ$25) -> 0 | BH13: =SUMIF('Marzo 23'!$E$5:$E$23,$A13,'Marzo 23'!$C$5:CQ$25) -> 0 | BI13: =SUMIF('Abril 23'!$E$5:$E$23,$A13,'Abril 23'!$C$5:CQ$25) -> 0 | BJ13: =SUMIF('Mayo 23'!$E$5:$E$23,$A13,'Mayo 23'!$C$5:CQ$25) -> 0 | BK13: =SUMIF('Junio 23'!$E$5:$E$23,$A13,'Junio 23'!$C$5:CQ$25) -> 0 | BL13: =SUMIF('Julio 23'!$E$5:$E$23,$A13,'Julio 23'!$C$5:CQ$25) -> 0 | BM13: =SUMIF('Agosto 23'!$E$5:$E$23,$A13,'Agosto 23'!$C$5:CQ$25) -> 0 | BN13: =SUMIF('Septiembre 23'!$E$5:$E$23,$A13,'Septiembre 23'!$C$5:CQ$25) -> 0 | BO13: =SUMIF('Octubre 23'!$E$5:$E$23,$A13,'Octubre 23'!$C$5:CQ$25) -> 0 | BP13: =SUMIF('Noviembre 23'!$E$5:$E$23,$A13,'Noviembre 23'!$C$5:CQ$25) -> 0 | BQ13: =SUMIF('Diciembre 23'!$E$5:$E$23,$A13,'Diciembre 23'!$C$5:CQ$25) -> 0 | BR13: =SUMIF('Enero 24'!$E$5:$E$23,$A13,'Enero 24'!$C$5:CQ$25) -> 0 | BS13: =SUMIF('Febrero 24'!$E$5:$E$23,$A13,'Febrero 24'!$C$5:CQ$25) -> 0 | BT13: =SUMIF('Marzo 24'!$E$5:$E$23,$A13,'Marzo 24'!$C$5:CQ$25) -> 0 | BU13: =SUMIF('abril 24'!$E$5:$E$23,$A13,'abril 24'!$C$5:CQ$25) -> 0 | BV13: =SUMIF('Mayo 24'!$E$5:$E$23,$A13,'Mayo 24'!$C$5:CQ$25) -> 0 | BW13: =SUMIF('Junio 24'!$E$5:$E$23,$A13,'Junio 24'!$C$5:CQ$25) -> 0 | BX13: =SUMIF('Julio 24'!$E$5:$E$23,$A13,'Julio 24'!$C$5:CQ$25) -> 0 | BY13: =SUMIF('Agosto 24'!$E$5:$E$23,$A13,'Agosto 24'!$C$5:CQ$25) -> 0 | BZ13: =SUMIF('Septiembre 24'!$E$5:$E$23,$A13,'Septiembre 24'!$C$5:CQ$25) -> 0 | CA13: =SUMIF('Octubre 24'!$E$5:$E$23,$A13,'Octubre 24'!$C$5:CQ$25) -> 0 | CB13: =SUMIF('Noviembre 24'!$E$5:$E$23,$A13,'Noviembre 24'!$C$5:CQ$25) -> 0 | CC13: =SUMIF('Diciembre 24'!$E$5:$E$23,$A13,'Diciembre 24'!$C$5:CQ$25) -> 0 | CD13: =SUMIF('Enero 25'!$E$5:$E$23,$A13,'Enero 25'!$C$5:CQ$25) -> 0 | CE13: =SUMIF('febrero 25'!$E$5:$E$23,$A13,'febrero 25'!$C$5:CQ$25) -> 0 | CF13: =SUMIF('marzo 25'!$E$5:$E$23,$A13,'marzo 25'!$C$5:CQ$25) -> 0 | CG13: =SUMIF('abril 25'!$E$5:$E$23,$A13,'abril 25'!$C$5:CQ$25) -> 0 | CH13: =SUMIF('Mayo 25'!$E$5:$E$23,$A13,'Mayo 25'!$C$5:CQ$25) -> 0 | CI13: =SUMIF('Junio 25'!$E$5:$E$23,$A13,'Junio 25'!$C$5:CQ$25) -> 0 | CJ13: =SUMIF('Julio 25'!$E$5:$E$23,$A13,'Julio 25'!$C$5:CQ$25) -> 0 | CK13: =SUMIF('Agosto 25'!$E$5:$E$23,$A13,'Agosto 25'!$C$5:CQ$25) -> 0 | CL13: =SUMIF('Septiembre 25'!$E$5:$E$23,$A13,'Septiembre 25'!$C$5:CQ$25) -> 0 | CM13: =SUMIF('Octubre 25'!$E$5:$E$23,$A13,'Octubre 25'!$C$5:CQ$25) -> 0 | CN13: =SUMIF('noviembre 25'!$E$5:$E$23,$A13,'noviembre 25'!$C$5:CQ$25) -> 0
A14: Imposiciones | B14: =MAX(BN14:ZZ14) -> 0 | C14: =MIN(AK14:ZZ14) -> 0 | D14: =AVERAGE(AK14:ZZ14) -> 0 | E14: =SUMIF(Agosto!$E$5:$E$25,$A14,Agosto!$C$5:$C$25) -> 0 | F14: =SUMIF(Septiembre!$E$5:$E$25,$A14,Septiembre!$C$5:$C$25) -> 0 | G14: =SUMIF(octubre!$E$5:E$25,$A14,octubre!$C$5:$C$25) -> 0 | H14: =SUMIF(noviembre!$E$5:F$25,$A14,noviembre!$C$5:$C$25) -> 0 | I14: =SUMIF(Diciembre!$E$5:CQ$25,$A14,Diciembre!$C$5:$C$25) -> 0 | J14: =SUMIF(Enero!$E$5:E$25,$A14,Enero!$C$5:$C$25) -> 0 | K14: =SUMIF(febrero!$E$5:$E$25,$A14,febrero!$C$5:CQ$25) -> 24175 | L14: =SUMIF(Marzo!$E$5:$E$25,$A14,Marzo!$C$5:CQ$25) -> 24175 | M14: =SUMIF(Abril!$E$5:$E$25,$A14,Abril!$C$5:CQ$25) -> 24175 | N14: =SUMIF(Mayo!$E$5:$E$25,$A14,Mayo!$C$5:CQ$25) -> 24175 | O14: =SUMIF(Junio!$E$5:$E$25,$A14,Junio!$C$5:CQ$25) -> 0 | P14: =SUMIF(Julio!$E$5:$E$25,$A14,Julio!$C$5:CQ$25) -> 12087.5 | Q14: =SUMIF('Agosto 19'!$E$5:$E$23,$A14,'Agosto 19'!$C$5:CQ$25) -> 18131.25 | R14: =SUMIF('Septiembre 19'!$E$5:$E$23,$A14,'Septiembre 19'!$C$5:CQ$25) -> 18131.25 | S14: =SUMIF('Octubre 19'!$E$5:$E$23,$A14,'Octubre 19'!$C$5:CQ$25) -> 6571 | T14: =SUMIF('Noviembre 19'!$E$5:$E$23,$A14,'Noviembre 19'!$C$5:CQ$25) -> 13142 | U14: =SUMIF('Diciembre 19'!$E$5:$E$23,$A14,'Diciembre 19'!$C$5:CQ$25) -> 13142 | V14: =SUMIF('Enero 20'!$E$5:$E$23,$A14,'Enero 20'!$C$5:CQ$25) -> 13142 | W14: =SUMIF('Febrero 20'!$E$5:$E$23,$A14,'Febrero 20'!$C$5:CQ$25) -> 13142 | X14: =SUMIF('Marzo 20'!$E$5:$E$23,$A14,'Marzo 20'!$C$5:CQ$25) -> 13142 | Y14: =SUMIF('Abril 20'!$E$5:$E$23,$A14,'Abril 20'!$C$5:CQ$25) -> 3500 | Z14: =SUMIF('Mayo 20'!$E$5:$E$23,$A14,'Mayo 20'!$C$5:CQ$25) -> 13142 | AA14: =SUMIF('Junio 20'!$E$5:$E$23,$A14,'Junio 20'!$C$5:CQ$25) -> 13142 | AB14: =SUMIF('Julio 20'!$E$5:$E$23,$A14,'Julio 20'!$C$5:CQ$25) -> 13142 | AC14: =SUMIF('Agosto 20'!$E$5:$E$23,$A14,'Agosto 20'!$C$5:CQ$25) -> 13142 | AD14: =SUMIF('Septiembre 20'!$E$5:$E$23,$A14,'Septiembre 20'!$C$5:CQ$25) -> 13142 | AE14: =SUMIF('octubre 20'!$E$5:$E$23,$A14,'octubre 20'!$C$5:CQ$25) -> 13142 | AF14: =SUMIF('noviembre 20'!$E$5:$E$23,$A14,'noviembre 20'!$C$5:CQ$25) -> 0 | AG14: =SUMIF('diciembre 20'!$E$5:$E$23,$A14,'diciembre 20'!$C$5:CQ$25) -> 0 | AH14: =SUMIF('enero 21'!$E$5:$E$23,$A14,'enero 21'!$C$5:CQ$25) -> 0 | AI14: =SUMIF('febrero 21'!$E$5:$E$23,$A14,'febrero 21'!$C$5:CQ$25) -> 0 | AJ14: =SUMIF('marzo 21'!$E$5:$E$23,$A14,'marzo 21'!$C$5:CQ$25) -> 0 | AK14: =SUMIF('abril 21'!$E$5:$E$23,$A14,'abril 21'!$C$5:CQ$25) -> 0 | AL14: =SUMIF('mayo 21'!$E$5:$E$23,$A14,'mayo 21'!$C$5:CQ$25) -> 0 | AM14: =SUMIF('Junio 21'!$E$5:$E$23,$A14,'Junio 21'!$C$5:CQ$25) -> 0 | AN14: =SUMIF('Julio 21'!$E$5:$E$23,$A14,'Julio 21'!$C$5:CQ$25) -> 0 | AO14: =SUMIF('Agosto 21'!$E$5:$E$23,$A14,'Agosto 21'!$C$5:CQ$25) -> 0 | AP14: =SUMIF('Septiembre 21'!$E$5:$E$23,$A14,'Septiembre 21'!$C$5:CQ$25) -> 0 | AQ14: =SUMIF('Octubre 21'!$E$5:$E$23,$A14,'Octubre 21'!$C$5:CQ$25) -> 0 | AR14: =SUMIF('Noviembre 21'!$E$5:$E$23,$A14,'Noviembre 21'!$C$5:CQ$25) -> 0 | AS14: =SUMIF('Diciembre 21'!$E$5:$E$23,$A14,'Noviembre 21'!$C$5:CQ$25) -> 0 | AT14: =SUMIF('Enero 22'!$E$5:$E$23,$A14,'Enero 22'!$C$5:CQ$25) -> 0 | AU14: =SUMIF('Febrero 22'!$E$5:$E$23,$A14,'Febrero 22'!$C$5:CQ$25) -> 0 | AV14: =SUMIF('Marzo 22'!$E$5:$E$23,$A14,'Marzo 22'!$C$5:CQ$25) -> 0 | AW14: =SUMIF('Abril 22'!$E$5:$E$23,$A14,'Abril 22'!$C$5:CQ$25) -> 0 | AX14: =SUMIF('Mayo 22'!$E$5:$E$23,$A14,'Mayo 22'!$C$5:CQ$25) -> 0 | AY14: =SUMIF('Junio 22'!$E$5:$E$23,$A14,'Junio 22'!$C$5:CQ$25) -> 0 | AZ14: =SUMIF('Julio 22'!$E$5:$E$23,$A14,'Julio 22'!$C$5:CQ$25) -> 0 | BA14: =SUMIF('Agosto 22'!$E$5:$E$23,$A14,'Agosto 22'!$C$5:CQ$25) -> 0 | BB14: =SUMIF('septiembre 22'!$E$5:$E$23,$A14,'septiembre 22'!$C$5:CQ$25) -> 0 | BC14: =SUMIF('octubre 22'!$E$5:$E$23,$A14,'octubre 22'!$C$5:CQ$25) -> 0 | BD14: =SUMIF('noviembre 22'!$E$5:$E$23,$A14,'noviembre 22'!$C$5:CQ$25) -> 0 | BE14: =SUMIF('diciembre 22'!$E$5:$E$23,$A14,'noviembre 22'!$C$5:CQ$25) -> 0 | BF14: =SUMIF('Enero 23'!$E$5:$E$23,$A14,'Enero 23'!$C$5:CQ$25) -> 0 | BG14: =SUMIF('Febrero 23'!$E$5:$E$23,$A14,'Febrero 23'!$C$5:CQ$25) -> 0 | BH14: =SUMIF('Marzo 23'!$E$5:$E$23,$A14,'Marzo 23'!$C$5:CQ$25) -> 0 | BI14: =SUMIF('Abril 23'!$E$5:$E$23,$A14,'Abril 23'!$C$5:CQ$25) -> 0 | BJ14: =SUMIF('Mayo 23'!$E$5:$E$23,$A14,'Mayo 23'!$C$5:CQ$25) -> 0 | BK14: =SUMIF('Junio 23'!$E$5:$E$23,$A14,'Junio 23'!$C$5:CQ$25) -> 0 | BL14: =SUMIF('Julio 23'!$E$5:$E$23,$A14,'Julio 23'!$C$5:CQ$25) -> 0 | BM14: =SUMIF('Agosto 23'!$E$5:$E$23,$A14,'Agosto 23'!$C$5:CQ$25) -> 0 | BN14: =SUMIF('Septiembre 23'!$E$5:$E$23,$A14,'Septiembre 23'!$C$5:CQ$25) -> 0 | BO14: =SUMIF('Octubre 23'!$E$5:$E$23,$A14,'Octubre 23'!$C$5:CQ$25) -> 0 | BP14: =SUMIF('Noviembre 23'!$E$5:$E$23,$A14,'Noviembre 23'!$C$5:CQ$25) -> 0 | BQ14: =SUMIF('Diciembre 23'!$E$5:$E$23,$A14,'Diciembre 23'!$C$5:CQ$25) -> 0 | BR14: =SUMIF('Enero 24'!$E$5:$E$23,$A14,'Enero 24'!$C$5:CQ$25) -> 0 | BS14: =SUMIF('Febrero 24'!$E$5:$E$23,$A14,'Febrero 24'!$C$5:CQ$25) -> 0 | BT14: =SUMIF('Marzo 24'!$E$5:$E$23,$A14,'Marzo 24'!$C$5:CQ$25) -> 0 | BU14: =SUMIF('abril 24'!$E$5:$E$23,$A14,'abril 24'!$C$5:CQ$25) -> 0 | BV14: =SUMIF('Mayo 24'!$E$5:$E$23,$A14,'Mayo 24'!$C$5:CQ$25) -> 0 | BW14: =SUMIF('Junio 24'!$E$5:$E$23,$A14,'Junio 24'!$C$5:CQ$25) -> 0 | BX14: =SUMIF('Julio 24'!$E$5:$E$23,$A14,'Julio 24'!$C$5:CQ$25) -> 0 | BY14: =SUMIF('Agosto 24'!$E$5:$E$23,$A14,'Agosto 24'!$C$5:CQ$25) -> 0 | BZ14: =SUMIF('Septiembre 24'!$E$5:$E$23,$A14,'Septiembre 24'!$C$5:CQ$25) -> 0 | CA14: =SUMIF('Octubre 24'!$E$5:$E$23,$A14,'Octubre 24'!$C$5:CQ$25) -> 0 | CB14: =SUMIF('Noviembre 24'!$E$5:$E$23,$A14,'Noviembre 24'!$C$5:CQ$25) -> 0 | CC14: =SUMIF('Diciembre 24'!$E$5:$E$23,$A14,'Diciembre 24'!$C$5:CQ$25) -> 0 | CD14: =SUMIF('Enero 25'!$E$5:$E$23,$A14,'Enero 25'!$C$5:CQ$25) -> 0 | CE14: =SUMIF('febrero 25'!$E$5:$E$23,$A14,'febrero 25'!$C$5:CQ$25) -> 0 | CF14: =SUMIF('marzo 25'!$E$5:$E$23,$A14,'marzo 25'!$C$5:CQ$25) -> 0 | CG14: =SUMIF('abril 25'!$E$5:$E$23,$A14,'abril 25'!$C$5:CQ$25) -> 0 | CH14: =SUMIF('Mayo 25'!$E$5:$E$23,$A14,'Mayo 25'!$C$5:CQ$25) -> 0 | CI14: =SUMIF('Junio 25'!$E$5:$E$23,$A14,'Junio 25'!$C$5:CQ$25) -> 0 | CJ14: =SUMIF('Julio 25'!$E$5:$E$23,$A14,'Julio 25'!$C$5:CQ$25) -> 0 | CK14: =SUMIF('Agosto 25'!$E$5:$E$23,$A14,'Agosto 25'!$C$5:CQ$25) -> 0 | CL14: =SUMIF('Septiembre 25'!$E$5:$E$23,$A14,'Septiembre 25'!$C$5:CQ$25) -> 0 | CM14: =SUMIF('Octubre 25'!$E$5:$E$23,$A14,'Octubre 25'!$C$5:CQ$25) -> 0 | CN14: =SUMIF('noviembre 25'!$E$5:$E$23,$A14,'noviembre 25'!$C$5:CQ$25) -> 0
A16: Total | B16: =SUM(B2:B15) -> 1777219.7 | C16: =SUM(C2:C15) -> 644056 | D16: =SUM(D2:D15) -> 1159049.3 | E16: =SUM(E2:E15) -> 1345021 | F16: =SUM(F2:F15) -> 1061237 | G16: =SUM(G2:G15) -> 1162096 | H16: =SUM(H2:H15) -> 1024344 | I16: =SUM(I2:I15) -> 1120809 | ... CQ16: =SUM(CQ2:CQ15) -> 0
B17: =B16-C16 -> 1133163.7
L18: =K5/J5 -> 1.011 | M18: 580000
L19: 0.016 | M19: =K5 -> 586380 | N19: =(M19-M18)*6 -> 38280
L20: 0.022 | M20: =M19*(1+L19) -> 595762.08 | N20: =(M20-M19)*6 -> 56292.48
M21: =M20*(1+L20) -> 608868.85 | N21: =(M21-M20)*6 -> 78640.595

Sheet Transacciones
B1: Para añadir o cambiar categorías, modifica las tablas "Ingresos" y "Gastos" de la hoja "Resumen".
B2: Gastos | D2: =IFERROR(__xludf.DUMMYFUNCTION("GOOGLEFINANCE((""CURRENCY:USDCLP""))+1"),926.24) -> 926.24 | H2: Pagos
M3: Pagado | N3: =SUMIF(F:F,"Pagado",C:C) -> 176000
B4: Fecha | C4: Importe | D4: Descripción | E4: Categoría | F4: Status | H4: Fecha | I4: Importe | J4: Descripción | K4: Categoría | M4: Por pagar | N4: =SUMIF(F5:F34,"Por pagar",C5:C34) -> 0
D5: Agua | E5: Agua | I5: =SUMIF(F:F,"Pagado",C:C) -> 176000 | J5: Javier | K5: Javier | Q5: =P5-O6 -> 0
C6: =IFERROR(__xludf.DUMMYFUNCTION("19.38*Resumen!B1-2.12*GOOGLEFINANCE((""CURRENCY:CLF/CLP""))"),704652.445) -> 704652.44 | D6: Arriendo | E6: Arriendo
C7: 18990 | D7: GTD | E7: Entel
D8: Gas | E8: Gas
D9: Gastos comunes | E9: Gastos comunes
D10: Luz | E10: Luz
C11: 37000 | D11: nana | E11: Nana
C12: 37000 | D12: nana | E12: Nana
C13: 14253 | D13: Netflix | E13: Netflix
C14: 7094 | D14: Spotify | E14: Spotify
C15: =176000 -> 176000 | D15: super | E15: Supermercado | F15: Pagado
D16: super | E16: Supermercado
D17: super | E17: Supermercado
D18: bencina | E18: bencina/luz
D19: tag | E19: tag
E20: tag
E21: Nana
C22: =IFERROR(__xludf.DUMMYFUNCTION("14.04/12*GOOGLEFINANCE((""CURRENCY:CLF/CLP""))"),47766.127499999995) -> 47766.128 | E22: Seguro depto

Sheet Copia de Transacciones
B1: Para añadir o cambiar categorías, modifica las tablas "Ingresos" y "Gastos" de la hoja "Resumen".
B2: Gastos | D2: =IFERROR(__xludf.DUMMYFUNCTION("GOOGLEFINANCE((""CURRENCY:USDCLP""))+1"),926.24) -> 926.24 | H2: Pagos
M3: Pagado | N3: =SUMIF(F:F,"Pagado",C:C) -> 1634315.6
B4: Fecha | C4: Importe | D4: Descripción | E4: Categoría | F4: Status | H4: Fecha | I4: Importe | J4: Descripción | K4: Categoría | M4: Por pagar | N4: =SUMIF(F5:F34,"Por pagar",C5:C34) -> 0
C5: 10000 | D5: Agua | E5: Agua | F5: Pagado | I5: =SUMIF(F:F,"Pagado",C:C) -> 1634315.6 | J5: Javier | K5: Javier | Q5: =P5-O6 -> 0
C6: =IFERROR(__xludf.DUMMYFUNCTION("19.38*Resumen!B1-2.12*GOOGLEFINANCE((""CURRENCY:CLF/CLP""))"),704652.445) -> 704652.44 | D6: Arriendo | E6: Arriendo | F6: Pagado
C7: 18990 | D7: GTD | E7: Entel | F7: Pagado
C8: 6405 | D8: Gas | E8: Gas
C9: 275000 | D9: Gastos comunes | E9: Gastos comunes | F9: Pagado
C10: 38733 | D10: Luz | E10: Luz | F10: Pagado
C11: 37000 | D11: nana | E11: Nana
C12: 37000 | D12: nana | E12: Nana
C13: 14253 | D13: Netflix | E13: Netflix
C14: 7094 | D14: Spotify | E14: Spotify | F14: Pagado
C15: =311000 -> 311000 | D15: super | E15: Supermercado | F15: Pagado
D16: super | E16: Supermercado
D17: super | E17: Supermercado
C18: =58000+32000+14080+17000 -> 121080 | D18: bencina | E18: bencina/luz | F18: Pagado
C19: 100000 | D19: tag | E19: tag | F19: Pagado
E20: tag
E21: Nana
C22: =IFERROR(__xludf.DUMMYFUNCTION("14.04/12*GOOGLEFINANCE((""CURRENCY:CLF/CLP""))"),47766.127499999995) -> 47766.128 | E22: Seguro depto | F22: Pagado

Sheet Mayo 26
B1: Para añadir o cambiar categorías, modifica las tablas "Ingresos" y "Gastos" de la hoja "Resumen".
B2: Gastos | D2: =IFERROR(__xludf.DUMMYFUNCTION("GOOGLEFINANCE((""CURRENCY:USDCLP""))+1"),926.24) -> 926.24 | H2: Pagos
M3: Pagado | N3: =SUMIF(F:F,"Pagado",C:C) -> 1809132
B4: Fecha | C4: Importe | D4: Descripción | E4: Categoría | F4: Status | H4: Fecha | I4: Importe | J4: Descripción | K4: Categoría | M4: Por pagar | N4: =SUMIF(F5:F34,"Por pagar",C5:C34) -> 0
C5: 11610 | D5: Agua | E5: Agua | F5: Pagado | I5: =SUMIF(F:F,"Pagado",C:C) -> 1809132 | J5: Javier | K5: Javier | Q5: =P5-O6 -> 0
C6: =19.38*Resumen!B1-70000 -> 721203.04 | D6: Arriendo | E6: Arriendo | F6: Pagado
C7: 19700 | D7: GTD | E7: Entel | F7: Pagado
C8: 6405 | D8: Gas | E8: Gas | F8: Pagado
C9: 237000 | D9: Gastos comunes | E9: Gastos comunes | F9: Pagado
C10: 35412 | D10: Luz | E10: Luz | F10: Pagado
C11: 37000 | D11: nana | E11: Nana | F11: Pagado
C12: 37000 | D12: nana | E12: Nana | F12: Pagado
C13: 14253 | D13: Netflix | E13: Netflix | F13: Pagado
C14: 7094 | D14: Spotify | E14: Spotify | F14: Pagado
C15: =194009+189000 -> 383009 | D15: super | E15: Supermercado | F15: Pagado
D16: super | E16: Supermercado
D17: super | E17: Supermercado
C18: =63169+25000+43000+31000 -> 162169 | D18: bencina | E18: bencina | F18: Pagado
C19: =115756+11400+10121 -> 137277 | D19: tag | E19: tag | F19: Pagado
E20: tag
E21: Nana
E22: Seguro depto

Sheet Abril 26
B1: Para añadir o cambiar categorías, modifica las tablas "Ingresos" y "Gastos" de la hoja "Resumen".
B2: Gastos | D2: =IFERROR(__xludf.DUMMYFUNCTION("GOOGLEFINANCE((""CURRENCY:USDCLP""))+1"),926.24) -> 926.24 | H2: Pagos
M3: Pagado | N3: =SUMIF(F:F,"Pagado",C:C) -> 1928048.7
B4: Fecha | C4: Importe | D4: Descripción | E4: Categoría | F4: Status | H4: Fecha | I4: Importe | J4: Descripción | K4: Categoría | M4: Por pagar | N4: =SUMIF(F5:F34,"Por pagar",C5:C34) -> 0
C5: 11610 | D5: Agua | E5: Agua | F5: Pagado | I5: =SUMIF(F:F,"Pagado",C:C) -> 1928048.7 | J5: Javier | K5: Javier | Q5: =P5-O6 -> 0
C6: =19.38*Resumen!B1 -> 791203.04 | D6: Arriendo | E6: Arriendo | F6: Pagado
C7: 19700 | D7: GTD | E7: Entel | F7: Pagado
C8: 6405 | D8: Gas | E8: Gas | F8: Pagado
C9: 237000 | D9: Gastos comunes | E9: Gastos comunes | F9: Pagado
C10: 35412 | D10: Luz | E10: Luz | F10: Pagado
C11: 37000 | D11: nana | E11: Nana | F11: Pagado
C12: 37000 | D12: nana | E12: Nana | F12: Pagado
C13: 14253 | D13: Netflix | E13: Netflix | F13: Pagado
C14: 7094 | D14: Spotify | E14: Spotify | F14: Pagado
C15: =194009+189000 -> 383009 | D15: super | E15: Supermercado | F15: Pagado
D16: super | E16: Supermercado
D17: super | E17: Supermercado
C18: =63169+25000+43000+31000 -> 162169 | D18: bencina | E18: bencina | F18: Pagado
C19: =115756+11400+10121 -> 137277 | D19: tag | E19: tag | F19: Pagado
E20: tag
E21: Nana
C22: =587000/12 -> 48916.667 | E22: Seguro depto | F22: Pagado

Sheet Mar 26
B1: Para añadir o cambiar categorías, modifica las tablas "Ingresos" y "Gastos" de la hoja "Resumen".
B2: Gastos | D2: =IFERROR(__xludf.DUMMYFUNCTION("GOOGLEFINANCE((""CURRENCY:USDCLP""))+1"),926.24) -> 926.24 | H2: Pagos
M3: Pagado | N3: =SUMIF(F:F,"Pagado",C:C) -> 1987907.8
B4: Fecha | C4: Importe | D4: Descripción | E4: Categoría | F4: Status | H4: Fecha | I4: Importe | J4: Descripción | K4: Categoría | M4: Por pagar | N4: =SUMIF(F5:F34,"Por pagar",C5:C34) -> 0
C5: 8640 | D5: Agua | E5: Agua | F5: Pagado | I5: =SUMIF(F:F,"Pagado",C:C) -> 1987907.8 | J5: Javier | K5: Javier | Q5: =P5-O6 -> 0
C6: =19.37*Resumen!B1 -> 790794.78 | D6: Arriendo | E6: Arriendo | F6: Pagado
C7: 19700 | D7: GTD | E7: Entel | F7: Pagado
C8: 4120 | D8: Gas | E8: Gas
C9: 299000 | D9: Gastos comunes | E9: Gastos comunes | F9: Pagado
C10: 38773 | D10: Luz | E10: Luz | F10: Pagado
C11: 37000 | D11: nana | E11: Nana | F11: Pagado
C12: 37000 | D12: nana | E12: Nana
C13: 14253 | D13: Netflix | E13: Netflix
C14: 7094 | D14: Spotify | E14: Spotify
C15: =125000+88000 -> 213000 | D15: super | E15: Supermercado | F15: Pagado
D16: super | E16: Supermercado
D17: super | E17: Supermercado
C18: =260000+75000+66000 -> 401000 | D18: bencina | E18: bencina | F18: Pagado
C19: 180000 | D19: tag | E19: tag | F19: Pagado
E20: tag
C21: 37000 | E21: Nana

Sheet Feb 26
B1: Para añadir o cambiar categorías, modifica las tablas "Ingresos" y "Gastos" de la hoja "Resumen".
B2: Gastos | D2: =IFERROR(__xludf.DUMMYFUNCTION("GOOGLEFINANCE((""CURRENCY:USDCLP""))+1"),926.24) -> 926.24 | H2: Pagos
M3: Pagado | N3: =SUMIF(F:F,"Pagado",C:C) -> 1119947
B4: Fecha | C4: Importe | D4: Descripción | E4: Categoría | F4: Status | H4: Fecha | I4: Importe | J4: Descripción | K4: Categoría | M4: Por pagar | N4: =SUMIF(F5:F34,"Por pagar",C5:C34) -> 0
C5: 11250 | D5: Agua | E5: Agua | F5: Pagado | I5: =SUMIF(F:F,"Pagado",C:C) -> 1119947 | J5: Javier | K5: Javier | Q5: =P5-O6 -> 0
C6: =15.6926*Resumen!B1 -> 640662.16 | D6: Arriendo | E6: Arriendo
C7: 19700 | D7: GTD | E7: Entel | F7: Pagado
C8: 4120 | D8: Gas | E8: Gas | F8: Pagado
C9: 171000 | D9: Gastos comunes | E9: Gastos comunes | F9: Pagado
C10: 65530 | D10: Luz | E10: Luz | F10: Pagado
C11: 37000 | D11: nana | E11: Nana | F11: Pagado
C12: 37000 | D12: nana | E12: Nana | F12: Pagado
C13: 14253 | D13: Netflix | E13: Netflix | F13: Pagado
C14: 7094 | D14: Spotify | E14: Spotify | F14: Pagado
C15: =138000+151000+30000 -> 319000 | D15: super | E15: Supermercado | F15: Pagado
D16: super | E16: Supermercado
D17: super | E17: Supermercado
C18: =57000+52000+50000+52000+50000 -> 261000 | D18: bencina | E18: bencina | F18: Pagado
C19: 136000 | D19: tag | E19: tag | F19: Pagado
E20: tag
C21: 37000 | E21: Nana | F21: Pagado

Sheet Ene 26
B1: Para añadir o cambiar categorías, modifica las tablas "Ingresos" y "Gastos" de la hoja "Resumen".
B2: Gastos | D2: =IFERROR(__xludf.DUMMYFUNCTION("GOOGLEFINANCE((""CURRENCY:USDCLP""))+1"),926.24) -> 926.24 | H2: Pagos
M3: Pagado | N3: =SUMIF(F:F,"Pagado",C:C) -> 1352412.2
B4: Fecha | C4: Importe | D4: Descripción | E4: Categoría | F4: Status | H4: Fecha | I4: Importe | J4: Descripción | K4: Categoría | M4: Por pagar | N4: =SUMIF(F5:F34,"Por pagar",C5:C34) -> 0
C5: 13250 | D5: Agua | E5: Agua | F5: Pagado | I5: =SUMIF(F:F,"Pagado",C:C) -> 1352412.2 | J5: Javier | K5: Javier | Q5: =P5-O6 -> 0
C6: =15.6926*Resumen!B1 -> 640662.16 | D6: Arriendo | E6: Arriendo | F6: Pagado
C7: 25500 | D7: GTD | E7: Entel | F7: Pagado
C8: 4000 | D8: Gas | E8: Gas | F8: Pagado
C9: 198000 | D9: Gastos comunes | E9: Gastos comunes | F9: Pagado
C10: 72000 | D10: Luz | E10: Luz | F10: Pagado
C11: 37000 | D11: nana | E11: Nana | F11: Pagado
C12: 37000 | D12: nana | E12: Nana | F12: Pagado
C13: 14253 | D13: Netflix | E13: Netflix
C14: 7094 | D14: Spotify | E14: Spotify
C15: =44000 -> 44000 | D15: super | E15: Supermercado
C16: 220000 | D16: super | E16: Supermercado
D17: super | E17: Supermercado
C18: =202000 -> 202000 | D18: bencina | E18: bencina | F18: Pagado
C19: 123000 | D19: tag | E19: tag | F19: Pagado
E20: tag
C21: 37000 | E21: Nana

Sheet Dic 26
B1: Para añadir o cambiar categorías, modifica las tablas "Ingresos" y "Gastos" de la hoja "Resumen".
B2: Gastos | D2: =IFERROR(__xludf.DUMMYFUNCTION("GOOGLEFINANCE((""CURRENCY:USDCLP""))+1"),926.24) -> 926.24 | H2: Pagos
M3: Pagado | N3: =SUMIF(F:F,"Pagado",C:C) -> 1572719.2
B4: Fecha | C4: Importe | D4: Descripción | E4: Categoría | F4: Status | H4: Fecha | I4: Importe | J4: Descripción | K4: Categoría | M4: Por pagar | N4: =SUMIF(F5:F34,"Por pagar",C5:C34) -> 0
C5: 10210 | D5: Agua | E5: Agua | F5: Pagado | I5: =SUMIF(F:F,"Pagado",C:C) -> 1572719.2 | J5: Javier | K5: Javier | Q5: =P5-O6 -> 0
C6: =15.6926*Resumen!B1 -> 640662.16 | D6: Arriendo | E6: Arriendo | F6: Pagado
C7: 17500 | D7: GTD | E7: Entel | F7: Pagado
D8: Gas | E8: Gas
C9: 257000 | D9: Gastos comunes | E9: Gastos comunes | F9: Pagado
C10: 58000 | D10: Luz | E10: Luz | F10: Pagado
C11: 37000 | D11: nana | E11: Nana | F11: Pagado
C12: 37000 | D12: nana | E12: Nana | F12: Pagado
C13: 14253 | D13: Netflix | E13: Netflix | F13: Pagado
C14: 7094 | D14: Spotify | E14: Spotify | F14: Pagado
C15: =44000 -> 44000 | D15: super | E15: Supermercado | F15: Pagado
C16: 220000 | D16: super | E16: Supermercado | F16: Pagado
D17: super | E17: Supermercado
C18: =110000 -> 110000 | D18: bencina | E18: bencina | F18: Pagado
C19: 120000 | D19: tag | E19: tag | F19: Pagado
E20: tag
C21: 37000 | E21: Nana

Sheet noviembre 25
B1: Para añadir o cambiar categorías, modifica las tablas "Ingresos" y "Gastos" de la hoja "Resumen".
B2: Gastos | D2: =IFERROR(__xludf.DUMMYFUNCTION("GOOGLEFINANCE((""CURRENCY:USDCLP""))+1"),926.24) -> 926.24 | H2: Pagos
M3: Pagado | N3: =SUMIF(F:F,"Pagado",C:C) -> 1559662.2
B4: Fecha | C4: Importe | D4: Descripción | E4: Categoría | F4: Status | H4: Fecha | I4: Importe | J4: Descripción | K4: Categoría | M4: Por pagar | N4: =SUMIF(F5:F34,"Por pagar",C5:C34) -> 0
C5: 6000 | D5: Agua | E5: Agua | F5: Pagado | I5: =SUMIF(F:F,"Pagado",C:C) -> 1559662.2 | J5: Javier | K5: Javier | Q5: =P5-O6 -> 0
C6: =15.6926*Resumen!B1 -> 640662.16 | D6: Arriendo | E6: Arriendo | F6: Pagado
C7: 17500 | D7: GTD | E7: Entel | F7: Pagado
C8: 4100 | D8: Gas | E8: Gas | F8: Pagado
C9: 240000 | D9: Gastos comunes | E9: Gastos comunes | F9: Pagado
C10: 20000 | D10: Luz | E10: Luz | F10: Pagado
C11: 37000 | D11: nana | E11: Nana | F11: Pagado
C12: 37000 | D12: nana | E12: Nana
C13: 14253 | D13: Netflix | E13: Netflix
C14: 7094 | D14: Spotify | E14: Spotify
C15: =100000 -> 100000 | D15: super | E15: Supermercado | F15: Pagado
C16: 169000 | D16: super | E16: Supermercado | F16: Pagado
D17: super | E17: Supermercado
C18: =150000+46000+22000 -> 218000 | D18: bencina | E18: bencina | F18: Pagado
C19: =12400+58000 -> 70400 | D19: tag | E19: tag | F19: Pagado
E20: tag
C21: 37000 | E21: Nana | F21: Pagado

Sheet Octubre 25
B1: Para añadir o cambiar categorías, modifica las tablas "Ingresos" y "Gastos" de la hoja "Resumen".
B2: Gastos | D2: =IFERROR(__xludf.DUMMYFUNCTION("GOOGLEFINANCE((""CURRENCY:USDCLP""))+1"),926.24) -> 926.24 | H2: Pagos
M3: Pagado | N3: =SUMIF(F:F,"Pagado",C:C) -> 913156.16
B4: Fecha | C4: Importe | D4: Descripción | E4: Categoría | F4: Status | H4: Fecha | I4: Importe | J4: Descripción | K4: Categoría | M4: Por pagar | N4: =SUMIF(F5:F34,"Por pagar",C5:C34) -> 0
C5: 9900 | D5: Agua | E5: Agua | F5: Pagado | I5: =SUMIF(F:F,"Pagado",C:C) -> 913156.16 | J5: Javier | K5: Javier | Q5: =P5-O6 -> 0
C6: =15.6926*Resumen!B1 -> 640662.16 | D6: Arriendo | E6: Arriendo | F6: Pagado
C7: 17500 | D7: GTD | E7: Entel | F7: Pagado
C8: 6300 | D8: Gas | E8: Gas
C9: 240000 | D9: Gastos comunes | E9: Gastos comunes
C10: 29000 | D10: Luz | E10: Luz | F10: Pagado
C11: 37000 | D11: nana | E11: Nana | F11: Pagado
C12: 37000 | D12: nana | E12: Nana | F12: Pagado
C13: 14253 | D13: Netflix | E13: Netflix
C14: 7094 | D14: Spotify | E14: Spotify | F14: Pagado
C15: =194000 -> 194000 | D15: super | E15: Supermercado
C16: =70000+60000 -> 130000 | D16: super | E16: Supermercado
D17: super | E17: Supermercado
C18: =53000 -> 53000 | D18: bencina | E18: bencina | F18: Pagado
C19: =45000 -> 45000 | D19: tag | E19: tag | F19: Pagado
E20: tag
C21: 37000 | E21: Nana | F21: Pagado

Sheet Septiembre 25
B1: Para añadir o cambiar categorías, modifica las tablas "Ingresos" y "Gastos" de la hoja "Resumen".
B2: Gastos | D2: =IFERROR(__xludf.DUMMYFUNCTION("GOOGLEFINANCE((""CURRENCY:USDCLP""))+1"),926.24) -> 926.24 | H2: Pagos
M3: Pagado | N3: =SUMIF(F:F,"Pagado",C:C) -> 1733806.2
B4: Fecha | C4: Importe | D4: Descripción | E4: Categoría | F4: Status | H4: Fecha | I4: Importe | J4: Descripción | K4: Categoría | M4: Por pagar | N4: =SUMIF(F5:F34,"Por pagar",C5:C34) -> 0
C5: 8050 | D5: Agua | E5: Agua | F5: Pagado | I5: =SUMIF(F:F,"Pagado",C:C) -> 1733806.2 | J5: Javier | K5: Javier | Q5: =P5-O6 -> 0
C6: =15.6926*Resumen!B1 -> 640662.16 | D6: Arriendo | E6: Arriendo | F6: Pagado
C7: 17500 | D7: GTD | E7: Entel | F7: Pagado
C8: 6300 | D8: Gas | E8: Gas | F8: Pagado
C9: 240000 | D9: Gastos comunes | E9: Gastos comunes | F9: Pagado
C10: 41200 | D10: Luz | E10: Luz | F10: Pagado
C11: 37000 | D11: nana | E11: Nana | F11: Pagado
C12: 37000 | D12: nana | E12: Nana | F12: Pagado
C13: 14253 | D13: Netflix | E13: Netflix
C14: 7094 | D14: Spotify | E14: Spotify | F14: Pagado
C15: =194000 -> 194000 | D15: super | E15: Supermercado | F15: Pagado
C16: =70000+60000 -> 130000 | D16: super | E16: Supermercado | F16: Pagado
D17: super | E17: Supermercado
C18: =23000+52000+150000+49000 -> 274000 | D18: bencina | E18: bencina | F18: Pagado
C19: =74000+27000 -> 101000 | D19: tag | E19: tag | F19: Pagado
E20: tag
C21: 37000 | E21: Nana

Sheet Agosto 25
B1: Para añadir o cambiar categorías, modifica las tablas "Ingresos" y "Gastos" de la hoja "Resumen".
B2: Gastos | D2: =IFERROR(__xludf.DUMMYFUNCTION("GOOGLEFINANCE((""CURRENCY:USDCLP""))+1"),926.24) -> 926.24 | H2: Pagos
M3: Pagado | N3: =SUMIF(F:F,"Pagado",C:C) -> 0
B4: Fecha | C4: Importe | D4: Descripción | E4: Categoría | F4: Status | H4: Fecha | I4: Importe | J4: Descripción | K4: Categoría | M4: Por pagar | N4: =SUMIF(F5:F34,"Por pagar",C5:C34) -> 0
C5: 9470 | D5: Agua | E5: Agua | I5: =SUMIF(F:F,"Pagado",C:C) -> 0 | J5: Javier | K5: Javier | Q5: =P5-O6 -> 0
C6: =15.6926*Resumen!B1 -> 640662.16 | D6: Arriendo | E6: Arriendo
C7: 17000 | D7: GTD | E7: Entel
C8: 8600 | D8: Gas | E8: Gas
C9: 270000 | D9: Gastos comunes | E9: Gastos comunes
C10: 57000 | D10: Luz | E10: Luz
C11: 37000 | D11: nana | E11: Nana
C12: 37000 | D12: nana | E12: Nana
C13: 14253 | D13: Netflix | E13: Netflix
C14: 7094 | D14: Spotify | E14: Spotify
C15: =204000+12000+40000 -> 256000 | D15: super | E15: Supermercado
C16: 70000 | D16: super | E16: Supermercado
D17: super | E17: Supermercado
C18: =35000+65000+52025+50500+30000 -> 232525 | D18: bencina | E18: bencina
C19: =62378+30421 -> 92799 | D19: tag | E19: tag
E20: tag
C21: 37000 | E21: Nana

Sheet Julio 25
B1: Para añadir o cambiar categorías, modifica las tablas "Ingresos" y "Gastos" de la hoja "Resumen".
B2: Gastos | D2: =IFERROR(__xludf.DUMMYFUNCTION("GOOGLEFINANCE((""CURRENCY:USDCLP""))+1"),926.24) -> 926.24 | H2: Pagos
M3: Pagado | N3: =SUMIF(F:F,"Pagado",C:C) -> 1659070.2
B4: Fecha | C4: Importe | D4: Descripción | E4: Categoría | F4: Status | H4: Fecha | I4: Importe | J4: Descripción | K4: Categoría | M4: Por pagar | N4: =SUMIF(F5:F34,"Por pagar",C5:C34) -> 0
C5: 10900 | D5: Agua | E5: Agua | F5: Pagado | I5: =SUMIF(F:F,"Pagado",C:C) -> 1659070.2 | J5: Javier | K5: Javier | Q5: =P5-O6 -> 0
C6: =15.6926*Resumen!B1 -> 640662.16 | D6: Arriendo | E6: Arriendo | F6: Pagado
C7: 17000 | D7: GTD | E7: Entel | F7: Pagado
C8: 8600 | D8: Gas | E8: Gas | F8: Pagado
C9: 225000 | D9: Gastos comunes | E9: Gastos comunes | F9: Pagado
C10: 49275 | D10: Luz | E10: Luz | F10: Pagado
C11: 37000 | D11: nana | E11: Nana | F11: Pagado
C12: 37000 | D12: nana | E12: Nana | F12: Pagado
C13: 14253 | D13: Netflix | E13: Netflix
C14: 7094 | D14: Spotify | E14: Spotify | F14: Pagado
C15: 229000 | D15: super | E15: Supermercado | F15: Pagado
C16: 49000 | D16: super | E16: Supermercado | F16: Pagado
C17: 20000 | D17: super | E17: Supermercado | F17: Pagado
C18: =59000+52000+47000 -> 158000 | D18: bencina | E18: bencina | F18: Pagado
C19: =32539+89000+18000+31000 -> 170539 | D19: tag | E19: tag | F19: Pagado
E20: tag
E21: tag

Sheet Junio 25
B1: Para añadir o cambiar categorías, modifica las tablas "Ingresos" y "Gastos" de la hoja "Resumen".
B2: Gastos | D2: =IFERROR(__xludf.DUMMYFUNCTION("GOOGLEFINANCE((""CURRENCY:USDCLP""))+1"),926.24) -> 926.24 | H2: Pagos
M3: Pagado | N3: =SUMIF(F:F,"Pagado",C:C) -> 1679884.2
B4: Fecha | C4: Importe | D4: Descripción | E4: Categoría | F4: Status | H4: Fecha | I4: Importe | J4: Descripción | K4: Categoría | M4: Por pagar | N4: =SUMIF(F5:F34,"Por pagar",C5:C34) -> 0
C5: 10900 | D5: Agua | E5: Agua | F5: Pagado | I5: =SUMIF(F:F,"Pagado",C:C) -> 1679884.2 | J5: Javier | K5: Javier | Q5: =P5-O6 -> 0
C6: =15.6926*Resumen!B1 -> 640662.16 | D6: Arriendo | E6: Arriendo | F6: Pagado
C7: 17000 | D7: GTD | E7: Entel | F7: Pagado
D8: Gas | E8: Gas
C9: 196000 | D9: Gastos comunes | E9: Gastos comunes | F9: Pagado
C10: 36000 | D10: Luz | E10: Luz | F10: Pagado
C11: 37000 | D11: nana | E11: Nana | F11: Pagado
C12: 37000 | D12: nana | E12: Nana | F12: Pagado
C13: 14253 | D13: Netflix | E13: Netflix | F13: Pagado
C14: 7094 | D14: Spotify | E14: Spotify | F14: Pagado
C15: 30000 | D15: suscripcion super | E15: Supermercado | F15: Pagado
C16: 200825 | D16: super | E16: Supermercado | F16: Pagado
C17: 124000 | D17: super | E17: Supermercado | F17: Pagado
C18: 200000 | D18: bencina | E18: bencina | F18: Pagado
C19: =11150+118000 -> 129150 | D19: tag | E19: tag | F19: Pagado
E20: tag
E21: tag

Sheet Mayo 25
B1: Para añadir o cambiar categorías, modifica las tablas "Ingresos" y "Gastos" de la hoja "Resumen".
B2: Gastos | D2: =IFERROR(__xludf.DUMMYFUNCTION("GOOGLEFINANCE((""CURRENCY:USDCLP""))+1"),926.24) -> 926.24 | H2: Pagos
M3: Pagado | N3: =SUMIF(F:F,"Pagado",C:C) -> 1752227.2
B4: Fecha | C4: Importe | D4: Descripción | E4: Categoría | F4: Status | H4: Fecha | I4: Importe | J4: Descripción | K4: Categoría | M4: Por pagar | N4: =SUMIF(F5:F34,"Por pagar",C5:C34) -> 0
C5: 12900 | D5: Agua | E5: Agua | F5: Pagado | I5: =SUMIF(F:F,"Pagado",C:C) -> 1752227.2 | J5: Javier | K5: Javier | Q5: =P5-O6 -> 0
C6: =15.6926*Resumen!B1 -> 640662.16 | D6: Arriendo | E6: Arriendo | F6: Pagado
C7: 17000 | D7: GTD | E7: Entel | F7: Pagado
C8: 6318 | D8: Gas | E8: Gas | F8: Pagado
C9: 240000 | D9: Gastos comunes | E9: Gastos comunes | F9: Pagado
C10: 31500 | D10: Luz | E10: Luz | F10: Pagado
C11: 37000 | D11: nana | E11: Nana | F11: Pagado
C12: 37000 | D12: nana | E12: Nana | F12: Pagado
C13: 14253 | D13: Netflix | E13: Netflix | F13: Pagado
C14: 7094 | D14: Spotify | E14: Spotify | F14: Pagado
C15: 37500 | D15: super | E15: Supermercado | F15: Pagado
C16: 190000 | D16: super | E16: Supermercado | F16: Pagado
C17: 90000 | D17: super | E17: Supermercado | F17: Pagado
C18: 220000 | D18: bencina | E18: bencina | F18: Pagado
C19: 86000 | D19: tag | E19: tag | F19: Pagado
C20: 57000 | E20: tag | F20: Pagado
C21: 28000 | E21: tag | F21: Pagado

Sheet abril 25
B1: Para añadir o cambiar categorías, modifica las tablas "Ingresos" y "Gastos" de la hoja "Resumen".
B2: Gastos | D2: =IFERROR(__xludf.DUMMYFUNCTION("GOOGLEFINANCE((""CURRENCY:USDCLP""))+1"),926.24) -> 926.24 | H2: Pagos
M3: Pagado | N3: =SUMIF(F:F,"Pagado",C:C) -> 1466609.2
B4: Fecha | C4: Importe | D4: Descripción | E4: Categoría | F4: Status | H4: Fecha | I4: Importe | J4: Descripción | K4: Categoría | M4: Por pagar | N4: =SUMIF(F5:F34,"Por pagar",C5:C34) -> 0
C5: 12100 | D5: Agua | E5: Agua | F5: Pagado | I5: =SUMIF(F:F,"Pagado",C:C) -> 1466609.2 | J5: Javier | K5: Javier | Q5: =P5-O6 -> 0
C6: =15.6926*Resumen!B1 -> 640662.16 | D6: Arriendo | E6: Arriendo | F6: Pagado
C7: 17000 | D7: GTD | E7: Entel | F7: Pagado
C8: 4150 | D8: Gas | E8: Gas
C9: 210000 | D9: Gastos comunes | E9: Gastos comunes | F9: Pagado
C10: 32500 | D10: Luz | E10: Luz | F10: Pagado
C11: 37000 | D11: nana | E11: Nana | F11: Pagado
C12: 37000 | D12: nana | E12: Nana | F12: Pagado
C13: 14253 | D13: Netflix | E13: Netflix | F13: Pagado
C14: 7094 | D14: Spotify | E14: Spotify | F14: Pagado
C15: 32000 | D15: super | E15: Supermercado
C16: 197000 | D16: super | E16: Supermercado | F16: Pagado
C17: 82000 | D17: super | E17: Supermercado | F17: Pagado
D18: Super | E18: Supermercado
C19: 40000 | D19: tag | E19: tag | F19: Pagado
C20: 140000 | E20: tag | F20: Pagado

Sheet marzo 25
B1: Para añadir o cambiar categorías, modifica las tablas "Ingresos" y "Gastos" de la hoja "Resumen".
B2: Gastos | D2: =IFERROR(__xludf.DUMMYFUNCTION("GOOGLEFINANCE((""CURRENCY:USDCLP""))+1"),926.24) -> 926.24 | H2: Pagos
M3: Pagado | N3: =SUMIF(F:F,"Pagado",C:C) -> 1438966.2
B4: Fecha | C4: Importe | D4: Descripción | E4: Categoría | F4: Status | H4: Fecha | I4: Importe | J4: Descripción | K4: Categoría | M4: Por pagar | N4: =SUMIF(F5:F34,"Por pagar",C5:C34) -> 0
C5: 15860 | D5: Agua | E5: Agua | F5: Pagado | I5: =SUMIF(F:F,"Pagado",C:C) -> 1438966.2 | J5: Javier | K5: Javier | Q5: =P5-O6 -> 0
C6: =15.6926*Resumen!B1 -> 640662.16 | D6: Arriendo | E6: Arriendo | F6: Pagado
C7: 17000 | D7: GTD | E7: Entel | F7: Pagado
C8: 4150 | D8: Gas | E8: Gas | F8: Pagado
C9: 181000 | D9: Gastos comunes | E9: Gastos comunes | F9: Pagado
C10: 40200 | D10: Luz | E10: Luz | F10: Pagado
C11: 37000 | D11: nana | E11: Nana | F11: Pagado
C12: 37000 | D12: nana | E12: Nana | F12: Pagado
C13: 14253 | D13: Netflix | E13: Netflix
C14: 7094 | D14: Spotify | E14: Spotify | F14: Pagado
C15: 32000 | D15: super | E15: Supermercado | F15: Pagado
C16: 213000 | D16: super | E16: Supermercado | F16: Pagado
C17: 82000 | D17: super | E17: Supermercado | F17: Pagado
D18: Super | E18: Supermercado
C19: 132000 | D19: tag | E19: tag | F19: Pagado

Sheet febrero 25
B1: Para añadir o cambiar categorías, modifica las tablas "Ingresos" y "Gastos" de la hoja "Resumen".
B2: Gastos | D2: =IFERROR(__xludf.DUMMYFUNCTION("GOOGLEFINANCE((""CURRENCY:USDCLP""))+1"),926.24) -> 926.24 | H2: Pagos
M3: Pagado | N3: =SUMIF(F:F,"Pagado",C:C) -> 1294248.2
B4: Fecha | C4: Importe | D4: Descripción | E4: Categoría | F4: Status | H4: Fecha | I4: Importe | J4: Descripción | K4: Categoría | M4: Por pagar | N4: =SUMIF(F5:F34,"Por pagar",C5:C34) -> 0
C5: 7500 | D5: Agua | E5: Agua | F5: Pagado | I5: =SUMIF(F:F,"Pagado",C:C) -> 1294248.2 | J5: Javier | K5: Javier | Q5: =P5-O6 -> 0
C6: =15.6926*Resumen!B1 -> 640662.16 | D6: Arriendo | E6: Arriendo | F6: Pagado
C7: 17000 | D7: GTD | E7: Entel | F7: Pagado
C8: 2000 | D8: Gas | E8: Gas
C9: 195000 | D9: Gastos comunes | E9: Gastos comunes | F9: Pagado
C10: 66739 | D10: Luz | E10: Luz | F10: Pagado
C11: 37000 | D11: nana | E11: Nana | F11: Pagado
C12: 37000 | D12: nana | E12: Nana | F12: Pagado
C13: 14253 | D13: Netflix | E13: Netflix | F13: Pagado
C14: 7094 | D14: Spotify | E14: Spotify | F14: Pagado
D15: super | E15: Supermercado
C16: 85000 | D16: super | E16: Supermercado | F16: Pagado
C17: 93000 | D17: super | E17: Supermercado | F17: Pagado
D18: Super | E18: Supermercado
C19: 94000 | D19: tag | E19: tag | F19: Pagado

Sheet Enero 25
B1: Para añadir o cambiar categorías, modifica las tablas "Ingresos" y "Gastos" de la hoja "Resumen".
B2: Gastos | D2: =IFERROR(__xludf.DUMMYFUNCTION("GOOGLEFINANCE((""CURRENCY:USDCLP""))+1"),926.24) -> 926.24 | H2: Pagos
M3: Pagado | N3: =SUMIF(F:F,"Pagado",C:C) -> 1273114.2
B4: Fecha | C4: Importe | D4: Descripción | E4: Categoría | F4: Status | H4: Fecha | I4: Importe | J4: Descripción | K4: Categoría | M4: Por pagar | N4: =SUMIF(F5:F34,"Por pagar",C5:C34) -> 0
C5: 8362 | D5: Agua | E5: Agua | F5: Pagado | I5: =SUMIF(F:F,"Pagado",C:C) -> 1273114.2 | J5: Javier | K5: Javier | Q5: =P5-O6 -> 0
C6: =IFERROR(__xludf.DUMMYFUNCTION("15.6926*GOOGLEFINANCE((""CURRENCY:CLFCLP""))"),640662.16445) -> 640662.16 | D6: Arriendo | E6: Arriendo | F6: Pagado
C7: 17000 | D7: GTD | E7: Entel | F7: Pagado
C8: 2000 | D8: Gas | E8: Gas | F8: Pagado
C9: 217636 | D9: Gastos comunes | E9: Gastos comunes | F9: Pagado
C10: 82107 | D10: Luz | E10: Luz | F10: Pagado
C11: 37000 | D11: nana | E11: Nana | F11: Pagado
C12: 37000 | D12: nana | E12: Nana | F12: Pagado
C13: 14253 | D13: Netflix | E13: Netflix | F13: Pagado
C14: 7094 | D14: Spotify | E14: Spotify | F14: Pagado
C15: 174000 | D15: super | E15: Supermercado | F15: Pagado
C16: 36000 | D16: super | E16: Supermercado | F16: Pagado
D17: super | E17: Supermercado
D18: Super | E18: Supermercado

Sheet Diciembre 24
B1: Para añadir o cambiar categorías, modifica las tablas "Ingresos" y "Gastos" de la hoja "Resumen".
B2: Gastos | D2: =IFERROR(__xludf.DUMMYFUNCTION("GOOGLEFINANCE((""CURRENCY:USDCLP""))+1"),926.24) -> 926.24 | H2: Pagos
M3: Pagado | N3: =SUMIF(F:F,"Pagado",C:C) -> 1241023.2
B4: Fecha | C4: Importe | D4: Descripción | E4: Categoría | F4: Status | H4: Fecha | I4: Importe | J4: Descripción | K4: Categoría | M4: Por pagar | N4: =SUMIF(F5:F34,"Por pagar",C5:C34) -> 0
C5: 4960 | D5: Agua | E5: Agua | F5: Pagado | I5: =SUMIF(F:F,"Pagado",C:C) -> 1241023.2 | J5: Javier | K5: Javier | Q5: =P5-O6 -> 0
C6: =IFERROR(__xludf.DUMMYFUNCTION("15.6926*GOOGLEFINANCE((""CURRENCY:CLFCLP""))"),640662.16445) -> 640662.16 | D6: Arriendo | E6: Arriendo | F6: Pagado
C7: 23990 | D7: GTD | E7: Entel | F7: Pagado
C8: 5873 | D8: Gas | E8: Gas
C9: 250000 | D9: Gastos comunes | E9: Gastos comunes | F9: Pagado
C10: 24064 | D10: Luz | E10: Luz | F10: Pagado
C11: 37000 | D11: nana | E11: Nana | F11: Pagado
C12: 37000 | D12: nana | E12: Nana | F12: Pagado
C13: 14253 | D13: Netflix | E13: Netflix | F13: Pagado
C14: 7094 | D14: Spotify | E14: Spotify | F14: Pagado
C15: 162000 | D15: super | E15: Supermercado | F15: Pagado
C16: 40000 | D16: super | E16: Supermercado | F16: Pagado
D17: super | E17: Supermercado
D18: Super | E18: Supermercado

Sheet Noviembre 24
B1: Para añadir o cambiar categorías, modifica las tablas "Ingresos" y "Gastos" de la hoja "Resumen".
B2: Gastos | D2: =IFERROR(__xludf.DUMMYFUNCTION("GOOGLEFINANCE((""CURRENCY:USDCLP""))+1"),926.24) -> 926.24 | H2: Pagos
M3: Pagado | N3: =SUMIF(F:F,"Pagado",C:C) -> 1135852.2
B4: Fecha | C4: Importe | D4: Descripción | E4: Categoría | F4: Status | H4: Fecha | I4: Importe | J4: Descripción | K4: Categoría | M4: Por pagar | N4: =SUMIF(F5:F34,"Por pagar",C5:C34) -> 0
C5: 10180 | D5: Agua | E5: Agua | F5: Pagado | I5: =SUMIF(F:F,"Pagado",C:C) -> 1135852.2 | J5: Javier | K5: Javier | Q5: =P5-O6 -> 0
C6: =IFERROR(__xludf.DUMMYFUNCTION("15.6926*GOOGLEFINANCE((""CURRENCY:CLFCLP""))"),640662.16445) -> 640662.16 | D6: Arriendo | E6: Arriendo | F6: Pagado
C7: 17990 | D7: GTD | E7: Entel | F7: Pagado
C8: 5873 | D8: Gas | E8: Gas | F8: Pagado
C9: 250000 | D9: Gastos comunes | E9: Gastos comunes
C10: 43800 | D10: Luz | E10: Luz | F10: Pagado
C11: 37000 | D11: nana | E11: Nana | F11: Pagado
C12: 37000 | D12: nana | E12: Nana | F12: Pagado
C13: 14253 | D13: Netflix | E13: Netflix | F13: Pagado
C14: 7094 | D14: Spotify | E14: Spotify | F14: Pagado
C15: 322000 | D15: super | E15: Supermercado | F15: Pagado
D16: super | E16: Supermercado
D17: super | E17: Supermercado
D18: Super | E18: Supermercado

Sheet Octubre 24
B1: Para añadir o cambiar categorías, modifica las tablas "Ingresos" y "Gastos" de la hoja "Resumen".
B2: Gastos | D2: =IFERROR(__xludf.DUMMYFUNCTION("GOOGLEFINANCE((""CURRENCY:USDCLP""))+1"),926.24) -> 926.24 | H2: Pagos
M3: Pagado | N3: =SUMIF(F:F,"Pagado",C:C) -> 1451112.7
B4: Fecha | C4: Importe | D4: Descripción | E4: Categoría | F4: Status | H4: Fecha | I4: Importe | J4: Descripción | K4: Categoría | M4: Por pagar | N4: =SUMIF(F5:F34,"Por pagar",C5:C34) -> 160000
C5: 7950 | D5: Agua | E5: Agua | F5: Pagado | I5: =SUMIF(F:F,"Pagado",C:C) -> 1451112.7 | J5: Javier | K5: Javier | Q5: =P5-O6 -> 0
C6: =IFERROR(__xludf.DUMMYFUNCTION("15.6926*GOOGLEFINANCE((""CURRENCY:CLFCLP""))"),640662.16445) -> 640662.16 | D6: Arriendo | E6: Arriendo | F6: Pagado
C7: 17990 | D7: GTD | E7: Entel | F7: Pagado
C8: 5873 | D8: Gas | E8: Gas
C9: 227000 | D9: Gastos comunes | E9: Gastos comunes | F9: Pagado
C10: 24676 | D10: Luz | E10: Luz | F10: Pagado
C11: 37000 | D11: nana | E11: Nana | F11: Pagado
C12: 37000 | D12: nana | E12: Nana | F12: Pagado
C13: 14253 | D13: Netflix | E13: Netflix | F13: Pagado
C14: 7094 | D14: Spotify | E14: Spotify | F14: Pagado
C15: 32000 | D15: super | E15: Supermercado | F15: Pagado
C16: 60000 | D16: super | E16: Supermercado | F16: Pagado
C17: =(116+132+125)*D2 -> 345487.52 | D17: super | E17: Supermercado | F17: Pagado
C18: 160000 | D18: Super | E18: Supermercado | F18: Por pagar

Sheet Septiembre 24
B1: Para añadir o cambiar categorías, modifica las tablas "Ingresos" y "Gastos" de la hoja "Resumen".
B2: Gastos | D2: =IFERROR(__xludf.DUMMYFUNCTION("GOOGLEFINANCE((""CURRENCY:USDCLP""))+1"),926.24) -> 926.24 | H2: Pagos
M3: Pagado | N3: =SUMIF(F:F,"Pagado",C:C) -> 1344379.2
B4: Fecha | C4: Importe | D4: Descripción | E4: Categoría | F4: Status | H4: Fecha | I4: Importe | J4: Descripción | K4: Categoría | M4: Por pagar | N4: =SUMIF(F5:F34,"Por pagar",C5:C34) -> 0
C5: 7810 | D5: Agua | E5: Agua | F5: Pagado | I5: =SUMIF(F:F,"Pagado",C:C) -> 1344379.2 | J5: Javier | K5: Javier | Q5: =P5-O6 -> 0
C6: =IFERROR(__xludf.DUMMYFUNCTION("15.6926*GOOGLEFINANCE((""CURRENCY:CLFCLP""))"),640662.16445) -> 640662.16 | D6: Arriendo | E6: Arriendo | F6: Pagado
C7: 17990 | D7: GTD | E7: Entel | F7: Pagado
C8: 5873 | D8: Gas | E8: Gas | F8: Pagado
C9: 252000 | D9: Gastos comunes | E9: Gastos comunes | F9: Pagado
C10: 27697 | D10: Luz | E10: Luz | F10: Pagado
C11: 37000 | D11: nana | E11: Nana | F11: Pagado
C12: 37000 | D12: nana | E12: Nana | F12: Pagado
C13: 14253 | D13: Netflix | E13: Netflix | F13: Pagado
C14: 7094 | D14: Spotify | E14: Spotify | F14: Pagado
C15: 57000 | D15: super | E15: Supermercado | F15: Pagado
C16: 80000 | D16: super | E16: Supermercado | F16: Pagado
C17: 99000 | D17: super | E17: Supermercado
C18: 160000 | D18: Super | E18: Supermercado | F18: Pagado

Sheet Agosto 24
B1: Para añadir o cambiar categorías, modifica las tablas "Ingresos" y "Gastos" de la hoja "Resumen".
B2: Gastos | D2: =IFERROR(__xludf.DUMMYFUNCTION("GOOGLEFINANCE((""CURRENCY:USDCLP""))+1"),926.24) -> 926.24 | H2: Pagos
M3: Pagado | N3: =SUMIF(F:F,"Pagado",C:C) -> 1374041.2
B4: Fecha | C4: Importe | D4: Descripción | E4: Categoría | F4: Status | H4: Fecha | I4: Importe | J4: Descripción | K4: Categoría | M4: Por pagar | N4: =SUMIF(F5:F34,"Por pagar",C5:C34) -> 0
C5: 9100 | D5: Agua | E5: Agua | F5: Pagado | I5: =SUMIF(F:F,"Pagado",C:C) -> 1374041.2 | J5: Javier | K5: Javier | Q5: =P5-O6 -> 0
C6: =IFERROR(__xludf.DUMMYFUNCTION("15.6926*GOOGLEFINANCE((""CURRENCY:CLFCLP""))"),640662.16445) -> 640662.16 | D6: Arriendo | E6: Arriendo | F6: Pagado
C7: 17990 | D7: GTD | E7: Entel | F7: Pagado
D8: Gas | E8: Gas
C9: 251000 | D9: Gastos comunes | E9: Gastos comunes | F9: Pagado
C10: 38432 | D10: Luz | E10: Luz | F10: Pagado
C11: 37000 | D11: nana | E11: Nana | F11: Pagado
C12: 37000 | D12: nana | E12: Nana | F12: Pagado
C13: 14253 | D13: Netflix | E13: Netflix | F13: Pagado
C14: 7094 | D14: Spotify | E14: Spotify | F14: Pagado
C15: 39510 | D15: super | E15: Supermercado | F15: Pagado
C16: 80000 | D16: super | E16: Supermercado | F16: Pagado
C17: 99000 | D17: super | E17: Supermercado | F17: Pagado
C18: 103000 | D18: Super | E18: Supermercado | F18: Pagado

Sheet Julio 24
B1: Para añadir o cambiar categorías, modifica las tablas "Ingresos" y "Gastos" de la hoja "Resumen".
B2: Gastos | D2: =IFERROR(__xludf.DUMMYFUNCTION("GOOGLEFINANCE((""CURRENCY:USDCLP""))+1"),926.24) -> 926.24 | H2: Pagos
M3: Pagado | N3: =SUMIF(F:F,"Pagado",C:C) -> 1170683.2
B4: Fecha | C4: Importe | D4: Descripción | E4: Categoría | F4: Status | H4: Fecha | I4: Importe | J4: Descripción | K4: Categoría | M4: Por pagar | N4: =SUMIF(F5:F34,"Por pagar",C5:C34) -> 0
C5: 7490 | D5: Agua | E5: Agua | F5: Pagado | I5: =SUMIF(F:F,"Pagado",C:C) -> 1170683.2 | J5: Javier | K5: Javier | Q5: =P5-O6 -> 0
C6: =IFERROR(__xludf.DUMMYFUNCTION("15.6926*GOOGLEFINANCE((""CURRENCY:CLFCLP""))"),640662.16445) -> 640662.16 | D6: Arriendo | E6: Arriendo | F6: Pagado
C7: 17990 | D7: GTD | E7: Entel | F7: Pagado
C8: 6300 | D8: Gas | E8: Gas | F8: Pagado
C9: 252000 | D9: Gastos comunes | E9: Gastos comunes | F9: Pagado
C10: 38894 | D10: Luz | E10: Luz | F10: Pagado
C11: 37000 | D11: nana | E11: Nana | F11: Pagado
C12: 37000 | D12: nana | E12: Nana | F12: Pagado
C13: 14253 | D13: Netflix | E13: Netflix | F13: Pagado
C14: 7094 | D14: Spotify | E14: Spotify | F14: Pagado
C15: 92000 | D15: super | E15: Supermercado | F15: Pagado
C16: 20000 | D16: super | E16: Supermercado | F16: Pagado
D17: super | E17: Supermercado
D18: Super | E18: Supermercado

Sheet Junio 24
B1: Para añadir o cambiar categorías, modifica las tablas "Ingresos" y "Gastos" de la hoja "Resumen".
B2: Gastos | D2: =IFERROR(__xludf.DUMMYFUNCTION("GOOGLEFINANCE((""CURRENCY:USDCLP""))+1"),926.24) -> 926.24 | H2: Pagos
M3: Pagado | N3: =SUMIF(F:F,"Pagado",C:C) -> 1357276.2
B4: Fecha | C4: Importe | D4: Descripción | E4: Categoría | F4: Status | H4: Fecha | I4: Importe | J4: Descripción | K4: Categoría | M4: Por pagar | N4: =SUMIF(F5:F34,"Por pagar",C5:C34) -> 0
D5: Gas | E5: Gas | I5: =SUMIF(F:F,"Pagado",C:C) -> 1357276.2 | J5: Javier | K5: Javier | Q5: =P5-O6 -> 0
C6: 10320 | D6: Agua | E6: Agua | F6: Pagado
C7: 7094 | D7: Spotify | E7: Spotify | F7: Pagado
C8: 35993 | D8: Luz | E8: Luz | F8: Pagado
C9: 14253 | D9: Netflix | E9: Netflix | F9: Pagado
C10: 40000 | D10: super | E10: Supermercado | F10: Pagado
C11: 52000 | D11: super | E11: Supermercado | F11: Pagado
C12: 17990 | D12: Entel | E12: Entel | F12: Pagado
C13: 234964 | D13: Gastos comunes | E13: Gastos comunes | F13: Pagado
C14: =IFERROR(__xludf.DUMMYFUNCTION("15.6926*GOOGLEFINANCE((""CURRENCY:CLFCLP""))"),640662.16445) -> 640662.16 | D14: Arriendo | E14: Arriendo | F14: Pagado
C15: 164000 | D15: super | E15: Supermercado | F15: Pagado
C16: 37000 | D16: nana | E16: Nana | F16: Pagado
C17: 66000 | D17: Super | E17: Supermercado | F17: Pagado
C18: 37000 | D18: nana | E18: Nana | F18: Pagado

Sheet Mayo 24
B1: Para añadir o cambiar categorías, modifica las tablas "Ingresos" y "Gastos" de la hoja "Resumen".
B2: Gastos | D2: =IFERROR(__xludf.DUMMYFUNCTION("GOOGLEFINANCE((""CURRENCY:USDCLP""))+1"),926.24) -> 926.24 | I2: Pagos
N3: Pagado | O3: =SUMIF(F:F,"Pagado",C:C) -> 1332080.6
B4: Fecha | C4: Importe | D4: Descripción | E4: Categoría | F4: Status | I4: Fecha | J4: Importe | K4: Descripción | L4: Categoría | N4: Por pagar | O4: =SUMIF(F5:F34,"Por pagar",C5:C34) -> 0
C5: 6321 | D5: Gas | E5: Gas | F5: Pagado | J5: =SUMIF(F:F,"Pagado",C:C) -> 1332080.6 | K5: Javier | L5: Javier | R5: =Q5-P6 -> 0
C6: 7490 | D6: Agua | E6: Agua | F6: Pagado
C7: 7094 | D7: Spotify | E7: Spotify | F7: Pagado
C8: 30617 | D8: Luz | E8: Luz | F8: Pagado
C9: 14253 | D9: Netflix | E9: Netflix | F9: Pagado
C10: =146.66*884 -> 129647.44 | D10: super | E10: Supermercado | F10: Pagado
C11: 67255 | D11: super | E11: Supermercado | F11: Pagado
C12: 19777 | D12: Entel | E12: Entel | F12: Pagado
C13: 226964 | D13: Gastos comunes | E13: Gastos comunes | F13: Pagado
C14: =IFERROR(__xludf.DUMMYFUNCTION("15.6926*GOOGLEFINANCE((""CURRENCY:CLFCLP""))"),640662.16445) -> 640662.16 | D14: Arriendo | E14: Arriendo | F14: Pagado
C15: 108000 | D15: super | E15: Supermercado | F15: Pagado
C16: 37000 | D16: nana | E16: Nana | F16: Pagado
C17: 37000 | E17: Nana | F17: Pagado

Sheet abril 24
B1: Para añadir o cambiar categorías, modifica las tablas "Ingresos" y "Gastos" de la hoja "Resumen".
B2: Gastos | D2: =IFERROR(__xludf.DUMMYFUNCTION("GOOGLEFINANCE((""CURRENCY:USDCLP""))+1"),926.24) -> 926.24 | I2: Pagos
N3: Pagado | O3: =SUMIF(F:F,"Pagado",C:C) -> 1358432.2
B4: Fecha | C4: Importe | D4: Descripción | E4: Categoría | F4: Status | I4: Fecha | J4: Importe | K4: Descripción | L4: Categoría | N4: Por pagar | O4: =SUMIF(F5:F34,"Por pagar",C5:C34) -> 0
D5: Gas | E5: Gas | J5: =SUMIF(F:F,"Pagado",C:C) -> 1358432.2 | K5: Javier | L5: Javier | R5: =Q5-P6 -> 0
C6: 10320 | D6: Agua | E6: Agua | F6: Pagado
C7: 7400 | D7: Spotify | E7: Spotify | F7: Pagado
C8: 26500 | D8: Luz | E8: Luz | F8: Pagado
C9: 10700 | D9: Netflix | E9: Netflix | F9: Pagado
C10: 121000 | D10: super | E10: Supermercado | F10: Pagado
C11: 112000 | D11: super | E11: Supermercado | F11: Pagado
C12: 29850 | D12: Entel | E12: Entel | F12: Pagado
C13: 216000 | D13: Gastos comunes | E13: Gastos comunes | F13: Pagado
C14: =IFERROR(__xludf.DUMMYFUNCTION("15.6926*GOOGLEFINANCE((""CURRENCY:CLFCLP""))"),640662.16445) -> 640662.16 | D14: Arriendo | E14: Arriendo | F14: Pagado
C15: 147000 | D15: super | E15: Supermercado | F15: Pagado
C16: 37000 | D16: nana | E16: Nana | F16: Pagado

Sheet Marzo 24
B1: Para añadir o cambiar categorías, modifica las tablas "Ingresos" y "Gastos" de la hoja "Resumen".
B2: Gastos | D2: =IFERROR(__xludf.DUMMYFUNCTION("GOOGLEFINANCE((""CURRENCY:USDCLP""))+1"),926.24) -> 926.24 | I2: Pagos
N3: Pagado | O3: =SUMIF(F:F,"Pagado",C:C) -> 1034633.2
B4: Fecha | C4: Importe | D4: Descripción | E4: Categoría | F4: Status | I4: Fecha | J4: Importe | K4: Descripción | L4: Categoría | N4: Por pagar | O4: =SUMIF(F5:F34,"Por pagar",C5:C34) -> 0
C5: 3958 | D5: Gas | E5: Gas | F5: Pagado | J5: =SUMIF(F:F,"Pagado",C:C) -> 1034633.2 | K5: Javier | L5: Javier | R5: =Q5-P6 -> 0
C6: 8340 | D6: Agua | E6: Agua | F6: Pagado
C7: 7400 | D7: Spotify | E7: Spotify | F7: Pagado
C8: 41316 | D8: Luz | E8: Luz | F8: Pagado
C9: 10700 | D9: Netflix | E9: Netflix | F9: Pagado
C10: 70000 | D10: super | E10: Supermercado | F10: Pagado
D11: super | E11: Supermercado
C12: 21380 | D12: Entel | E12: Entel | F12: Pagado
C13: 230877 | D13: Gastos comunes | E13: Gastos comunes | F13: Pagado
C14: =IFERROR(__xludf.DUMMYFUNCTION("15.6926*GOOGLEFINANCE((""CURRENCY:CLFCLP""))"),640662.16445) -> 640662.16 | D14: Arriendo | E14: Arriendo | F14: Pagado

Sheet Febrero 24
B1: Para añadir o cambiar categorías, modifica las tablas "Ingresos" y "Gastos" de la hoja "Resumen".
B2: Gastos | D2: =IFERROR(__xludf.DUMMYFUNCTION("GOOGLEFINANCE((""CURRENCY:USDCLP""))+1"),926.24) -> 926.24 | I2: Pagos
N3: Pagado | O3: =SUMIF(F:F,"Pagado",C:C) -> 1023399.2
B4: Fecha | C4: Importe | D4: Descripción | E4: Categoría | F4: Status | I4: Fecha | J4: Importe | K4: Descripción | L4: Categoría | N4: Por pagar | O4: =SUMIF(F5:F34,"Por pagar",C5:C34) -> 0
D5: Gas | E5: Gas | J5: =SUMIF(F:F,"Pagado",C:C) -> 1023399.2 | K5: Javier | L5: Javier | R5: =Q5-P6 -> 0
C6: 10880 | D6: Agua | E6: Agua | F6: Pagado
C7: 7400 | D7: Spotify | E7: Spotify | F7: Pagado
C8: 36500 | D8: Luz | E8: Luz | F8: Pagado
C9: 10700 | D9: Netflix | E9: Netflix | F9: Pagado
C10: 70000 | D10: super | E10: Supermercado | F10: Pagado
D11: super | E11: Supermercado
C12: 21380 | D12: Entel | E12: Entel | F12: Pagado
C13: 225877 | D13: Gastos comunes | E13: Gastos comunes | F13: Pagado
C14: =IFERROR(__xludf.DUMMYFUNCTION("15.6926*GOOGLEFINANCE((""CURRENCY:CLFCLP""))"),640662.16445) -> 640662.16 | D14: Arriendo | E14: Arriendo | F14: Pagado

Sheet Enero 24
B1: Para añadir o cambiar categorías, modifica las tablas "Ingresos" y "Gastos" de la hoja "Resumen".
B2: Gastos | D2: =IFERROR(__xludf.DUMMYFUNCTION("GOOGLEFINANCE((""CURRENCY:USDCLP""))+1"),926.24) -> 926.24 | I2: Pagos
N3: Pagado | O3: =SUMIF(F:F,"Pagado",C:C) -> 947372.16
B4: Fecha | C4: Importe | D4: Descripción | E4: Categoría | F4: Status | I4: Fecha | J4: Importe | K4: Descripción | L4: Categoría | N4: Por pagar | O4: =SUMIF(F5:F34,"Por pagar",C5:C34) -> 0
D5: Gas | E5: Gas | J5: =SUMIF(F:F,"Pagado",C:C) -> 947372.16 | K5: Javier | L5: Javier | R5: =Q5-P6 -> 0
C6: 11280 | D6: Agua | E6: Agua | F6: Pagado
C7: 7400 | D7: Spotify | E7: Spotify | F7: Pagado
C8: 30073 | D8: Luz | E8: Luz | F8: Pagado
C9: 10700 | D9: Netflix | E9: Netflix | F9: Pagado
D10: super | E10: Supermercado
D11: super | E11: Supermercado
C12: 21380 | D12: Entel | E12: Entel | F12: Pagado
C13: 225877 | D13: Gastos comunes | E13: Gastos comunes | F13: Pagado
C14: =IFERROR(__xludf.DUMMYFUNCTION("15.6926*GOOGLEFINANCE((""CURRENCY:CLFCLP""))"),640662.16445) -> 640662.16 | D14: Arriendo | E14: Arriendo | F14: Pagado

Sheet Diciembre 23
B1: Para añadir o cambiar categorías, modifica las tablas "Ingresos" y "Gastos" de la hoja "Resumen".
B2: Gastos | D2: =IFERROR(__xludf.DUMMYFUNCTION("GOOGLEFINANCE((""CURRENCY:USDCLP""))+1"),926.24) -> 926.24 | I2: Pagos
N3: Pagado | O3: =SUMIF(F:F,"Pagado",C:C) -> 939504.16
B4: Fecha | C4: Importe | D4: Descripción | E4: Categoría | F4: Status | I4: Fecha | J4: Importe | K4: Descripción | L4: Categoría | N4: Por pagar | O4: =SUMIF(F5:F34,"Por pagar",C5:C34) -> 0
D5: Gas | E5: Gas | J5: =SUMIF(F:F,"Pagado",C:C) -> 939504.16 | K5: Javier | L5: Javier | R5: =Q5-P6 -> 0
C6: 7640 | D6: Agua | E6: Agua | F6: Pagado
C7: 7400 | D7: Spotify | E7: Spotify | F7: Pagado
C8: 16507 | D8: Luz | E8: Luz | F8: Pagado
C9: 10700 | D9: Netflix | E9: Netflix | F9: Pagado
C10: =130000*2/3 -> 86666.667 | D10: super | E10: Supermercado
C11: =110000*2/3 -> 73333.333 | D11: super | E11: Supermercado
C12: 20718 | D12: Entel | E12: Entel | F12: Pagado
C13: 235877 | D13: Gastos comunes | E13: Gastos comunes | F13: Pagado
C14: =IFERROR(__xludf.DUMMYFUNCTION("15.6926*GOOGLEFINANCE((""CURRENCY:CLFCLP""))"),640662.16445) -> 640662.16 | D14: Arriendo | E14: Arriendo | F14: Pagado

Sheet Noviembre 23
B1: Para añadir o cambiar categorías, modifica las tablas "Ingresos" y "Gastos" de la hoja "Resumen".
B2: Gastos | D2: =IFERROR(__xludf.DUMMYFUNCTION("GOOGLEFINANCE((""CURRENCY:USDCLP""))+1"),926.24) -> 926.24 | I2: Pagos
N3: Pagado | O3: =SUMIF(F:F,"Pagado",C:C) -> 917328.16
B4: Fecha | C4: Importe | D4: Descripción | E4: Categoría | F4: Status | I4: Fecha | J4: Importe | K4: Descripción | L4: Categoría | N4: Por pagar | O4: =SUMIF(F5:F34,"Por pagar",C5:C34) -> 0
D5: Gas | E5: Gas | J5: =SUMIF(F:F,"Pagado",C:C) -> 917328.16 | K5: Javier | L5: Javier | R5: =Q5-P6 -> 0
C6: 10770 | D6: Agua | E6: Agua | F6: Pagado
C7: 7400 | D7: Spotify | E7: Spotify
C8: 15695 | D8: Luz | E8: Luz | F8: Pagado
C9: 10700 | D9: Netflix | E9: Netflix | F9: Pagado
C10: =130000*2/3 -> 86666.667 | D10: super | E10: Supermercado
C11: =110000*2/3 -> 73333.333 | D11: super | E11: Supermercado
C12: 20718 | D12: Entel | E12: Entel | F12: Pagado
C13: 218783 | D13: Gastos comunes | E13: Gastos comunes | F13: Pagado
C14: =IFERROR(__xludf.DUMMYFUNCTION("15.6926*GOOGLEFINANCE((""CURRENCY:CLFCLP""))"),640662.16445) -> 640662.16 | D14: Arriendo | E14: Arriendo | F14: Pagado

Sheet Octubre 23
B1: Para añadir o cambiar categorías, modifica las tablas "Ingresos" y "Gastos" de la hoja "Resumen".
B2: Gastos | D2: =IFERROR(__xludf.DUMMYFUNCTION("GOOGLEFINANCE((""CURRENCY:USDCLP""))+1"),926.24) -> 926.24 | I2: Pagos
N3: Pagado | O3: =SUMIF(F:F,"Pagado",C:C) -> 1002729.8
B4: Fecha | C4: Importe | D4: Descripción | E4: Categoría | F4: Status | I4: Fecha | J4: Importe | K4: Descripción | L4: Categoría | N4: Por pagar | O4: =SUMIF(F5:F34,"Por pagar",C5:C34) -> 0
D5: Gas | E5: Gas | J5: =SUMIF(F:F,"Pagado",C:C) -> 1002729.8 | K5: Javier | L5: Javier | R5: =Q5-P6 -> 0
C6: 6500 | D6: Agua | E6: Agua | F6: Pagado
C7: 7400 | D7: Spotify | E7: Spotify | F7: Pagado
C8: 15300 | D8: Luz | E8: Luz | F8: Pagado
C9: 10700 | D9: Netflix | E9: Netflix | F9: Pagado
C10: =130000*2/3 -> 86666.667 | D10: super | E10: Supermercado | F10: Pagado
C11: =110000*2/3 -> 73333.333 | D11: super | E11: Supermercado
C12: 20718 | D12: Entel | E12: Entel | F12: Pagado
C13: 214783 | D13: Gastos comunes | E13: Gastos comunes | F13: Pagado
C14: =IFERROR(__xludf.DUMMYFUNCTION("15.6926*GOOGLEFINANCE((""CURRENCY:CLFCLP""))"),640662.16445) -> 640662.16 | D14: Arriendo | E14: Arriendo | F14: Pagado

Sheet Septiembre 23
B1: Para añadir o cambiar categorías, modifica las tablas "Ingresos" y "Gastos" de la hoja "Resumen".
B2: Gastos | D2: =IFERROR(__xludf.DUMMYFUNCTION("GOOGLEFINANCE((""CURRENCY:USDCLP""))+1"),926.24) -> 926.24 | I2: Pagos
N3: Pagado | O3: =SUMIF(F:F,"Pagado",C:C) -> 1075105.2
B4: Fecha | C4: Importe | D4: Descripción | E4: Categoría | F4: Status | I4: Fecha | J4: Importe | K4: Descripción | L4: Categoría | N4: Por pagar | O4: =SUMIF(F5:F34,"Por pagar",C5:C34) -> 0
D5: Gas | E5: Gas | J5: =SUMIF(F:F,"Pagado",C:C) -> 1075105.2 | K5: Javier | L5: Javier | R5: =Q5-P6 -> 0
C6: 5980 | D6: Agua | E6: Agua | F6: Pagado
C7: 7400 | D7: Spotify | E7: Spotify | F7: Pagado
C8: 21446 | D8: Luz | E8: Luz | F8: Pagado
C9: 10700 | D9: Netflix | E9: Netflix | F9: Pagado
C10: =130000*2/3 -> 86666.667 | D10: super | E10: Supermercado | F10: Pagado
C11: =110000*2/3 -> 73333.333 | D11: super | E11: Supermercado | F11: Pagado
C12: 20718 | D12: Entel | E12: Entel | F12: Pagado
C13: 208199 | D13: Gastos comunes | E13: Gastos comunes | F13: Pagado
C14: =IFERROR(__xludf.DUMMYFUNCTION("15.6926*GOOGLEFINANCE((""CURRENCY:CLFCLP""))"),640662.16445) -> 640662.16 | D14: Arriendo | E14: Arriendo | F14: Pagado

Sheet Agosto 23
B1: Para añadir o cambiar categorías, modifica las tablas "Ingresos" y "Gastos" de la hoja "Resumen".
B2: Gastos | D2: =IFERROR(__xludf.DUMMYFUNCTION("GOOGLEFINANCE((""CURRENCY:USDCLP""))+1"),926.24) -> 926.24 | I2: Pagos
N3: Pagado | O3: =SUMIF(F:F,"Pagado",C:C) -> 1036731.2
B4: Fecha | C4: Importe | D4: Descripción | E4: Categoría | F4: Status | I4: Fecha | J4: Importe | K4: Descripción | L4: Categoría | N4: Por pagar | O4: =SUMIF(F5:F34,"Por pagar",C5:C34) -> 0
D5: Gas | E5: Gas | J5: =SUMIF(F:F,"Pagado",C:C) -> 1036731.2 | K5: Javier | L5: Javier | R5: =Q5-P6 -> 0
C6: 4890 | D6: Agua | E6: Agua | F6: Pagado
C7: 7400 | D7: Spotify | E7: Spotify | F7: Pagado
C8: 13890 | D8: Luz | E8: Luz | F8: Pagado
C9: 10700 | D9: Netflix | E9: Netflix | F9: Pagado
C10: 130000 | D10: super | E10: Supermercado | F10: Pagado
D11: super | E11: Supermercado
C12: 19990 | D12: Entel | E12: Entel | F12: Pagado
C13: 209199 | D13: Gastos comunes | E13: Gastos comunes | F13: Pagado
C14: =IFERROR(__xludf.DUMMYFUNCTION("15.6926*GOOGLEFINANCE((""CURRENCY:CLFCLP""))"),640662.16445) -> 640662.16 | D14: Arriendo | E14: Arriendo | F14: Pagado

Sheet Julio 23
B1: Para añadir o cambiar categorías, modifica las tablas "Ingresos" y "Gastos" de la hoja "Resumen".
B2: Gastos | D2: =IFERROR(__xludf.DUMMYFUNCTION("GOOGLEFINANCE((""CURRENCY:USDCLP""))+1"),926.24) -> 926.24 | I2: Pagos
N3: Pagado | O3: =SUMIF(F:F,"Pagado",C:C) -> 1073078.2
B4: Fecha | C4: Importe | D4: Descripción | E4: Categoría | F4: Status | I4: Fecha | J4: Importe | K4: Descripción | L4: Categoría | N4: Por pagar | O4: =SUMIF(F5:F34,"Por pagar",C5:C34) -> 0
D5: Gas | E5: Gas | J5: =SUMIF(F:F,"Pagado",C:C) -> 1073078.2 | K5: Javier | L5: Javier | R5: =Q5-P6 -> 0
C6: 2380 | D6: Agua | E6: Agua | F6: Pagado
C7: 6300 | D7: Spotify | E7: Spotify | F7: Pagado
C8: 15117 | D8: Luz | E8: Luz | F8: Pagado
C9: 10700 | D9: Netflix | E9: Netflix | F9: Pagado
C10: 200000 | D10: super | E10: Supermercado | F10: Pagado
D11: super | E11: Supermercado
C12: 19990 | D12: Entel | E12: Entel | F12: Pagado
C13: 177929 | D13: Gastos comunes | E13: Gastos comunes | F13: Pagado
C14: =IFERROR(__xludf.DUMMYFUNCTION("15.6926*GOOGLEFINANCE((""CURRENCY:CLFCLP""))"),640662.16445) -> 640662.16 | D14: Arriendo | E14: Arriendo | F14: Pagado

Sheet Junio 23
B1: Para añadir o cambiar categorías, modifica las tablas "Ingresos" y "Gastos" de la hoja "Resumen".
B2: Gastos | D2: =IFERROR(__xludf.DUMMYFUNCTION("GOOGLEFINANCE((""CURRENCY:USDCLP""))+1"),926.24) -> 926.24 | I2: Pagos
N3: Pagado | O3: =SUMIF(F:F,"Pagado",C:C) -> 1011411.2
B4: Fecha | C4: Importe | D4: Descripción | E4: Categoría | F4: Status | I4: Fecha | J4: Importe | K4: Descripción | L4: Categoría | N4: Por pagar | O4: =SUMIF(F5:F34,"Por pagar",C5:C34) -> 0
D5: Gas | E5: Gas | J5: =SUMIF(F:F,"Pagado",C:C) -> 1011411.2 | K5: Javier | L5: Javier | R5: =Q5-P6 -> 0
C6: 2380 | D6: Agua | E6: Agua | F6: Pagado
C7: 6300 | D7: Spotify | E7: Spotify | F7: Pagado
C8: 7308 | D8: Luz | E8: Luz | F8: Pagado
C9: 10700 | D9: Netflix | E9: Netflix | F9: Pagado
C10: 140000 | D10: super | E10: Supermercado | F10: Pagado
D11: super | E11: Supermercado
C12: 19990 | D12: Entel | E12: Entel | F12: Pagado
C13: 184071 | D13: Gastos comunes | E13: Gastos comunes | F13: Pagado
C14: =IFERROR(__xludf.DUMMYFUNCTION("15.6926*GOOGLEFINANCE((""CURRENCY:CLFCLP""))"),640662.16445) -> 640662.16 | D14: Arriendo | E14: Arriendo | F14: Pagado

Sheet Mayo 23
B1: Para añadir o cambiar categorías, modifica las tablas "Ingresos" y "Gastos" de la hoja "Resumen".
B2: Gastos | D2: =IFERROR(__xludf.DUMMYFUNCTION("GOOGLEFINANCE((""CURRENCY:USDCLP""))+1"),926.24) -> 926.24 | I2: Pagos
N3: Pagado | O3: =SUMIF(F:F,"Pagado",C:C) -> 1024717.2
B4: Fecha | C4: Importe | D4: Descripción | E4: Categoría | F4: Status | I4: Fecha | J4: Importe | K4: Descripción | L4: Categoría | N4: Por pagar | O4: =SUMIF(F5:F34,"Por pagar",C5:C34) -> 0
D5: Gas | E5: Gas | J5: =SUMIF(F:F,"Pagado",C:C) -> 1024717.2 | K5: Javier | L5: Javier | R5: =Q5-P6 -> 0
C6: 4670 | D6: Agua | E6: Agua | F6: Pagado
C7: 6300 | D7: Spotify | E7: Spotify | F7: Pagado
C8: 8324 | D8: Luz | E8: Luz | F8: Pagado
C9: 10700 | D9: Netflix | E9: Netflix | F9: Pagado
C10: 140000 | D10: super | E10: Supermercado | F10: Pagado
D11: super | E11: Supermercado
C12: 19990 | D12: Entel | E12: Entel | F12: Pagado
C13: 194071 | D13: Gastos comunes | E13: Gastos comunes | F13: Pagado
C14: =IFERROR(__xludf.DUMMYFUNCTION("15.6926*GOOGLEFINANCE((""CURRENCY:CLFCLP""))"),640662.16445) -> 640662.16 | D14: Arriendo | E14: Arriendo | F14: Pagado

Sheet Abril 23
B1: Para añadir o cambiar categorías, modifica las tablas "Ingresos" y "Gastos" de la hoja "Resumen".
B2: Gastos | D2: =IFERROR(__xludf.DUMMYFUNCTION("GOOGLEFINANCE((""CURRENCY:USDCLP""))+1"),926.24) -> 926.24 | I2: Pagos
N3: Pagado | O3: =SUMIF(F:F,"Pagado",C:C) -> 909870.16
B4: Fecha | C4: Importe | D4: Descripción | E4: Categoría | F4: Status | I4: Fecha | J4: Importe | K4: Descripción | L4: Categoría | N4: Por pagar | O4: =SUMIF(F5:F34,"Por pagar",C5:C34) -> 0
C5: 1887 | D5: Gas | E5: Gas | F5: Pagado | J5: =SUMIF(F:F,"Pagado",C:C) -> 909870.16 | K5: Javier | L5: Javier | R5: =Q5-P6 -> 0
C6: 5020 | D6: Agua | E6: Agua | F6: Pagado
C7: 6300 | D7: Spotify | E7: Spotify | F7: Pagado
C8: 8000 | D8: Luz | E8: Luz | F8: Pagado
C9: 10700 | D9: Netflix | E9: Netflix | F9: Pagado
C10: 15000 | D10: super | E10: Supermercado | F10: Pagado
C11: 17600 | D11: super | E11: Supermercado | F11: Pagado
C12: 19990 | D12: Entel | E12: Entel | F12: Pagado
C13: 184711 | D13: Gastos comunes | E13: Gastos comunes | F13: Pagado
C14: =IFERROR(__xludf.DUMMYFUNCTION("15.6926*GOOGLEFINANCE((""CURRENCY:CLFCLP""))"),640662.16445) -> 640662.16 | D14: Arriendo | E14: Arriendo | F14: Pagado
D21: Super | E21: Supermercado
D22: ecook | E22: Supermercado
D23: super | E23: Supermercado

Sheet Marzo 23
B1: Para añadir o cambiar categorías, modifica las tablas "Ingresos" y "Gastos" de la hoja "Resumen".
B2: Gastos | D2: =IFERROR(__xludf.DUMMYFUNCTION("GOOGLEFINANCE((""CURRENCY:USDCLP""))+1"),926.24) -> 926.24 | I2: Pagos
N3: Pagado | O3: =SUMIF(F:F,"Pagado",C:C) -> 1095476.5
B4: Fecha | C4: Importe | D4: Descripción | E4: Categoría | F4: Status | I4: Fecha | J4: Importe | K4: Descripción | L4: Categoría | N4: Por pagar | O4: =SUMIF(F5:F34,"Por pagar",C5:C34) -> 0
C5: 0 | D5: Gas | E5: Gas | J5: =SUMIF(F:F,"Pagado",C:C) -> 1095476.5 | K5: Javier | L5: Javier | R5: =Q5-P6 -> 0
C6: 6320 | D6: Agua | E6: Agua | F6: Pagado
C7: 6300 | D7: Spotify | E7: Spotify | F7: Pagado
C8: 9602 | D8: Luz | E8: Luz | F8: Pagado
C9: 10700 | D9: Netflix | E9: Netflix | F9: Pagado
C10: 27990 | D10: Entel | E10: Entel | F10: Pagado
C11: 30000 | D11: Nana | E11: Nana
C12: 30000 | D12: Nana | E12: Nana
C13: 30000 | D13: nana | E13: Nana
C14: 30000 | D14: Nana | E14: Nana
C15: 30000 | D15: nana | E15: Nana
D16: super | E16: Supermercado
C17: =175537/3 -> 58512.333 | D17: contribuciones | E17: Contribuciones | F17: Pagado
C18: 197555 | D18: Gastos comunes | E18: Gastos comunes | F18: Pagado
C19: =IFERROR(__xludf.DUMMYFUNCTION("15.6926*GOOGLEFINANCE((""CURRENCY:CLFCLP""))"),640662.16445) -> 640662.16 | D19: Arriendo | E19: Arriendo | F19: Pagado
C20: 60000 | D20: Super | E20: Supermercado | F20: Pagado
D21: ecook | E21: Supermercado
C22: 36000 | D22: super | E22: Supermercado | F22: Pagado
C23: 41835 | D23: super | E23: Supermercado | F23: Pagado

Sheet Febrero 23
B1: Para añadir o cambiar categorías, modifica las tablas "Ingresos" y "Gastos" de la hoja "Resumen".
B2: Gastos | D2: =IFERROR(__xludf.DUMMYFUNCTION("GOOGLEFINANCE((""CURRENCY:USDCLP""))+1"),926.24) -> 926.24 | H2: Pagos
M3: Pagado | N3: =SUMIF(F:F,"Pagado",C:C) -> 1122510.5
B4: Fecha | C4: Importe | D4: Descripción | E4: Categoría | F4: Status | H4: Fecha | I4: Importe | J4: Descripción | K4: Categoría | M4: Por pagar | N4: =SUMIF(F5:F34,"Por pagar",C5:C34) -> 0
C5: 0 | D5: Gas | E5: Gas | I5: =SUMIF(F:F,"Pagado",C:C) -> 1122510.5 | J5: Javier | K5: Javier | Q5: =P5-O6 -> 0
C6: 3910 | D6: Agua | E6: Agua | F6: Pagado
C7: 6300 | D7: Spotify | E7: Spotify | F7: Pagado
C8: 9867 | D8: Luz | E8: Luz | F8: Pagado
C9: 10700 | D9: Netflix | E9: Netflix | F9: Pagado
C10: 27990 | D10: Entel | E10: Entel | F10: Pagado
C11: 30000 | D11: Nana | E11: Nana | F11: Pagado
C12: 30000 | D12: Nana | E12: Nana | F12: Pagado
C13: 30000 | D13: nana | E13: Nana | F13: Pagado
C14: 30000 | D14: Nana | E14: Nana | F14: Pagado
C15: 30000 | D15: nana | E15: Nana | F15: Pagado
C16: 42000 | D16: super | E16: Supermercado | F16: Pagado
C17: =175537/3 -> 58512.333 | D17: contribuciones | E17: Contribuciones | F17: Pagado
C18: 172569 | D18: Gastos comunes | E18: Gastos comunes | F18: Pagado
C19: =IFERROR(__xludf.DUMMYFUNCTION("15.6926*GOOGLEFINANCE((""CURRENCY:CLFCLP""))"),640662.16445) -> 640662.16 | D19: Arriendo | E19: Arriendo | F19: Pagado
D20: Super | E20: Supermercado
D21: ecook | E21: Supermercado
D22: super | E22: Supermercado
D23: super | E23: Supermercado

Sheet Enero 23
B1: Para añadir o cambiar categorías, modifica las tablas "Ingresos" y "Gastos" de la hoja "Resumen".
B2: Gastos | D2: =IFERROR(__xludf.DUMMYFUNCTION("GOOGLEFINANCE((""CURRENCY:USDCLP""))+1"),926.24) -> 926.24 | H2: Pagos
M3: Pagado | N3: =SUMIF(F:F,"Pagado",C:C) -> 1208033.5
B4: Fecha | C4: Importe | D4: Descripción | E4: Categoría | F4: Status | H4: Fecha | I4: Importe | J4: Descripción | K4: Categoría | M4: Por pagar | N4: =SUMIF(F5:F34,"Por pagar",C5:C34) -> 0
C5: 6300 | D5: Spotify | E5: Spotify | I5: =SUMIF(F:F,"Pagado",C:C) -> 1208033.5 | J5: Javier | K5: Javier | Q5: =P5-O6 -> 0
C6: 10700 | D6: Netflix | E6: Netflix | F6: Pagado
C7: 27990 | D7: Entel | E7: Entel | F7: Pagado
C8: 30000 | D8: Nana | E8: Nana | F8: Pagado
C9: 30000 | D9: Nana | E9: Nana | F9: Pagado
C10: 30000 | D10: nana | E10: Nana | F10: Pagado
C11: 30000 | D11: Nana | E11: Nana | F11: Pagado
C12: 30000 | D12: nana | E12: Nana | F12: Pagado
C13: =175537/3 -> 58512.333 | D13: contribuciones | E13: Contribuciones | F13: Pagado
C14: 189369 | D14: Gastos comunes | E14: Gastos comunes | F14: Pagado
C15: =IFERROR(__xludf.DUMMYFUNCTION("15.6926*GOOGLEFINANCE((""CURRENCY:CLFCLP""))"),640662.16445) -> 640662.16 | D15: Arriendo | E15: Arriendo | F15: Pagado
C16: 107000 | D16: Super | E16: Supermercado | F16: Pagado
C17: 11091 | D17: Luz | E17: Luz | F17: Pagado
D18: Gas | E18: Gas
C19: 2709 | D19: Agua | E19: Agua | F19: Pagado
C20: 10000 | D20: super | E20: Supermercado | F20: Pagado
D21: ecook | E21: Supermercado
D22: super | E22: Supermercado
D23: super | E23: Supermercado

Sheet diciembre 22
B1: Para añadir o cambiar categorías, modifica las tablas "Ingresos" y "Gastos" de la hoja "Resumen".
B2: Gastos | D2: =IFERROR(__xludf.DUMMYFUNCTION("GOOGLEFINANCE((""CURRENCY:USDCLP""))+1"),926.24) -> 926.24 | H2: Pagos
M3: Pagado | N3: =SUMIF(F:F,"Pagado",C:C) -> 1213097.5
B4: Fecha | C4: Importe | D4: Descripción | E4: Categoría | F4: Status | H4: Fecha | I4: Importe | J4: Descripción | K4: Categoría | M4: Por pagar | N4: =SUMIF(F5:F34,"Por pagar",C5:C34) -> 0
C5: 6300 | D5: Spotify | E5: Spotify | F5: Pagado | I5: =SUMIF(F:F,"Pagado",C:C) -> 1213097.5 | J5: Javier | K5: Javier | Q5: =P5-O6 -> 0
C6: 10700 | D6: Netflix | E6: Netflix | F6: Pagado
C7: 27990 | D7: Entel | E7: Entel | F7: Pagado
C8: 30000 | D8: Nana | E8: Nana | F8: Pagado
C9: 30000 | D9: Nana | E9: Nana | F9: Pagado
C10: 30000 | D10: nana | E10: Nana | F10: Pagado
C11: 30000 | D11: Nana | E11: Nana | F11: Pagado
C12: 30000 | E12: Nana | F12: Pagado
C13: =175537/3 -> 58512.333 | D13: contribuciones | E13: Contribuciones | F13: Pagado
C14: 178421 | D14: Gastos comunes | E14: Gastos comunes | F14: Pagado
C15: =IFERROR(__xludf.DUMMYFUNCTION("15.6926*GOOGLEFINANCE((""CURRENCY:CLFCLP""))"),640662.16445) -> 640662.16 | D15: Arriendo | E15: Arriendo | F15: Pagado
C16: 85000 | D16: Super | E16: Supermercado | F16: Pagado
C17: 9672 | D17: Luz | E17: Luz | F17: Pagado
D18: Gas | E18: Gas
C19: 5840 | D19: Agua | E19: Agua | F19: Pagado
D20: super | E20: Supermercado
D21: ecook | E21: Supermercado
C22: 40000 | D22: super | E22: Supermercado | F22: Pagado
D23: super | E23: Supermercado

Sheet noviembre 22
B1: Para añadir o cambiar categorías, modifica las tablas "Ingresos" y "Gastos" de la hoja "Resumen".
B2: Gastos | D2: =IFERROR(__xludf.DUMMYFUNCTION("GOOGLEFINANCE((""CURRENCY:USDCLP""))+1"),926.24) -> 926.24 | H2: Pagos
M3: Pagado | N3: =SUMIF(F:F,"Pagado",C:C) -> 1213097.5
B4: Fecha | C4: Importe | D4: Descripción | E4: Categoría | F4: Status | H4: Fecha | I4: Importe | J4: Descripción | K4: Categoría | M4: Por pagar | N4: =SUMIF(F5:F34,"Por pagar",C5:C34) -> 0
C5: 6300 | D5: Spotify | E5: Spotify | F5: Pagado | I5: =SUMIF(F:F,"Pagado",C:C) -> 1213097.5 | J5: Javier | K5: Javier | Q5: =P5-O6 -> 0
C6: 10700 | D6: Netflix | E6: Netflix | F6: Pagado
C7: 27990 | D7: Entel | E7: Entel | F7: Pagado
C8: 30000 | D8: Nana | E8: Nana | F8: Pagado
C9: 30000 | D9: Nana | E9: Nana | F9: Pagado
C10: 30000 | D10: nana | E10: Nana | F10: Pagado
C11: 30000 | D11: Nana | E11: Nana | F11: Pagado
C12: 30000 | E12: Nana | F12: Pagado
C13: =175537/3 -> 58512.333 | D13: contribuciones | E13: Contribuciones | F13: Pagado
C14: 178421 | D14: Gastos comunes | E14: Gastos comunes | F14: Pagado
C15: =IFERROR(__xludf.DUMMYFUNCTION("15.6926*GOOGLEFINANCE((""CURRENCY:CLFCLP""))"),640662.16445) -> 640662.16 | D15: Arriendo | E15: Arriendo | F15: Pagado
C16: 85000 | D16: Super | E16: Supermercado | F16: Pagado
C17: 9672 | D17: Luz | E17: Luz | F17: Pagado
D18: Gas | E18: Gas
C19: 5840 | D19: Agua | E19: Agua | F19: Pagado
D20: super | E20: Supermercado
D21: ecook | E21: Supermercado
C22: 40000 | D22: super | E22: Supermercado | F22: Pagado
D23: super | E23: Supermercado

Sheet octubre 22
B1: Para añadir o cambiar categorías, modifica las tablas "Ingresos" y "Gastos" de la hoja "Resumen".
B2: Gastos | D2: =IFERROR(__xludf.DUMMYFUNCTION("GOOGLEFINANCE((""CURRENCY:USDCLP""))+1"),926.24) -> 926.24 | H2: Pagos
M3: Pagado | N3: =SUMIF(F:F,"Pagado",C:C) -> 1251164.5
B4: Fecha | C4: Importe | D4: Descripción | E4: Categoría | F4: Status | H4: Fecha | I4: Importe | J4: Descripción | K4: Categoría | M4: Por pagar | N4: =SUMIF(F5:F34,"Por pagar",C5:C34) -> 0
C5: 6300 | D5: Spotify | E5: Spotify | F5: Pagado | I5: =SUMIF(F:F,"Pagado",C:C) -> 1251164.5 | J5: Javier | K5: Javier | Q5: =P5-O6 -> 0
C6: 10700 | D6: Netflix | E6: Netflix | F6: Pagado
C7: 27990 | D7: Entel | E7: Entel | F7: Pagado
C8: 30000 | D8: Nana | E8: Nana | F8: Pagado
C9: 30000 | D9: Nana | E9: Nana | F9: Pagado
C10: 30000 | D10: nana | E10: Nana | F10: Pagado
C11: 30000 | D11: Nana | E11: Nana | F11: Pagado
C12: 30000 | E12: Nana | F12: Pagado
C13: =175537/3 -> 58512.333 | D13: contribuciones | E13: Contribuciones | F13: Pagado
C14: 199000 | D14: Gastos comunes | E14: Gastos comunes | F14: Pagado
C15: =IFERROR(__xludf.DUMMYFUNCTION("15.6926*GOOGLEFINANCE((""CURRENCY:CLFCLP""))"),640662.16445) -> 640662.16 | D15: Arriendo | E15: Arriendo | F15: Pagado
D16: Super | E16: Supermercado
D17: Luz | E17: Luz
D18: Gas | E18: Gas
D19: Agua | E19: Agua
C20: 158000 | D20: super | E20: Supermercado | F20: Pagado
D21: ecook | E21: Supermercado
D22: super | E22: Supermercado
D23: super | E23: Supermercado

Sheet septiembre 22
B1: Para añadir o cambiar categorías, modifica las tablas "Ingresos" y "Gastos" de la hoja "Resumen".
B2: Gastos | D2: =IFERROR(__xludf.DUMMYFUNCTION("GOOGLEFINANCE((""CURRENCY:USDCLP""))+1"),926.24) -> 926.24 | H2: Pagos
M3: Pagado | N3: =SUMIF(F:F,"Pagado",C:C) -> 1168302.5
B4: Fecha | C4: Importe | D4: Descripción | E4: Categoría | F4: Status | H4: Fecha | I4: Importe | J4: Descripción | K4: Categoría | M4: Por pagar | N4: =SUMIF(F5:F34,"Por pagar",C5:C34) -> 0
B5: 44805 | C5: 30000 | D5: Nana | E5: Nana | F5: Pagado | I5: =SUMIF(F:F,"Pagado",C:C) -> 1168302.5 | J5: Javier | K5: Javier | Q5: =P5-O6 -> 0
B6: 44805 | C6: 10700 | D6: Netflix | E6: Netflix | F6: Pagado
B7: 44812 | C7: 30000 | D7: nana | E7: Nana | F7: Pagado
B8: 44819 | C8: 30000 | D8: Nana | E8: Nana | F8: Pagado
B9: 44826 | C9: 30000 | D9: nana | E9: Nana | F9: Pagado
B10: 44826 | C10: 106000 | D10: Super | E10: Supermercado | F10: Pagado
C11: =175537/3 -> 58512.333 | D11: contribuciones | E11: Contribuciones | F11: Pagado
C12: 27990 | D12: Entel | E12: Entel | F12: Pagado
C13: 181886 | D13: Gastos comunes | E13: Gastos comunes | F13: Pagado
C14: 11058 | D14: Luz | E14: Luz | F14: Pagado
C15: =IFERROR(__xludf.DUMMYFUNCTION("15.6926*GOOGLEFINANCE((""CURRENCY:CLFCLP""))"),640662.16445) -> 640662.16 | D15: Arriendo | E15: Arriendo | F15: Pagado
C16: 1824 | D16: Gas | E16: Gas | F16: Pagado
C17: 3370 | D17: Agua | E17: Agua | F17: Pagado
C18: 6300 | D18: Spotify | E18: Spotify | F18: Pagado
D19: super | E19: Supermercado
C20: 30000 | D20: Nana | E20: Nana
D21: ecook | E21: Supermercado
D22: super | E22: Supermercado
D23: super | E23: Supermercado

Sheet Agosto 22
B1: Para añadir o cambiar categorías, modifica las tablas "Ingresos" y "Gastos" de la hoja "Resumen".
B2: Gastos | D2: =IFERROR(__xludf.DUMMYFUNCTION("GOOGLEFINANCE((""CURRENCY:USDCLP""))+1"),926.24) -> 926.24 | H2: Pagos
M3: Pagado | N3: =SUMIF(F:F,"Pagado",C:C) -> 1133231.5
B4: Fecha | C4: Importe | D4: Descripción | E4: Categoría | F4: Status | H4: Fecha | I4: Importe | J4: Descripción | K4: Categoría | M4: Por pagar | N4: =SUMIF(F5:F34,"Por pagar",C5:C34) -> 0
B5: 44774 | C5: 10700 | D5: Netflix | E5: Netflix | F5: Pagado | I5: =SUMIF(F:F,"Pagado",C:C) -> 1133231.5 | J5: Javier | K5: Javier | Q5: =P5-O6 -> 0
B6: 44774 | C6: =175537/3 -> 58512.333 | D6: contribuciones | E6: Contribuciones | F6: Pagado
B7: 44778 | C7: 25000 | D7: nana | E7: Nana | F7: Pagado
B8: 44785 | C8: 25000 | D8: Nana | E8: Nana | F8: Pagado
B9: 44785 | C9: 85000 | D9: super | E9: Supermercado | F9: Pagado
B10: 44788 | C10: 2210 | D10: Agua | E10: Agua | F10: Pagado
B11: 44788 | C11: 27990 | D11: Entel | E11: Entel | F11: Pagado
B12: 44791 | C12: 25000 | D12: Nana | E12: Nana | F12: Pagado
B13: 44798 | C13: 6300 | D13: Spotify | E13: Spotify | F13: Pagado
B14: 44798 | C14: 25000 | D14: nana | E14: Nana | F14: Pagado
B15: 44800 | C15: 181886 | D15: Gastos comunes | E15: Gastos comunes | F15: Pagado
B16: 44798 | C16: 19971 | D16: Luz | E16: Luz | F16: Pagado
D17: Nana | E17: Nana
C18: =IFERROR(__xludf.DUMMYFUNCTION("15.6926*GOOGLEFINANCE((""CURRENCY:CLFCLP""))"),640662.16445) -> 640662.16 | D18: Arriendo | E18: Arriendo | F18: Pagado
D19: Super | E19: Supermercado
D20: ecook | E20: Supermercado
D21: Gas | E21: Gas
D22: super | E22: Supermercado
D23: super | E23: Supermercado

Sheet Julio 22
B1: Para añadir o cambiar categorías, modifica las tablas "Ingresos" y "Gastos" de la hoja "Resumen".
B2: Gastos | D2: =IFERROR(__xludf.DUMMYFUNCTION("GOOGLEFINANCE((""CURRENCY:USDCLP""))+1"),926.24) -> 926.24 | H2: Pagos
M3: Pagado | N3: =SUMIF(F:F,"Pagado",C:C) -> 1180599.5
B4: Fecha | C4: Importe | D4: Descripción | E4: Categoría | F4: Status | H4: Fecha | I4: Importe | J4: Descripción | K4: Categoría | M4: Por pagar | N4: =SUMIF(F5:F34,"Por pagar",C5:C34) -> 0
B5: 44743 | C5: 10700 | D5: Netflix | E5: Netflix | F5: Pagado | I5: =SUMIF(F:F,"Pagado",C:C) -> 1180599.5 | J5: Javier | K5: Javier | Q5: =P5-O6 -> 0
B6: 44743 | C6: =175537/3 -> 58512.333 | D6: contribuciones | E6: Contribuciones | F6: Pagado
B7: 44749 | C7: 25000 | D7: nana | E7: Nana | F7: Pagado
B8: 44756 | C8: 25000 | D8: Nana | E8: Nana | F8: Pagado
B9: 44758 | C9: 27990 | D9: Entel | E9: Entel | F9: Pagado
B10: 44758 | C10: 19300 | D10: Luz | E10: Luz | F10: Pagado
B11: 44761 | C11: 40000 | D11: super | E11: Supermercado | F11: Pagado
B12: 44761 | C12: 4520 | D12: Agua | E12: Agua | F12: Pagado
B13: 44767 | C13: 100000 | D13: Super | E13: Supermercado | F13: Pagado
B14: 44767 | C14: =IFERROR(__xludf.DUMMYFUNCTION("15.6926*GOOGLEFINANCE((""CURRENCY:CLFCLP""))"),640662.16445) -> 640662.16 | D14: Arriendo | E14: Arriendo | F14: Pagado
B15: 44767 | C15: 178915 | D15: Gastos comunes | E15: Gastos comunes | F15: Pagado
B16: 44763 | C16: 25000 | D16: Nana | E16: Nana | F16: Pagado
B17: 44770 | C17: 25000 | D17: nana | E17: Nana | F17: Pagado
C18: 6300 | D18: Spotify | E18: Spotify
D19: ecook | E19: Supermercado
D20: Gas | E20: Gas
D21: super | E21: Supermercado
D22: super | E22: Supermercado
C23: 25000 | D23: Nana | E23: Nana

Sheet Junio 22
B1: Para añadir o cambiar categorías, modifica las tablas "Ingresos" y "Gastos" de la hoja "Resumen".
B2: Gastos | D2: =IFERROR(__xludf.DUMMYFUNCTION("GOOGLEFINANCE((""CURRENCY:USDCLP""))+1"),926.24) -> 926.24 | H2: Pagos
M3: Pagado | N3: =SUMIF(F:F,"Pagado",C:C) -> 1159349.5
B4: Fecha | C4: Importe | D4: Descripción | E4: Categoría | F4: Status | H4: Fecha | I4: Importe | J4: Descripción | K4: Categoría | M4: Por pagar | N4: =SUMIF(F5:F34,"Por pagar",C5:C34) -> 0
B5: 44713 | C5: 10700 | D5: Netflix | E5: Netflix | F5: Pagado | I5: =SUMIF(F:F,"Pagado",C:C) -> 1159349.5 | J5: Javier | K5: Javier | Q5: =P5-O6 -> 0
B6: 44713 | C6: =175537/3 -> 58512.333 | D6: contribuciones | E6: Contribuciones | F6: Pagado
B7: 44714 | C7: 25000 | D7: Nana | E7: Nana | F7: Pagado
B8: 44721 | C8: 25000 | D8: Nana | E8: Nana | F8: Pagado
B9: 44726 | C9: 27990 | D9: Entel | E9: Entel | F9: Pagado
B10: 44729 | C10: 25000 | D10: nana | E10: Nana | F10: Pagado
B11: 44732 | C11: 12000 | D11: Luz | E11: Luz | F11: Pagado
B12: 44732 | C12: 6300 | D12: Spotify | E12: Spotify | F12: Pagado
B13: 44733 | C13: 100000 | D13: Super | E13: Supermercado | F13: Pagado
B14: 44735 | C14: 25000 | D14: nana | E14: Nana | F14: Pagado
D15: super | E15: Supermercado
B16: 44741 | C16: =IFERROR(__xludf.DUMMYFUNCTION("15.6926*GOOGLEFINANCE((""CURRENCY:CLFCLP""))"),640662.16445) -> 640662.16 | D16: Arriendo | E16: Arriendo | F16: Pagado
D17: ecook | E17: Supermercado
C18: 4320 | D18: Agua | E18: Agua | F18: Pagado
B19: 44737 | C19: 173865 | D19: Gastos comunes | E19: Gastos comunes | F19: Pagado
D20: Gas | E20: Gas
D21: super | E21: Supermercado
D22: super | E22: Supermercado
C23: 25000 | D23: Nana | E23: Nana | F23: Pagado

Sheet Mayo 22
B1: Para añadir o cambiar categorías, modifica las tablas "Ingresos" y "Gastos" de la hoja "Resumen".
B2: Gastos | D2: =IFERROR(__xludf.DUMMYFUNCTION("GOOGLEFINANCE((""CURRENCY:USDCLP""))+1"),926.24) -> 926.24 | H2: Pagos
M3: Pagado | N3: =SUMIF(F:F,"Pagado",C:C) -> 1219272.5
B4: Fecha | C4: Importe | D4: Descripción | E4: Categoría | F4: Status | H4: Fecha | I4: Importe | J4: Descripción | K4: Categoría | M4: Por pagar | N4: =SUMIF(F5:F34,"Por pagar",C5:C34) -> 0
B5: 44682 | C5: 10700 | D5: Netflix | E5: Netflix | F5: Pagado | I5: =SUMIF(F:F,"Pagado",C:C) -> 1219272.5 | J5: Javier | K5: Javier | Q5: =P5-O6 -> 0
B6: 44683 | C6: 27990 | D6: Entel | E6: Entel | F6: Pagado
B7: 44686 | C7: 25000 | D7: Nana | E7: Nana | F7: Pagado
B8: 44690 | C8: 95000 | D8: super | E8: Supermercado | F8: Pagado
B9: 44693 | C9: 25000 | D9: Nana | E9: Nana | F9: Pagado
B10: 44700 | C10: 25000 | D10: nana | E10: Nana | F10: Pagado
B11: 44700 | C11: 45000 | D11: Super | E11: Supermercado | F11: Pagado
B12: 44701 | C12: 6300 | D12: Spotify | E12: Spotify | F12: Pagado
B13: 44701 | C13: 10563 | D13: Luz | E13: Luz | F13: Pagado
B14: 44705 | C14: =175537/3 -> 58512.333 | D14: contribuciones | E14: Contribuciones | F14: Pagado
B15: 44707 | C15: =IFERROR(__xludf.DUMMYFUNCTION("15.6926*GOOGLEFINANCE((""CURRENCY:CLFCLP""))"),640662.16445) -> 640662.16 | D15: Arriendo | E15: Arriendo | F15: Pagado
D16: ecook | E16: Supermercado
B17: 44707 | C17: 25000 | D17: nana | E17: Nana | F17: Pagado
C18: 10070 | D18: Agua | E18: Agua | F18: Pagado
B19: 44705 | C19: 172675 | D19: Gastos comunes | E19: Gastos comunes | F19: Pagado
C20: 1800 | D20: Gas | E20: Gas | F20: Pagado
C21: 40000 | D21: super | E21: Supermercado | F21: Pagado
D22: super | E22: Supermercado

Sheet Abril 22
B1: Para añadir o cambiar categorías, modifica las tablas "Ingresos" y "Gastos" de la hoja "Resumen".
B2: Gastos | D2: =IFERROR(__xludf.DUMMYFUNCTION("GOOGLEFINANCE((""CURRENCY:USDCLP""))+1"),926.24) -> 926.24 | H2: Pagos
M3: Pagado | N3: =SUMIF(F:F,"Pagado",C:C) -> 1133849.5
B4: Fecha | C4: Importe | D4: Descripción | E4: Categoría | F4: Status | H4: Fecha | I4: Importe | J4: Descripción | K4: Categoría | M4: Por pagar | N4: =SUMIF(F5:F34,"Por pagar",C5:C34) -> 0
B5: 44652 | C5: 10700 | D5: Netflix | E5: Netflix | F5: Pagado | I5: =SUMIF(F:F,"Pagado",C:C) -> 1133849.5 | J5: Javier | K5: Javier | Q5: =P5-O6 -> 0
B6: 44658 | C6: 25000 | D6: Nana | E6: Nana | F6: Pagado
B7: 44665 | C7: 27990 | D7: Entel | E7: Entel | F7: Pagado
B8: 44665 | C8: 25000 | D8: Nana | E8: Nana | F8: Pagado
B9: 44669 | C9: 108000 | D9: super | E9: Supermercado | F9: Pagado
B10: 44671 | C10: 6300 | D10: Spotify | E10: Spotify | F10: Pagado
B11: 44672 | C11: 9255 | D11: Luz | E11: Luz | F11: Pagado
B12: 44672 | C12: 25000 | D12: nana | E12: Nana | F12: Pagado
B13: 44673 | C13: =IFERROR(__xludf.DUMMYFUNCTION("15.6926*GOOGLEFINANCE((""CURRENCY:CLFCLP""))"),640662.16445) -> 640662.16 | D13: Arriendo | E13: Arriendo | F13: Pagado
B14: 44677 | C14: =175537/3 -> 58512.333 | D14: contribuciones | E14: Contribuciones | F14: Pagado
D15: ecook | E15: Supermercado
B16: 44681 | C16: 25000 | D16: nana | E16: Nana | F16: Pagado
C17: 4370 | D17: Agua | E17: Agua | F17: Pagado
D18: Super | E18: Supermercado
B19: 44677 | C19: 168060 | D19: Gastos comunes | E19: Gastos comunes | F19: Pagado
D20: Gas | E20: Gas
D21: super | E21: Supermercado
D22: super | E22: Supermercado

Sheet Marzo 22
B1: Para añadir o cambiar categorías, modifica las tablas "Ingresos" y "Gastos" de la hoja "Resumen".
B2: Gastos | D2: =IFERROR(__xludf.DUMMYFUNCTION("GOOGLEFINANCE((""CURRENCY:USDCLP""))+1"),926.24) -> 926.24 | H2: Pagos
M3: Pagado | N3: =SUMIF(F:F,"Pagado",C:C) -> 1342265.2
B4: Fecha | C4: Importe | D4: Descripción | E4: Categoría | F4: Status | H4: Fecha | I4: Importe | J4: Descripción | K4: Categoría | M4: Por pagar | N4: =SUMIF(F5:F34,"Por pagar",C5:C34) -> 0
B5: 44621 | C5: 10700 | D5: Netflix | E5: Netflix | F5: Pagado | I5: =SUMIF(F:F,"Pagado",C:C) -> 1342265.2 | J5: Javier | K5: Javier | Q5: =P5-O6 -> 0
B6: 44621 | C6: 56333 | D6: contribuciones | E6: Contribuciones | F6: Pagado
B7: 44621 | C7: 120000 | D7: super | E7: Supermercado | F7: Pagado
B8: 44623 | C8: 25000 | D8: Nana | E8: Nana | F8: Pagado
B9: 44628 | C9: 117000 | D9: ecook | E9: Supermercado | F9: Pagado
B10: 44631 | C10: 25000 | D10: nana | E10: Nana | F10: Pagado
B11: 44635 | C11: 4160 | D11: Agua | E11: Agua | F11: Pagado
B12: 44635 | C12: 8900 | D12: Luz | E12: Luz | F12: Pagado
B13: 44635 | C13: 27990 | D13: Entel | E13: Entel | F13: Pagado
B14: 44640 | C14: 6300 | D14: Spotify | E14: Spotify | F14: Pagado
B15: 44638 | C15: 25000 | D15: Nana | E15: Nana | F15: Pagado
B16: 44651 | C16: 25000 | D16: nana | E16: Nana | F16: Pagado
B17: 44644 | C17: 71000 | D17: Super | E17: Supermercado | F17: Pagado
B18: 44644 | C18: 177531 | D18: Gastos comunes | E18: Gastos comunes | F18: Pagado
B19: 44644 | C19: =IFERROR(__xludf.DUMMYFUNCTION("15.6926*GOOGLEFINANCE((""CURRENCY:CLFCLP""))"),640662.16445) -> 640662.16 | D19: Arriendo | E19: Arriendo | F19: Pagado
C20: 1689 | D20: Gas | E20: Gas | F20: Pagado
D21: super | E21: Supermercado
D22: super | E22: Supermercado

Sheet Febrero 22
B1: Para añadir o cambiar categorías, modifica las tablas "Ingresos" y "Gastos" de la hoja "Resumen".
B2: Gastos | D2: =IFERROR(__xludf.DUMMYFUNCTION("GOOGLEFINANCE((""CURRENCY:USDCLP""))+1"),926.24) -> 926.24 | H2: Pagos
M3: Pagado | N3: =SUMIF(F:F,"Pagado",C:C) -> 1073428.2
B4: Fecha | C4: Importe | D4: Descripción | E4: Categoría | F4: Status | H4: Fecha | I4: Importe | J4: Descripción | K4: Categoría | M4: Por pagar | N4: =SUMIF(F5:F34,"Por pagar",C5:C34) -> 0
B5: 44593 | C5: 6300 | D5: Spotify | E5: Spotify | F5: Pagado | I5: =SUMIF(F:F,"Pagado",C:C) -> 1073428.2 | J5: Javier | K5: Javier | Q5: =P5-O6 -> 0
C6: 7580 | D6: Agua | E6: Agua | F6: Pagado
B7: 44593 | C7: 10700 | D7: Netflix | E7: Netflix | F7: Pagado
C8: 10841 | D8: Luz | E8: Luz | F8: Pagado
B9: 44595 | C9: 25000 | D9: Nana | E9: Nana | F9: Pagado
B10: 44620 | C10: 25000 | D10: nana | E10: Nana | F10: Pagado
B11: 44616 | C11: 25000 | D11: nana | E11: Nana | F11: Pagado
B12: 44599 | C12: 28420 | D12: Entel | E12: Entel | F12: Pagado
B13: 44601 | C13: 30000 | D13: Nana | E13: Nana | F13: Pagado
C14: 40000 | D14: Super | E14: Supermercado | F14: Pagado
B15: 44593 | C15: 56333 | D15: contribuciones | E15: Contribuciones | F15: Pagado
C16: 167592 | D16: Gastos comunes | E16: Gastos comunes | F16: Pagado
C17: =IFERROR(__xludf.DUMMYFUNCTION("15.6926*GOOGLEFINANCE((""CURRENCY:CLFCLP""))"),640662.16445) -> 640662.16 | D17: Arriendo | E17: Arriendo | F17: Pagado
D18: ecook | E18: Supermercado
D19: Gas | E19: Gas
D20: super | E20: Supermercado
D21: super | E21: Supermercado
D22: super | E22: Supermercado

Sheet Enero 22
B1: Para añadir o cambiar categorías, modifica las tablas "Ingresos" y "Gastos" de la hoja "Resumen".
B2: Gastos | D2: =IFERROR(__xludf.DUMMYFUNCTION("GOOGLEFINANCE((""CURRENCY:USDCLP""))+1"),926.24) -> 926.24 | H2: Pagos
M3: Pagado | N3: =SUMIF(F:F,"Pagado",C:C) -> 1169085.2
B4: Fecha | C4: Importe | D4: Descripción | E4: Categoría | F4: Status | H4: Fecha | I4: Importe | J4: Descripción | K4: Categoría | M4: Por pagar | N4: =SUMIF(F5:F34,"Por pagar",C5:C34) -> 0
C5: 1600 | D5: Gas | E5: Gas | F5: Pagado | I5: =SUMIF(F:F,"Pagado",C:C) -> 1169085.2 | J5: Javier | K5: Javier | Q5: =P5-O6 -> 0
C6: 6300 | D6: Spotify | E6: Spotify | F6: Pagado
C7: 10700 | D7: Netflix | E7: Netflix | F7: Pagado
C8: 12600 | D8: Luz | E8: Luz | F8: Pagado
C9: 15700 | D9: Agua | E9: Agua | F9: Pagado
C10: 25000 | D10: Nana | E10: Nana | F10: Pagado
C11: 25000 | D11: Nana | E11: Nana | F11: Pagado
C12: 25000 | D12: nana | E12: Nana | F12: Pagado
C13: 29190 | D13: Entel | E13: Entel | F13: Pagado
C14: 35000 | D14: super | E14: Supermercado | F14: Pagado
C15: 47000 | D15: Super | E15: Supermercado | F15: Pagado
C16: 56333 | D16: contribuciones | E16: Contribuciones | F16: Pagado
C17: 156000 | D17: Gastos comunes | E17: Gastos comunes | F17: Pagado
C18: =IFERROR(__xludf.DUMMYFUNCTION("15.6926*GOOGLEFINANCE((""CURRENCY:CLFCLP""))"),640662.16445) -> 640662.16 | D18: Arriendo | E18: Arriendo | F18: Pagado
C19: 58000 | D19: super | E19: Supermercado | F19: Pagado
D20: super | E20: Supermercado
D21: ecook | E21: Supermercado
C22: 25000 | D22: nana | E22: Nana | F22: Pagado

Sheet Diciembre 21
B1: Para añadir o cambiar categorías, modifica las tablas "Ingresos" y "Gastos" de la hoja "Resumen".
B2: Gastos | D2: =IFERROR(__xludf.DUMMYFUNCTION("GOOGLEFINANCE((""CURRENCY:USDCLP""))+1"),926.24) -> 926.24 | H2: Pagos
M3: Pagado | N3: =SUMIF(F:F,"Pagado",C:C) -> 958473
B4: Fecha | C4: Importe | D4: Descripción | E4: Categoría | F4: Status | H4: Fecha | I4: Importe | J4: Descripción | K4: Categoría | M4: Por pagar | N4: =SUMIF(F5:F34,"Por pagar",C5:C34) -> 0
C5: 6300 | D5: Spotify | E5: Spotify | F5: Pagado | I5: =SUMIF(F:F,"Pagado",C:C) -> 958473 | J5: Javier | K5: Javier | Q5: =P5-O6 -> 0
C6: 10700 | D6: Netflix | E6: Netflix | F6: Pagado
C7: 11800 | D7: Luz | E7: Luz | F7: Pagado
C8: 28000 | D8: Entel | E8: Entel | F8: Pagado
C9: 36940 | D9: Super | E9: Supermercado | F9: Pagado
C10: 56333 | D10: contribuciones | E10: Contribuciones | F10: Pagado
C11: 482000 | D11: Arriendo | E11: Arriendo | F11: Pagado
C12: 28000 | D12: super | E12: Supermercado | F12: Pagado
D13: super | E13: Supermercado
D14: super | E14: Supermercado
C15: 106000 | D15: ecook | E15: Supermercado | F15: Pagado
D16: Agua | E16: Agua
D17: lider | E17: Supermercado
C18: 142400 | D18: Gastos comunes | E18: Gastos comunes | F18: Pagado
D19: Gas | E19: Gas
C20: 25000 | D20: Nana | E20: Nana | F20: Pagado
C21: 25000 | E21: Nana | F21: Pagado

Sheet Noviembre 21
B1: Para añadir o cambiar categorías, modifica las tablas "Ingresos" y "Gastos" de la hoja "Resumen".
B2: Gastos | D2: =IFERROR(__xludf.DUMMYFUNCTION("GOOGLEFINANCE((""CURRENCY:USDCLP""))+1"),926.24) -> 926.24 | H2: Pagos
M3: Pagado | N3: =SUMIF(F:F,"Pagado",C:C) -> 960282
B4: Fecha | C4: Importe | D4: Descripción | E4: Categoría | F4: Status | H4: Fecha | I4: Importe | J4: Descripción | K4: Categoría | M4: Por pagar | N4: =SUMIF(F5:F34,"Por pagar",C5:C34) -> 0
C5: 6300 | D5: Spotify | E5: Spotify | F5: Pagado | I5: =SUMIF(F:F,"Pagado",C:C) -> 960282 | J5: Javier | K5: Javier | Q5: =P5-O6 -> 0
C6: 10700 | D6: Netflix | E6: Netflix | F6: Pagado
C7: 13852 | D7: Luz | E7: Luz | F7: Pagado
C8: 27990 | D8: Entel | E8: Entel | F8: Pagado
C9: 85000 | D9: Super | E9: Supermercado | F9: Pagado
C10: 56333 | D10: contribuciones | E10: Contribuciones | F10: Pagado
C11: 471000 | D11: Arriendo | E11: Arriendo | F11: Pagado
C12: 53000 | D12: super | E12: Supermercado | F12: Pagado
C13: 45421 | D13: super | E13: Supermercado | F13: Pagado
D14: super | E14: Supermercado
D15: ecook | E15: Supermercado
C16: 6350 | D16: Agua | E16: Agua | F16: Pagado
D17: lider | E17: Supermercado
C18: 180954 | D18: Gastos comunes | E18: Gastos comunes | F18: Pagado
C19: 3382 | D19: Gas | E19: Gas | F19: Pagado

Sheet Octubre 21
B1: Para añadir o cambiar categorías, modifica las tablas "Ingresos" y "Gastos" de la hoja "Resumen".
B2: Gastos | D2: =IFERROR(__xludf.DUMMYFUNCTION("GOOGLEFINANCE((""CURRENCY:USDCLP""))+1"),926.24) -> 926.24 | H2: Pagos
M3: Pagado | N3: =SUMIF(F:F,"Pagado",C:C) -> 909270
B4: Fecha | C4: Importe | D4: Descripción | E4: Categoría | F4: Status | H4: Fecha | I4: Importe | J4: Descripción | K4: Categoría | M4: Por pagar | N4: =SUMIF(F5:F34,"Por pagar",C5:C34) -> 0
B5: 44471 | C5: 6300 | D5: Spotify | E5: Spotify | F5: Pagado | I5: =SUMIF(F:F,"Pagado",C:C) -> 909270 | J5: Javier | K5: Javier | Q5: =P5-O6 -> 0
B6: 44471 | C6: 10700 | D6: Netflix | E6: Netflix | F6: Pagado
B7: 44475 | C7: 13200 | D7: Luz | E7: Luz | F7: Pagado
B8: 44475 | C8: 27990 | D8: Entel | E8: Entel | F8: Pagado
B9: 44482 | C9: 23000 | D9: Super | E9: Supermercado | F9: Pagado
C10: 25400 | D10: super | E10: Supermercado | F10: Pagado
B11: 44481 | C11: 46362 | D11: super | E11: Supermercado | F11: Pagado
C12: 56333 | D12: contribuciones | E12: Contribuciones | F12: Pagado
B13: 44472 | C13: 60000 | D13: super | E13: Supermercado | F13: Pagado
C14: 466000 | D14: Arriendo | E14: Arriendo | F14: Pagado
D15: ecook | E15: Supermercado
B16: 44494 | C16: 5190 | D16: Agua | E16: Agua | F16: Pagado
D17: lider | E17: Supermercado
B18: 44494 | C18: 168795 | D18: Gastos comunes | E18: Gastos comunes | F18: Pagado
D19: Gas | E19: Gas

Sheet Septiembre 21
B1: Para añadir o cambiar categorías, modifica las tablas "Ingresos" y "Gastos" de la hoja "Resumen".
B2: Gastos | D2: =IFERROR(__xludf.DUMMYFUNCTION("GOOGLEFINANCE((""CURRENCY:USDCLP""))+1"),926.24) -> 926.24 | H2: Pagos
M3: Pagado | N3: =SUMIF(F:F,"Pagado",C:C) -> 1114275
B4: Fecha | C4: Importe | D4: Descripción | E4: Categoría | F4: Status | H4: Fecha | I4: Importe | J4: Descripción | K4: Categoría | M4: Por pagar | N4: =SUMIF(F5:F34,"Por pagar",C5:C34) -> 0
B5: 44440 | C5: 6300 | D5: Spotify | E5: Spotify | F5: Pagado | I5: =SUMIF(F:F,"Pagado",C:C) -> 1114275 | J5: Javier | K5: Javier | Q5: =P5-O6 -> 0
B6: 44440 | C6: 10700 | D6: Netflix | E6: Netflix | F6: Pagado
B7: 44440 | C7: 466000 | D7: Arriendo | E7: Arriendo | F7: Pagado
B8: 44444 | C8: 21990 | D8: GTD | E8: Entel | F8: Pagado
B9: 44444 | C9: 56333 | D9: contribuciones | E9: Contribuciones | F9: Pagado
B10: 44452 | C10: 80000 | D10: super | E10: Supermercado | F10: Pagado
B11: 44453 | C11: 119000 | D11: ecook | E11: Supermercado | F11: Pagado
B12: 44456 | C12: 8200 | D12: Agua | E12: Agua | F12: Pagado
B13: 44456 | C13: 32000 | D13: super | E13: Supermercado | F13: Pagado
B14: 44456 | C14: 49000 | D14: lider | E14: Supermercado | F14: Pagado
D15: Luz | E15: Luz
B16: 44465 | C16: 84000 | D16: Super | E16: Supermercado | F16: Pagado
B17: 44462 | C17: 177519 | D17: Gastos comunes | E17: Gastos comunes | F17: Pagado
B18: 44462 | C18: 3233 | D18: Gas | E18: Gas | F18: Pagado
D19: corner 4

Sheet Agosto 21
B1: Para añadir o cambiar categorías, modifica las tablas "Ingresos" y "Gastos" de la hoja "Resumen".
B2: Gastos | D2: =IFERROR(__xludf.DUMMYFUNCTION("GOOGLEFINANCE((""CURRENCY:USDCLP""))+1"),926.24) -> 926.24 | H2: Pagos
M3: Pagado | N3: =SUMIF(F:F,"Pagado",C:C) -> 814107
B4: Fecha | C4: Importe | D4: Descripción | E4: Categoría | F4: Status | H4: Fecha | I4: Importe | J4: Descripción | K4: Categoría | M4: Por pagar | N4: =SUMIF(F5:F34,"Por pagar",C5:C34) -> 0
B5: 44409 | C5: 466000 | D5: Arriendo | E5: Arriendo | F5: Pagado | I5: =SUMIF(F:F,"Pagado",C:C) -> 814107 | J5: Javier | K5: Javier | Q5: =P5-O6 -> 0
B6: 44409 | C6: 53333 | D6: contribuciones | E6: Contribuciones | F6: Pagado
B7: 44410 | C7: 6300 | D7: Spotify | E7: Spotify | F7: Pagado
B8: 44410 | C8: 10700 | D8: Netflix | E8: Netflix | F8: Pagado
B9: 44409 | C9: 57210 | D9: super | E9: Supermercado | F9: Pagado
B10: 44417 | C10: 21990 | D10: GTD | E10: Entel | F10: Pagado
B11: 44431 | C11: 12000 | D11: Luz | E11: Luz | F11: Pagado
D12: Agua | E12: Agua
D13: Super | E13: Supermercado
D14: ecook | E14: Supermercado
C15: 174074 | D15: Gastos comunes | E15: Gastos comunes | F15: Pagado
D16: Gas | E16: Gas
B17: 44418 | C17: 12500 | D17: lider | E17: Supermercado | F17: Pagado
D18: corner 4
D19: super | E19: Supermercado

Sheet Julio 21
B1: Para añadir o cambiar categorías, modifica las tablas "Ingresos" y "Gastos" de la hoja "Resumen".
B2: Gastos | D2: =IFERROR(__xludf.DUMMYFUNCTION("GOOGLEFINANCE((""CURRENCY:USDCLP""))+1"),926.24) -> 926.24 | H2: Pagos
M3: Pagado | N3: =SUMIF(F:F,"Pagado",C:C) -> 969900
B4: Fecha | C4: Importe | D4: Descripción | E4: Categoría | F4: Status | H4: Fecha | I4: Importe | J4: Descripción | K4: Categoría | M4: Por pagar | N4: =SUMIF(F5:F34,"Por pagar",C5:C34) -> 0
B5: 44378 | C5: 6300 | D5: Spotify | E5: Spotify | F5: Pagado | I5: =SUMIF(F:F,"Pagado",C:C) -> 969900 | J5: Javier | K5: Javier | Q5: =P5-O6 -> 0
B6: 44378 | C6: 10700 | D6: Netflix | E6: Netflix | F6: Pagado
B7: 44378 | C7: 27000 | D7: super | E7: Supermercado | F7: Pagado
B8: 44378 | C8: 466000 | D8: Arriendo | E8: Arriendo | F8: Pagado
B9: 44378 | C9: 53333 | D9: contribuciones | E9: Contribuciones | F9: Pagado
B10: 44381 | C10: 21990 | D10: GTD | E10: Entel | F10: Pagado
B11: 44385 | C11: 7818 | D11: Luz | E11: Luz | F11: Pagado
B12: 44395 | C12: 15130 | D12: Agua | E12: Agua | F12: Pagado
B13: 44395 | C13: 126000 | D13: Super | E13: Supermercado | F13: Pagado
B14: 44397 | C14: 68452 | D14: ecook | E14: Supermercado | F14: Pagado
B15: 44401 | C15: 162615 | D15: Gastos comunes | E15: Gastos comunes | F15: Pagado
B16: 44401 | C16: 4562 | D16: Gas | E16: Gas | F16: Pagado
D17: lider | E17: Supermercado
D18: corner 4
D19: super | E19: Supermercado

Sheet Junio 21
B1: Para añadir o cambiar categorías, modifica las tablas "Ingresos" y "Gastos" de la hoja "Resumen".
B2: Gastos | D2: =IFERROR(__xludf.DUMMYFUNCTION("GOOGLEFINANCE((""CURRENCY:USDCLP""))+1"),926.24) -> 926.24 | H2: Pagos
M3: Pagado | N3: =SUMIF(F:F,"Pagado",C:C) -> 1009413
B4: Fecha | C4: Importe | D4: Descripción | E4: Categoría | F4: Status | H4: Fecha | I4: Importe | J4: Descripción | K4: Categoría | M4: Por pagar | N4: =SUMIF(F5:F34,"Por pagar",C5:C34) -> 0
B5: 44348 | C5: 10700 | D5: Netflix | E5: Netflix | F5: Pagado | I5: =SUMIF(F:F,"Pagado",C:C) -> 1009413 | J5: Javier | K5: Javier | Q5: =P5-O6 -> 0
B6: 44348 | C6: 116589 | D6: ecook | E6: Supermercado | F6: Pagado
B7: 44348 | C7: 466000 | D7: Arriendo | E7: Arriendo | F7: Pagado
B8: 44349 | C8: 6300 | D8: Spotify | E8: Spotify | F8: Pagado
B9: 44355 | C9: 21990 | D9: GTD | E9: Entel | F9: Pagado
B10: 44356 | C10: 28500 | D10: Super | E10: Supermercado | F10: Pagado
B11: 44362 | C11: 1900 | D11: Agua | E11: Agua | F11: Pagado
B12: 44362 | C12: 14181 | D12: Luz | E12: Luz | F12: Pagado
B13: 44362 | C13: 28000 | D13: super | E13: Supermercado | F13: Pagado
B14: 44362 | C14: 35700 | D14: lider | E14: Supermercado | F14: Pagado
B15: 44371 | C15: 171383 | D15: Gastos comunes | E15: Gastos comunes | F15: Pagado
D16: Gas | E16: Gas
B17: 44370 | C17: 45170 | D17: corner 4 | F17: Pagado
B18: 44373 | C18: 63000 | D18: super | E18: Supermercado | F18: Pagado

Sheet mayo 21
B1: Para añadir o cambiar categorías, modifica las tablas "Ingresos" y "Gastos" de la hoja "Resumen".
B2: Gastos | D2: =IFERROR(__xludf.DUMMYFUNCTION("GOOGLEFINANCE((""CURRENCY:USDCLP""))+1"),926.24) -> 926.24 | H2: Pagos
M3: Pagado | N3: =SUMIF(F:F,"Pagado",C:C) -> 1015479
B4: Fecha | C4: Importe | D4: Descripción | E4: Categoría | F4: Status | H4: Fecha | I4: Importe | J4: Descripción | K4: Categoría | M4: Por pagar | N4: =SUMIF(F5:F34,"Por pagar",C5:C34) -> 0
B5: 44333 | C5: 2690 | D5: Agua | E5: Agua | F5: Pagado | I5: =SUMIF(F:F,"Pagado",C:C) -> 1015479 | J5: Javier | K5: Javier | Q5: =P5-O6 -> 0
B6: 44317 | C6: 6300 | D6: Spotify | E6: Spotify | F6: Pagado
B7: 44317 | C7: 10700 | D7: Netflix | E7: Netflix | F7: Pagado
B8: 44330 | C8: 21990 | D8: GTD | E8: Entel | F8: Pagado
B9: 44333 | C9: 26468 | D9: Luz | E9: Luz | F9: Pagado
B10: 44326 | C10: 44874 | D10: Cornershop III | E10: Supermercado | F10: Pagado
B11: 44317 | C11: 54710 | D11: lider | E11: Supermercado | F11: Pagado
B12: 44317 | C12: 61750 | D12: ecook | E12: Supermercado | F12: Pagado
B13: 44334 | C13: 70000 | D13: Super | E13: Supermercado | F13: Pagado
B14: 44341 | C14: 161513 | D14: Gastos comunes | E14: Gastos comunes | F14: Pagado
B15: 44341 | C15: 550000 | D15: Arriendo | E15: Arriendo | F15: Pagado
B16: 44341 | C16: 4484 | D16: Gas | E16: Gas | F16: Pagado
D17: corner 4

Sheet abril 21
B1: Para añadir o cambiar categorías, modifica las tablas "Ingresos" y "Gastos" de la hoja "Resumen".
B2: Gastos | D2: =IFERROR(__xludf.DUMMYFUNCTION("GOOGLEFINANCE((""CURRENCY:USDCLP""))+1"),926.24) -> 926.24 | H2: Pagos
M3: Pagado | N3: =SUMIF(F:F,"Pagado",C:C) -> 1041831
B4: Fecha | C4: Importe | D4: Descripción | E4: Categoría | F4: Status | H4: Fecha | I4: Importe | J4: Descripción | K4: Categoría | M4: Por pagar | N4: =SUMIF(F5:F34,"Por pagar",C5:C34) -> 0
B5: 44287 | C5: 10700 | D5: Netflix | E5: Netflix | F5: Pagado | I5: =SUMIF(F:F,"Pagado",C:C) -> 1041831 | J5: Javier | K5: Javier | Q5: =P5-O6 -> 0
B6: 44287 | C6: 6300 | D6: Spotify | E6: Spotify | F6: Pagado
B7: 44289 | C7: =62000*0.7 -> 43400 | D7: Cornershop I | E7: Supermercado | F7: Pagado
B8: 44294 | C8: 21990 | D8: Entel | E8: Entel | F8: Pagado
B9: 44295 | C9: 58000 | D9: Cornershop II | E9: Supermercado | F9: Pagado
B10: 44302 | C10: 69000 | D10: ecook | E10: Supermercado | F10: Pagado
C11: 12200 | D11: Agua | E11: Agua | F11: Pagado
C12: 16185 | D12: Luz | E12: Luz | F12: Pagado
C13: 550000 | D13: Arriendo | E13: Arriendo | F13: Pagado
C14: 110000 | D14: Cornershop III | E14: Supermercado | F14: Pagado
D15: Gas | E15: Gas
C16: 144056 | D16: Gastos comunes | E16: Gastos comunes | F16: Pagado
C17: 19000 | D17: corner 4

Sheet marzo 21
B1: Para añadir o cambiar categorías, modifica las tablas "Ingresos" y "Gastos" de la hoja "Resumen".
B2: Gastos | D2: =IFERROR(__xludf.DUMMYFUNCTION("GOOGLEFINANCE((""CURRENCY:USDCLP""))+1"),926.24) -> 926.24 | H2: Pagos
M3: Pagado | N3: =SUMIF(F:F,"Pagado",C:C) -> 324806
B4: Fecha | C4: Importe | D4: Descripción | E4: Categoría | F4: Status | H4: Fecha | I4: Importe | J4: Descripción | K4: Categoría | M4: Por pagar | N4: =SUMIF(F5:F34,"Por pagar",C5:C34) -> 0
B5: 44256 | C5: 25990 | D5: Entel | E5: Entel | F5: Pagado | I5: =SUMIF(F:F,"Pagado",C:C) -> 324806 | J5: Javier | K5: Javier | Q5: =P5-O6 -> 0
B6: 44256 | C6: 10700 | D6: Netflix | E6: Netflix | F6: Pagado
B7: 44257 | C7: 6300 | D7: Spotify | E7: Spotify | F7: Pagado
B8: 44261 | C8: 75000 | D8: Cornershop I | E8: Supermercado | F8: Pagado
B9: 44269 | C9: 58000 | D9: Cornershop II | E9: Supermercado | F9: Pagado
B10: 44271 | C10: 4600 | D10: Agua | E10: Agua | F10: Pagado
B11: 44271 | C11: 9216 | D11: Luz | E11: Luz | F11: Pagado
C13: 550000 | D13: Arriendo | E13: Arriendo
D14: Cornershop III | E14: Supermercado
D15: Gas | E15: Gas
C16: 135000 | D16: Gastos comunes | E16: Gastos comunes | F16: Pagado

Sheet febrero 21
B1: Para añadir o cambiar categorías, modifica las tablas "Ingresos" y "Gastos" de la hoja "Resumen".
B2: Gastos | D2: =IFERROR(__xludf.DUMMYFUNCTION("GOOGLEFINANCE((""CURRENCY:USDCLP""))+1"),926.24) -> 926.24 | H2: Pagos
M3: Pagado | N3: =SUMIF(F:F,"Pagado",C:C) -> 845978
B4: Fecha | C4: Importe | D4: Descripción | E4: Categoría | F4: Status | H4: Fecha | I4: Importe | J4: Descripción | K4: Categoría | M4: Por pagar | N4: =SUMIF(F5:F33,"Por pagar",C5:C33) -> 0
B5: 44228 | C5: 6300 | D5: Spotify | E5: Spotify | F5: Pagado | I5: =SUMIF(F:F,"Pagado",C:C) -> 845978 | J5: Javier | K5: Javier | Q5: =P5-O6 -> 0
B6: 44228 | C6: 10700 | D6: Netflix | E6: Netflix | F6: Pagado
B7: 44228 | C7: 25990 | D7: Entel | E7: Entel | F7: Pagado
B8: 44228 | C8: 1470 | D8: Gas | E8: Gas | F8: Pagado
C9: 5780 | D9: Agua | E9: Agua | F9: Pagado
B10: 44229 | C10: 66000 | D10: Cornershop I | E10: Supermercado | F10: Pagado
B11: 44241 | C11: 53814 | D11: Cornershop II | E11: Supermercado | F11: Pagado
D12: Cornershop III | E12: Supermercado
D13: Lavandería | E13: Lavandería
C14: 0 | D14: Nana | E14: Nana
B15: 44250 | C15: 9873 | D15: Luz | E15: Luz | F15: Pagado
B16: 44250 | C16: 116051 | D16: Gastos comunes | E16: Gastos comunes | F16: Pagado
B17: 44250 | C17: 550000 | D17: Arriendo | E17: Arriendo | F17: Pagado

Sheet enero 21
B1: Para añadir o cambiar categorías, modifica las tablas "Ingresos" y "Gastos" de la hoja "Resumen".
B2: Gastos | D2: =IFERROR(__xludf.DUMMYFUNCTION("GOOGLEFINANCE((""CURRENCY:USDCLP""))+1"),926.24) -> 926.24 | H2: Pagos
M3: Pagado | N3: =SUMIF(F:F,"Pagado",C:C) -> 919771
B4: Fecha | C4: Importe | D4: Descripción | E4: Categoría | F4: Status | H4: Fecha | I4: Importe | J4: Descripción | K4: Categoría | M4: Por pagar | N4: =SUMIF(F5:F33,"Por pagar",C5:C33) -> 0
B5: 44197 | C5: 6300 | D5: Spotify | E5: Spotify | F5: Pagado | I5: =SUMIF(F:F,"Pagado",C:C) -> 919771 | J5: Javier | K5: Javier | Q5: =P5-O6 -> 0
B6: 44197 | C6: 10700 | D6: Netflix | E6: Netflix | F6: Pagado
B7: 44197 | C7: 25990 | D7: Entel | E7: Entel | F7: Pagado
C8: 10140 | D8: Agua | E8: Agua | F8: Pagado
B9: 44200 | C9: =58980 -> 58980 | D9: Cornershop I | E9: Supermercado | F9: Pagado
C10: 35000 | D10: Cornershop II | E10: Supermercado | F10: Pagado
C11: 21990 | D11: Cornershop III | E11: Supermercado | F11: Pagado
D12: Gas | E12: Gas
B13: 44218 | C13: 10000 | D13: Lavandería | E13: Lavandería | F13: Pagado
C14: 0 | D14: Nana | E14: Nana
C15: 16191 | D15: Luz | E15: Luz | F15: Pagado
C16: 138100 | D16: Gastos comunes | E16: Gastos comunes | F16: Pagado
C17: 586380 | D17: Arriendo | E17: Arriendo | F17: Pagado
D18: imposiciones | E18: Imposiciones
D19: lavan | E19: Lavandería
D20: Super | E20: Supermercado
D21: nana 2 | E21: Nana
D22: corner | E22: Supermercado

Sheet diciembre 20
B1: Para añadir o cambiar categorías, modifica las tablas "Ingresos" y "Gastos" de la hoja "Resumen".
B2: Gastos | D2: =IFERROR(__xludf.DUMMYFUNCTION("GOOGLEFINANCE((""CURRENCY:USDCLP""))+1"),926.24) -> 926.24 | H2: Pagos
M3: Pagado | N3: =SUMIF(F:F,"Pagado",C:C) -> 871888
B4: Fecha | C4: Importe | D4: Descripción | E4: Categoría | F4: Status | H4: Fecha | I4: Importe | J4: Descripción | K4: Categoría | M4: Por pagar | N4: =SUMIF(F5:F33,"Por pagar",C5:C33) -> 0
C5: 5990 | D5: Spotify | E5: Spotify | F5: Pagado | I5: =SUMIF(F:F,"Pagado",C:C) -> 871888 | J5: Javier | K5: Javier | Q5: =P5-O6 -> 0
C6: 10700 | D6: Netflix | E6: Netflix | F6: Pagado
C7: 25990 | D7: Entel | E7: Entel | F7: Pagado
C8: 5600 | D8: Agua | E8: Agua | F8: Pagado
C9: 2745 | D9: Gas | E9: Gas | F9: Pagado
C10: 20000 | D10: Lavandería | E10: Lavandería | F10: Pagado
C11: =64000+12900 -> 76900 | D11: Cornershop I | E11: Supermercado | F11: Pagado
C12: 0 | D12: Nana | E12: Nana
C13: 11466 | D13: Luz | E13: Luz | F13: Pagado
C14: 126117 | D14: Gastos comunes | E14: Gastos comunes | F14: Pagado
C15: 586380 | D15: Arriendo | E15: Arriendo | F15: Pagado
D16: imposiciones | E16: Imposiciones
D17: Cornershop II | E17: Supermercado
D18: lavan | E18: Lavandería
D19: Cornershop III | E19: Supermercado
D20: Super | E20: Supermercado
D21: nana 2 | E21: Nana
D22: corner | E22: Supermercado

Sheet noviembre 20
B1: Para añadir o cambiar categorías, modifica las tablas "Ingresos" y "Gastos" de la hoja "Resumen".
B2: Gastos | D2: =IFERROR(__xludf.DUMMYFUNCTION("GOOGLEFINANCE((""CURRENCY:USDCLP""))+1"),926.24) -> 926.24 | H2: Pagos
M3: Pagado | N3: =SUMIF(F:F,"Pagado",C:C) -> 898695
B4: Fecha | C4: Importe | D4: Descripción | E4: Categoría | F4: Status | H4: Fecha | I4: Importe | J4: Descripción | K4: Categoría | M4: Por pagar | N4: =SUMIF(F5:F33,"Por pagar",C5:C33) -> 0
B5: 44136 | C5: 5990 | D5: Spotify | E5: Spotify | F5: Pagado | I5: =SUMIF(F:F,"Pagado",C:C) -> 898695 | J5: Javier | K5: Javier | Q5: =P5-O6 -> 0
B6: 44136 | C6: 10700 | D6: Netflix | E6: Netflix | F6: Pagado
B7: 44138 | C7: 25990 | D7: Entel | E7: Entel | F7: Pagado
B8: 44141 | C8: 20000 | D8: Lavandería | E8: Lavandería | F8: Pagado
B9: 44152 | C9: 5600 | D9: Agua | E9: Agua | F9: Pagado
B10: 44155 | C10: 115000 | D10: Cornershop I | E10: Supermercado | F10: Pagado
C11: 0 | D11: Nana | E11: Nana
B12: 44161 | C12: 11500 | D12: Luz | E12: Luz | F12: Pagado
B13: 44160 | C13: 117535 | D13: Gastos comunes | E13: Gastos comunes | F13: Pagado
B14: 44160 | C14: 586380 | D14: Arriendo | E14: Arriendo | F14: Pagado
D15: imposiciones | E15: Imposiciones
D16: Gas | E16: Gas
D17: Cornershop II | E17: Supermercado
D18: lavan | E18: Lavandería
D19: Cornershop III | E19: Supermercado
D20: Super | E20: Supermercado
D21: nana 2 | E21: Nana
D22: corner | E22: Supermercado

Sheet octubre 20
B1: Para añadir o cambiar categorías, modifica las tablas "Ingresos" y "Gastos" de la hoja "Resumen".
B2: Gastos | D2: =IFERROR(__xludf.DUMMYFUNCTION("GOOGLEFINANCE((""CURRENCY:USDCLP""))+1"),926.24) -> 926.24 | H2: Pagos
M3: Pagado | N3: =SUMIF(F:F,"Pagado",C:C) -> 917527
B4: Fecha | C4: Importe | D4: Descripción | E4: Categoría | F4: Status | H4: Fecha | I4: Importe | J4: Descripción | K4: Categoría | M4: Por pagar | N4: =SUMIF(F5:F33,"Por pagar",C5:C33) -> 0
B5: 44105 | C5: 10700 | D5: Netflix | E5: Netflix | F5: Pagado | I5: =SUMIF(F:F,"Pagado",C:C) -> 917527 | J5: Javier | K5: Javier | Q5: =P5-O6 -> 0
B6: 44105 | C6: 5990 | D6: Spotify | E6: Spotify | F6: Pagado
B7: 44105 | C7: =6571*COUNTIF(E:E,"Nana") -> 13142 | D7: imposiciones | E7: Imposiciones | F7: Pagado
B8: 44107 | C8: 25990 | D8: Entel | E8: Entel | F8: Pagado
B9: 44107 | C9: 4176 | D9: Gas | E9: Gas | F9: Pagado
B10: 44121 | C10: 6540 | D10: Agua | E10: Agua | F10: Pagado
B11: 44121 | C11: 25000 | D11: Cornershop II | E11: Supermercado | F11: Pagado
B12: 44128 | C12: 93000 | D12: Cornershop I | E12: Supermercado | F12: Pagado
B13: 44129 | C13: 586380 | D13: Arriendo | E13: Arriendo | F13: Pagado
B14: 44129 | C14: 121609 | D14: Gastos comunes | E14: Gastos comunes | F14: Pagado
C15: 0 | D15: Nana | E15: Nana
D16: Lavandería | E16: Lavandería
D17: lavan | E17: Lavandería
B18: 44135 | C18: 25000 | D18: Cornershop III | E18: Supermercado | F18: Pagado
C19: 0 | D19: Luz | E19: Luz | F19: Pagado
D20: Super | E20: Supermercado
D21: nana 2 | E21: Nana
D22: corner | E22: Supermercado

Sheet Septiembre 20
B1: Para añadir o cambiar categorías, modifica las tablas "Ingresos" y "Gastos" de la hoja "Resumen".
B2: Gastos | D2: =IFERROR(__xludf.DUMMYFUNCTION("GOOGLEFINANCE((""CURRENCY:USDCLP""))+1"),926.24) -> 926.24 | H2: Pagos
M3: Pagado | N3: =SUMIF(F:F,"Pagado",C:C) -> 1110271
B4: Fecha | C4: Importe | D4: Descripción | E4: Categoría | F4: Status | H4: Fecha | I4: Importe | J4: Descripción | K4: Categoría | M4: Por pagar | N4: =SUMIF(F5:F33,"Por pagar",C5:C33) -> 0
B5: 44075 | C5: 10700 | D5: Netflix | E5: Netflix | F5: Pagado | I5: =SUMIF(F:F,"Pagado",C:C) -> 1110271 | J5: Javier | K5: Javier | Q5: =P5-O6 -> 0
B6: 44075 | C6: 25990 | D6: Entel | E6: Entel | F6: Pagado
B7: 44075 | C7: 5990 | D7: Spotify | E7: Spotify | F7: Pagado
B8: 44075 | C8: 40000 | D8: Nana | E8: Nana | F8: Pagado
B9: 44076 | C9: =6571*COUNTIF(E:E,"Nana") -> 13142 | D9: imposiciones | E9: Imposiciones | F9: Pagado
B10: 44079 | C10: 81090 | D10: Cornershop I | E10: Supermercado | F10: Pagado
D11: Gas | E11: Gas
B12: 44102 | C12: 20000 | D12: Lavandería | E12: Lavandería | F12: Pagado
B13: 44091 | C13: 5600 | D13: Agua | E13: Agua | F13: Pagado
D14: lavan | E14: Lavandería
B15: 44081 | C15: 9170 | D15: Cornershop II | E15: Supermercado | F15: Pagado
B16: 44099 | C16: 586380 | D16: Arriendo | E16: Arriendo | F16: Pagado
B17: 44090 | C17: 80000 | D17: Cornershop III | E17: Supermercado | F17: Pagado
C18: 12028 | D18: Luz | E18: Luz | F18: Pagado
D19: Super | E19: Supermercado
B20: 44099 | C20: 140181 | D20: Gastos comunes | E20: Gastos comunes | F20: Pagado
B21: 44101 | C21: 20000 | D21: nana 2 | E21: Nana | F21: Pagado
B22: 44101 | C22: 60000 | D22: corner | E22: Supermercado | F22: Pagado

Sheet Agosto 20
B1: Para añadir o cambiar categorías, modifica las tablas "Ingresos" y "Gastos" de la hoja "Resumen".
B2: Gastos | D2: =IFERROR(__xludf.DUMMYFUNCTION("GOOGLEFINANCE((""CURRENCY:USDCLP""))+1"),926.24) -> 926.24 | H2: Pagos
M3: Pagado | N3: =SUMIF(F:F,"Pagado",C:C) -> 1048950
B4: Fecha | C4: Importe | D4: Descripción | E4: Categoría | F4: Status | H4: Fecha | I4: Importe | J4: Descripción | K4: Categoría | M4: Por pagar | N4: =SUMIF(F5:F33,"Por pagar",C5:C33) -> 0
B5: 44044 | C5: 10700 | D5: Netflix | E5: Netflix | F5: Pagado | I5: =SUMIF(F:F,"Pagado",C:C) -> 1048950 | J5: Javier | K5: Javier | Q5: =P5-O6 -> 0
B6: 44044 | C6: 25990 | D6: Entel | E6: Entel | F6: Pagado
B7: 44044 | C7: =33082-25990 -> 7092 | D7: Gas | E7: Gas | F7: Pagado
B8: 44045 | C8: 5990 | D8: Spotify | E8: Spotify | F8: Pagado
B9: 44046 | C9: =6571*COUNTIF(E:E,"Nana") -> 13142 | D9: imposiciones | E9: Imposiciones | F9: Pagado
B10: 44046 | C10: 20000 | D10: Lavandería | E10: Lavandería | F10: Pagado
B11: 44051 | C11: 46360 | D11: Cornershop I | E11: Supermercado | F11: Pagado
B12: 44058 | C12: 7470 | D12: Agua | E12: Agua | F12: Pagado
B13: 44061 | C13: 9000 | D13: lavan | E13: Lavandería | F13: Pagado
B14: 44062 | C14: 12550 | D14: Cornershop II | E14: Supermercado | F14: Pagado
C15: 60000 | D15: Nana | E15: Nana | F15: Pagado
C16: 586380 | D16: Arriendo | E16: Arriendo | F16: Pagado
C17: 61608 | D17: Cornershop III | E17: Supermercado | F17: Pagado
C18: 16119 | D18: Luz | E18: Luz | F18: Pagado
D19: Super | E19: Supermercado
C20: 166549 | D20: Gastos comunes | E20: Gastos comunes | F20: Pagado
D21: nana 2 | E21: Nana
D22: corner | E22: Supermercado

Sheet Julio 20
B1: Para añadir o cambiar categorías, modifica las tablas "Ingresos" y "Gastos" de la hoja "Resumen".
B2: Gastos | D2: =IFERROR(__xludf.DUMMYFUNCTION("GOOGLEFINANCE((""CURRENCY:USDCLP""))+1"),926.24) -> 926.24 | H2: Pagos
M3: Pagado | N3: =SUMIF(F:F,"Pagado",C:C) -> 1072498
B4: Fecha | C4: Importe | D4: Descripción | E4: Categoría | F4: Status | H4: Fecha | I4: Importe | J4: Descripción | K4: Categoría | M4: Por pagar | N4: =SUMIF(F5:F33,"Por pagar",C5:C33) -> 0
B5: 44013 | C5: 5990 | D5: Spotify | E5: Spotify | F5: Pagado | I5: =SUMIF(F:F,"Pagado",C:C) -> 1072498 | J5: Javier | K5: Javier | Q5: =P5-O6 -> 0
B6: 44013 | C6: 8990 | D6: Netflix | E6: Netflix | F6: Pagado
B7: 44013 | C7: =6571*COUNTIF(E:E,"Nana") -> 13142 | D7: imposiciones | E7: Imposiciones | F7: Pagado
B8: 44016 | C8: 20000 | D8: Lavandería | E8: Lavandería | F8: Pagado
B9: 44020 | C9: 25990 | D9: Entel | E9: Entel | F9: Pagado
B10: 44023 | C10: 49000 | D10: Cornershop I | E10: Supermercado | F10: Pagado
B11: 44027 | C11: =42000-6500 -> 35500 | D11: Cornershop II | E11: Supermercado | F11: Pagado
B12: 44029 | C12: 3070 | D12: Agua | E12: Agua | F12: Pagado
C13: 60000 | D13: Nana | E13: Nana | F13: Pagado
B14: 44036 | C14: 586380 | D14: Arriendo | E14: Arriendo | F14: Pagado
B15: 44032 | C15: 58000 | D15: Cornershop III | E15: Supermercado | F15: Pagado
C16: 15128 | D16: Luz | E16: Luz | F16: Pagado
D17: Super | E17: Supermercado
B18: 44036 | C18: 146308 | D18: Gastos comunes | E18: Gastos comunes | F18: Pagado
D19: Gas | E19: Gas
D20: nana 2 | E20: Nana
C21: 45000 | D21: corner | E21: Supermercado | F21: Pagado

Sheet Junio 20
B1: Para añadir o cambiar categorías, modifica las tablas "Ingresos" y "Gastos" de la hoja "Resumen".
B2: Gastos | D2: =IFERROR(__xludf.DUMMYFUNCTION("GOOGLEFINANCE((""CURRENCY:USDCLP""))+1"),926.24) -> 926.24 | H2: Pagos
M3: Pagado | N3: =SUMIF(F:F,"Pagado",C:C) -> 1069291
B4: Fecha | C4: Importe | D4: Descripción | E4: Categoría | F4: Status | H4: Fecha | I4: Importe | J4: Descripción | K4: Categoría | M4: Por pagar | N4: =SUMIF(F5:F33,"Por pagar",C5:C33) -> 0
B5: 43983 | C5: 5990 | D5: Spotify | E5: Spotify | F5: Pagado | I5: =SUMIF(F:F,"Pagado",C:C) -> 1069291 | J5: Javier | K5: Javier | Q5: =P5-O6 -> 0
B6: 43983 | C6: 8990 | D6: Netflix | E6: Netflix | F6: Pagado
B7: 43983 | C7: 20000 | D7: Lavandería | E7: Lavandería | F7: Pagado
B8: 43983 | C8: 89000 | D8: Cornershop I | E8: Supermercado | F8: Pagado
B9: 43991 | C9: =6571*COUNTIF(E:E,"Nana") -> 13142 | D9: imposiciones | E9: Imposiciones | F9: Pagado
B10: 43996 | C10: 43113 | D10: Cornershop II | E10: Supermercado | F10: Pagado
B11: 43997 | C11: 6400 | D11: Agua | E11: Agua | F11: Pagado
B12: 44002 | C12: 21000 | D12: Cornershop III | E12: Supermercado | F12: Pagado
B13: 44008 | C13: 14385 | D13: Luz | E13: Luz | F13: Pagado
C14: 60000 | D14: Nana | E14: Nana | F14: Pagado
C15: 80000 | D15: Super | E15: Supermercado | F15: Pagado
B16: 44005 | C16: 120891 | D16: Gastos comunes | E16: Gastos comunes | F16: Pagado
B17: 44007 | C17: 586380 | D17: Arriendo | E17: Arriendo | F17: Pagado
D18: Gas | E18: Gas
C19: 22124 | D19: Entel | E19: Entel
D20: nana 2 | E20: Nana

Sheet Mayo 20
B1: Para añadir o cambiar categorías, modifica las tablas "Ingresos" y "Gastos" de la hoja "Resumen".
